Workbook

Sheet Start Set
A1: Title | B1: Authors | C1: Year | D1: Venue
A2: Non-Intrusive Distributed Tracing of Wireless IoT Devices with the FlockLab 2 Testbed | B2: Trub, Roman and Da Forno, Reto and Daschinger, Lukas and Biri, Andreas and Beutel, Jan and Thiele, Lothar | C2: 2021 | D2: ACM Transactions on Internet of Things, Volume 3, Issue 1
A3: Distributed Graph Routing and Scheduling for Industrial Wireless Sensor-Actuator Networks | B3: Shi, Junyang and Sha, Mo and Yang, Zhicheng | C3: 2019 | D3: IEEE/ACM Transactions on Networking (TON), Volume 27, Issue 4
A4: Ensuring End-to-End Dependability Requirements in Cloud-based Bluetooth Low Energy Applications | B4: Sp\"{o}rk, Michael and Schu\ss{}, Markus and Boano, Carlo Alberto and R\"{o}mer, Kay | C4: 2021 | D4: Proceedings of the 2021 International Conference on Embedded Wireless Systems and Networks
A5: Unobtrusive, Accurate, and Live Measurements of Network Latency and Reliability for Time-Critical Internet of Things | B5: Bhimavarapu K. and Pang Z. and Dobrijevic O. and Wiatr P. | C5: 2022 | D5: IEEE Internet of Things Magazine
A6: On the Performance of Commodity Hardware for Low Latency and Low Jitter Packet Processing | B6: Stylianopoulos, Charalampos and Almgren, Magnus and Landsiedel, Olaf and Papatriantafilou, Marina and Neish, Trevor and Gillander, Linus and Johansson, Bengt and Bonnier, Staffan | C6: 2020 | D6: DEBS 2020 - Proceedings of the 14th ACM International Conference on Distributed and Event-Based Systems
A7: Fog network task scheduling for IoT applications | B7: Zhang, Chongchong and Shen, Fei and Jin, Jiong and Yang, Yang | C7: 2020 | D7: OpenAccess Series in Informatics
A8: A software architecture for the industrial internet of things - a conceptual model | B8: Ungurean, Ioan and Gaitan, Nicoleta Cristina | C8: 2020 | D8: Sensors (Switzerland)
A9: Analysis of joint scheduling and power control for predictable URLLC in industrial wireless networks | B9: Wang, Ling and Zhang, Hongwei | C9: 2019 | D9: Proceedings - IEEE International Conference on Industrial Internet Cloud, ICII 2019
A10: PrioMQTT: A prioritized version of the MQTT protocol | B10: Patti, Gaetano and Leonardi, Luca and Testa, Giuseppe and Lo Bello, Lucia | C10: 2024 | D10: Computer Communications
A11: RT-BLE: Real-time Multi-Connection Scheduling for Bluetooth Low Energy | B11: Li, Yeming and Lv, Jiamei and Li, Borui and Dong, Wei | C11: 2023 | D11: Proceedings - IEEE INFOCOM
A12: Towards Multi-channel GTS Allocation in Visible Light Communication | B12: Kurunathan, Harrison and Samano-Robles, Ramiro and Gaitan, Miguel Gutierrez and Indhumathi, R. and Tovar, Eduardo | C12: 2023 | D12: 2023 South American Conference on Visible Light Communications, SACVLC 2023
A13: Transmission Early-Stopping Scheme for Anti-Jamming Over Delay-Sensitive IoT Applications | B13: Halloush, RD | C13: 2019 | D13: IEEE INTERNET OF THINGS JOURNAL
... A39: End-to-end response time analysis for RT-MQTT: Trajectory approach versus holistic approach | B39: E. Shahri, P. Pedreiras, L. Almeida | C39: 2023 | D39: 19th International Conference on Factory Communication Systems, WFCS

Sheet Iteration 1 - Forward
A1: Title | B1: Authors | C1: Year | D1: Venue | E1: D | F1: DS | G1: EC1 | H1: EC2-4 | I1: EC5 | J1: EC6 | K1: IC1
A2: Analysis of simulators for designing network architecture in Wireless Sensor Network applications. | B2: MG Periwal, J Deere | C2: 2025 | D2: saeindia.org | E2: =--(ROW(A2)<>MATCH(A2,$A:$A,0)) -> 0 | F2: =IF(COUNTIF('Start Set'!A:A, A2) > 0, 1, 0) -> 0 | H2: 1
A3: Automatisierte Integration von IoT-Geräten in IoT-Umgebungen | B3: M Reichel | C3: 2019 | D3: elib.uni-stuttgart.de | E3: =--(ROW(A3)<>MATCH(A3,$A:$A,0)) -> 0 | F3: =IF(COUNTIF('Start Set'!A:A, A3) > 0, 1, 0) -> 0 | G3: 1 | H3: 1
A4: Verbesserung von Robustheit und Ausfallsicherheit bei der Datenverarbeitung in IoT-Umgebungen | B4: T Schubert | C4: 2020 | D4: elib.uni-stuttgart.de | E4: =--(ROW(A4)<>MATCH(A4,$A:$A,0)) -> 0 | F4: =IF(COUNTIF('Start Set'!A:A, A4) > 0, 1, 0) -> 0 | H4: 1
A5: Studio e sviluppo di sistemi di manutenzione predittiva basati su industrial IoT | B5: G Temperini | C5: 2020 | D5: univpm.it | E5: =--(ROW(A5)<>MATCH(A5,$A:$A,0)) -> 0 | F5: =IF(COUNTIF('Start Set'!A:A, A5) > 0, 1, 0) -> 0 | H5: 1
A6: Physical-layer Jammer Detection in Multi-hop IoT Networks | B6: M Bag-Mohammadi | C6: 2020 | D6: durham-repository.worktribe.com | E6: =--(ROW(A6)<>MATCH(A6,$A:$A,0)) -> 0 | F6: =IF(COUNTIF('Start Set'!A:A, A6) > 0, 1, 0) -> 0 | H6: 1
A7: E2E-Aware Multi-Service Radio Resource Management for 5G New Radio: Radio Access and Resource Management Solutions | B7: AAMAA Esswie | C7: 2020 | D7: Aalborg University (aau.dk) | E7: =--(ROW(A7)<>MATCH(A7,$A:$A,0)) -> 0 | F7: =IF(COUNTIF('Start Set'!A:A, A7) > 0, 1, 0) -> 0 | H7: 1
A8: Intelligent and Low Overhead Network Synchronization over Large-Scale Industrial Internet of Things Systems | B8: P Jia | C8: 2020 | D8: ProQuest | E8: =--(ROW(A8)<>MATCH(A8,$A:$A,0)) -> 0 | F8: =IF(COUNTIF('Start Set'!A:A, A8) > 0, 1, 0) -> 0 | H8: 1
A9: Improving Response Time of Task Offloading by Random Forest Extra-Trees and Adaboost Classifiers in Mobile Fog Computing | B9: E Darbanian, D Rahbari, R Ghanizadeh… | C9: 2020 | D9: Jordanian Journal of … | E9: =--(ROW(A9)<>MATCH(A9,$A:$A,0)) -> 0 | F9: =IF(COUNTIF('Start Set'!A:A, A9) > 0, 1, 0) -> 0 | H9: 1
A10: Comparative Analysis of NoSQL Database's Activities and Scalability Investigation With Library Introspection | B10: CH Seo, B Tak | C10: 2020 | D10: Journal of The Korea Society of … | E10: =--(ROW(A10)<>MATCH(A10,$A:$A,0)) -> 0 | F10: =IF(COUNTIF('Start Set'!A:A, A10) > 0, 1, 0) -> 0 | H10: 1
A11: Real-Time Control Over Wireless Networks | B11: VP Modekurthy | C11: 2020 | D11: ProQuest (Book) | E11: =--(ROW(A11)<>MATCH(A11,$A:$A,0)) -> 0 | F11: =IF(COUNTIF('Start Set'!A:A, A11) > 0, 1, 0) -> 0 | H11: 1
A12: NGHIÊN CỨU GIẢI PHÁP ĐIỀU KHIỂN TRUY NHẬP PHƯƠNG TIỆN ƯU TIÊN TRÊN CỬA SỔ CẠNH TRANH CHO MẠNG CẢM BIẾN KHÔNG DÂY IoT ĐA SỰ KIỆN … | B12: NTT Hằng, VT Vinh | C12: 2021 | D12: Journal of Science and Technology on … | E12: =--(ROW(A12)<>MATCH(A12,$A:$A,0)) -> 0 | F12: =IF(COUNTIF('Start Set'!A:A, A12) > 0, 1, 0) -> 0 | H12: 1
A13: RETRACTED CHAPTER: Optimization of the Overlap Shortest-Path Routing for TSCH Networks | B13: J Caceres, MV Garcia | C13: 2021 | D13: Sustainable Systems: Selected Papers of WorldS4 … | E13: =--(ROW(A13)<>MATCH(A13,$A:$A,0)) -> 0 | F13: =IF(COUNTIF('Start Set'!A:A, A13) > 0, 1, 0) -> 0 | H13: 1
A14: Criterios de ubicación de algoritmos de inteligencia computacional en la web de las cosas: Revisión sistemática de la literatura | B14: LCER Parra, MÁN Zambrano… | C14: 2021 | D14: Innovación en … | E14: =--(ROW(A14)<>MATCH(A14,$A:$A,0)) -> 0 | F14: =IF(COUNTIF('Start Set'!A:A, A14) > 0, 1, 0) -> 0 | H14: 1
A15: Metode de planificare timp real pentru sisteme distribuite cu niveluri mixte de criticalitate | B15: EA Capotă, MV Micea | C15: 2021 | D15: UPT | E15: =--(ROW(A15)<>MATCH(A15,$A:$A,0)) -> 0 | F15: =IF(COUNTIF('Start Set'!A:A, A15) > 0, 1, 0) -> 0 | H15: 1
... A20: ХМАРНА АРХІТЕКТУРА ПЕРЕДАЧІ ДАНИХ… | B20: ОС Омельченко, НМ Луцька | C20: 2021 | D20: EBSCOhost | E20: =--(ROW(A20)<>MATCH(A20,$A:$A,0)) -> 0 | F20: =IF(COUNTIF('Start Set'!A:A, A20) > 0, 1, 0) -> 0 | H20: 1
A21: A survey of 802.15. 4 TSCH schedulers for a standardized industrial Internet of Things | B21: AR Urke, Ø Kure, K Øvsthus | C21: 2021 | D21: Sensors | E21: 1 | F21: =IF(COUNTIF('Start Set'!A:A, A21) > 0, 1, 0) -> 0 | H21: 1
A22: EDF Scheduling and Minimal-Overlap Shortest-Path Routing for Real-Time TSCH Networks | B22: M Gutiérrez Gaitán, L Almeida, PM Santos… | C22: 2021 | D22: recipp.ipp.pt | E22: =--(ROW(A22)<>MATCH(A22,$A:$A,0)) -> 0 | F22: =IF(COUNTIF('Start Set'!A:A, A22) > 0, 1, 0) -> 0 | H22: 1
A23: BAMSim Simulator | B23: RF Reale, JSB Martins | C23: 2021 | D23: arXiv preprint arXiv:2102.00273 | E23: =--(ROW(A23)<>MATCH(A23,$A:$A,0)) -> 0 | F23: =IF(COUNTIF('Start Set'!A:A, A23) > 0, 1, 0) -> 0 | H23: 1
A24: T2AS: Topology/Traffic Aware Scheduling to Optimize the End-to-end Delay in IEEE802. 154e-TSCH Networks | B24: E Mozaffari Ahrar, M Nassiri | C24: 2021 | D24: مجله مهندسی برق دانشگاه تبریز | E24: =--(ROW(A24)<>MATCH(A24,$A:$A,0)) -> 0 | F24: =IF(COUNTIF('Start Set'!A:A, A24) > 0, 1, 0) -> 0 | H24: 1
A25: AIoT for achieving sustainable development goals | B25: JM Corchado Rodríguez | C25: 2021 | E25: =--(ROW(A25)<>MATCH(A25,$A:$A,0)) -> 0 | F25: =IF(COUNTIF('Start Set'!A:A, A25) > 0, 1, 0) -> 0 | H25: 1
A26: Last mile delivery | B26: JM Corchado Rodríguez | C26: 2021 | E26: =--(ROW(A26)<>MATCH(A26,$A:$A,0)) -> 0 | F26: =IF(COUNTIF('Start Set'!A:A, A26) > 0, 1, 0) -> 0 | H26: 1
A27: IoT-Fog architectures in smart city applications: A survey | B27: SS Hajam, SA Sofi | C27: 2021 | D27: China Communications | E27: =--(ROW(A27)<>MATCH(A27,$A:$A,0)) -> 0 | F27: =IF(COUNTIF('Start Set'!A:A, A27) > 0, 1, 0) -> 0 | H27: 1
A28: Distributed Signal Processing in Digital Substations: Integrating High Sampling Rate Measurements at the Process-Level | B28: F Hohn | C28: 2021 | D28: diva-portal.org | E28: =--(ROW(A28)<>MATCH(A28,$A:$A,0)) -> 0 | F28: =IF(COUNTIF('Start Set'!A:A, A28) > 0, 1, 0) -> 0 | H28: 1
A29: Predictable Multiprocessor Platform for Safety-Critical Real-Time Systems | B29: PA Sigurðsson | C29: 2021 | D29: diva-portal.org | E29: =--(ROW(A29)<>MATCH(A29,$A:$A,0)) -> 0 | F29: =IF(COUNTIF('Start Set'!A:A, A29) > 0, 1, 0) -> 0 | H29: 1
A30: Intelligent aquaculture environment monitoring system based on LoRa communication technology. | B30: H Cai, F Li, P Lv, L Ran, L Zou | C30: 2021 | D30: INMATEH-Agricultural Engineering | E30: =--(ROW(A30)<>MATCH(A30,$A:$A,0)) -> 0 | F30: =IF(COUNTIF('Start Set'!A:A, A30) > 0, 1, 0) -> 0 | H30: 1
A31: Analysis of freertos overheads on periodic tasks | B31: BD Miranda, RS de Oliveira… | C31: 2021 | D31: … em Desempenho de … | E31: =--(ROW(A31)<>MATCH(A31,$A:$A,0)) -> 0 | F31: =IF(COUNTIF('Start Set'!A:A, A31) > 0, 1, 0) -> 0 | H31: 1
A32: Research on joint computation offloading and resource allocation strategy for mobile edge computing | B32: D Huang, YU Liyang, C Jue… | C32: 2021 | D32: Journal of East China … | E32: =--(ROW(A32)<>MATCH(A32,$A:$A,0)) -> 0 | F32: =IF(COUNTIF('Start Set'!A:A, A32) > 0, 1, 0) -> 0 | H32: 1
A33: A study on the VLC security at the physical layer for two indoor scenarios | B33: S Riurean | C33: 2021 | D33: MATEC Web of Conferences | E33: =--(ROW(A33)<>MATCH(A33,$A:$A,0)) -> 0 | F33: =IF(COUNTIF('Start Set'!A:A, A33) > 0, 1, 0) -> 0 | H33: 1
A34: Analysis and design of control plane functions for industrial internet of things | B34: D Fanucchi | C34: 2021 | D34: opus.bibliothek.uni-augsburg.de | E34: =--(ROW(A34)<>MATCH(A34,$A:$A,0)) -> 0 | F34: =IF(COUNTIF('Start Set'!A:A, A34) > 0, 1, 0) -> 0 | H34: 1
A35: A 3-hop Topology With TSCH Scheduling in Small and Dense WSNs or In-Vehicles WSNs | B35: RG Goh | C35: 2021 | D35: ProQuest | E35: =--(ROW(A35)<>MATCH(A35,$A:$A,0)) -> 0 | F35: =IF(COUNTIF('Start Set'!A:A, A35) > 0, 1, 0) -> 0 | H35: 1
A36: Long-Term Stable Communication in Centrally Scheduled Low-Power Wireless Networks | B36: O Harms | C36: 2021 | D36: ProQuest | E36: =--(ROW(A36)<>MATCH(A36,$A:$A,0)) -> 0 | F36: =IF(COUNTIF('Start Set'!A:A, A36) > 0, 1, 0) -> 0 | H36: 1
A37: Master Thesis Computer Science | B37: N Traffic | C37: 2022 | D37: hs-esslingen.de | E37: =--(ROW(A37)<>MATCH(A37,$A:$A,0)) -> 0 | F37: =IF(COUNTIF('Start Set'!A:A, A37) > 0, 1, 0) -> 0 | H37: 1
A38: 面向海洋节能边缘计算的任务卸载研究 | B38: 蒋欣秀, 常俊, 李波, 杨志军, 丁洪伟 | C38: 2022 | D38: 计算机工程与科学 | E38: =--(ROW(A38)<>MATCH(A38,$A:$A,0)) -> 0 | F38: =IF(COUNTIF('Start Set'!A:A, A38) > 0, 1, 0) -> 0 | H38: 1
... A50: Oakestra white paper: An orchestrator for edge computing | B50: G Bartolomeo, M Yosofie, S Bäurle… | C50: 2022 | D50: arXiv preprint | E50: =--(ROW(A50)<>MATCH(A50,$A:$A,0)) -> 0 | F50: =IF(COUNTIF('Start Set'!A:A, A50) > 0, 1, 0) -> 0 | H50: 1
A51: Developing educational curricula for digital transformation V2 | B51: JM Corchado | C51: 2022 | E51: =--(ROW(A51)<>MATCH(A51,$A:$A,0)) -> 0 | F51: =IF(COUNTIF('Start Set'!A:A, A51) > 0, 1, 0) -> 0 | H51: 1
A52: Blockchain for smart manufacturing systems: a survey | B52: Z Song, J Zhu | C52: 2022 | D52: Chinese Management Studies | E52: =--(ROW(A52)<>MATCH(A52,$A:$A,0)) -> 0 | F52: =IF(COUNTIF('Start Set'!A:A, A52) > 0, 1, 0) -> 0 | H52: 1
A53: A relative torsional vibration monitoring method for intelligent ships and associated error analysis | B53: AN Yunsheng, C Huang, Z Wu, Q Li, J Li… | C53: 2022 | D53: Insight-Non … | E53: =--(ROW(A53)<>MATCH(A53,$A:$A,0)) -> 0 | F53: =IF(COUNTIF('Start Set'!A:A, A53) > 0, 1, 0) -> 0 | H53: 1
A54: DOCUMENTS & INFORMATIONS | B54: A No | C54: 2022 | D54: transact-ecsel.eu / HeinOnline | E54: =--(ROW(A54)<>MATCH(A54,$A:$A,0)) -> 0 | F54: =IF(COUNTIF('Start Set'!A:A, A54) > 0, 1, 0) -> 0 | H54: 1
A55: Multi-criteria decision support for energy-efficient IoT edge computing offloading | B55: A Jaddoa | C55: 2022 | D55: University of Greenwich | E55: =--(ROW(A55)<>MATCH(A55,$A:$A,0)) -> 0 | F55: =IF(COUNTIF('Start Set'!A:A, A55) > 0, 1, 0) -> 0 | H55: 1
A56: Toward Intelligent Management The of Service Case of Quality a Low Rate in the WPAN | B56: G Le Gall, GZ Papadopoulos… | C56: 2022 | D56: Books (Google) | E56: =--(ROW(A56)<>MATCH(A56,$A:$A,0)) -> 0 | F56: =IF(COUNTIF('Start Set'!A:A, A56) > 0, 1, 0) -> 0 | H56: 1
A57: RAHEC: An Edge Computing Reference Architecture for Healthcare | B57: L de Geus | C57: 2022 | D57: linwang.info | E57: =--(ROW(A57)<>MATCH(A57,$A:$A,0)) -> 0 | F57: =IF(COUNTIF('Start Set'!A:A, A57) > 0, 1, 0) -> 0 | H57: 1
A58: Poster: Towards a Federated Testbed Infrastructure for Geographically-Distributed Low-Power Wireless Systems. | B58: M Schuß, CA Boano, M Baddeley, M Prakash… | C58: 2022 | D58: michaelbaddeley.com | E58: =--(ROW(A58)<>MATCH(A58,$A:$A,0)) -> 0 | F58: =IF(COUNTIF('Start Set'!A:A, A58) > 0, 1, 0) -> 0 | H58: 1
A59: Dynamic Task Offloading for Latency Minimization in Iot Edge-Cloud Environments | B59: H Ku | C59: 2022 | D59: ProQuest | E59: =--(ROW(A59)<>MATCH(A59,$A:$A,0)) -> 1 | F59: =IF(COUNTIF('Start Set'!A:A, A59) > 0, 1, 0) -> 0 | H59: 1
A60: Optimizing task offloading for mobile edge cloud systems | B60: Z Chen | C60: 2022 | D60: Warwick | E60: =--(ROW(A60)<>MATCH(A60,$A:$A,0)) -> 0 | F60: =IF(COUNTIF('Start Set'!A:A, A60) > 0, 1, 0) -> 0 | H60: 1
A61: Анализ возможности выполнения требований индустриального интернета вещей методами Wi-Fi 6 | B61: АЮ Карамышев, МВ Любогощев, АИ Ляхов… | C61: 2023 | D61: Информационные … | E61: =--(ROW(A61)<>MATCH(A61,$A:$A,0)) -> 0 | F61: =IF(COUNTIF('Start Set'!A:A, A61) > 0, 1, 0) -> 0 | H61: 1
A62: 突发流量自适应的 6TiSCH 网络分布式 PID 调度 | B62: 张焱， 陈峰， 谢泽堃， 蔡有鑫， 韩延… | C62: 2023 | D62: 电子测量与仪器 … | E62: =--(ROW(A62)<>MATCH(A62,$A:$A,0)) -> 0 | F62: =IF(COUNTIF('Start Set'!A:A, A62) > 0, 1, 0) -> 0 | H62: 1
A63: Uso de SDN para Gestão Holística de Comunicações em CPPS | B63: E Shahri | C63: 2023 | D63: ProQuest | E63: =--(ROW(A63)<>MATCH(A63,$A:$A,0)) -> 0 | F63: =IF(COUNTIF('Start Set'!A:A, A63) > 0, 1, 0) -> 0 | H63: 1
... A78: Understanding concurrent transmissions: The impact of carrier frequency offset and RF interference on physical layer performance | B78: M Baddeley, CA Boano, A Escobar-Molero… | C78: 2023 | D78: ACM Transactions on … | E78: =--(ROW(A78)<>MATCH(A78,$A:$A,0)) -> 0 | F78: =IF(COUNTIF('Start Set'!A:A, A78) > 0, 1, 0) -> 0 | H78: 1
A79: URLLC and eMBB in 5G Industrial IoT: A Survey | B79: B Sharfeen, S Jangsher, A Al-Dweik | C79: 2023 | D79: Authorea Preprints | E79: 1 | F79: =IF(COUNTIF('Start Set'!A:A, A79) > 0, 1, 0) -> 0 | H79: 1
A80: Distributed Precoding For Decentralized Estimation In Coexisting IoT Networks | B80: N Garg, T Ratnarajah, VM Vakamulla… | C80: 2023 | D80: Authorea Preprints (TechRxiv) | E80: =--(ROW(A80)<>MATCH(A80,$A:$A,0)) -> 0 | F80: =IF(COUNTIF('Start Set'!A:A, A80) > 0, 1, 0) -> 0 | H80: 1
A81: Resource-Aware Time-Critical Application Placement in the Computing Continuum | B81: ZN Samani | C81: 2023 | D81: Doctoral Thesis (AAU Austria) | E81: =--(ROW(A81)<>MATCH(A81,$A:$A,0)) -> 0 | F81: =IF(COUNTIF('Start Set'!A:A, A81) > 0, 1, 0) -> 0 | H81: 1
A82: MTProto Algorithm in Smart Home Remote Control Using Robot Telegram | B82: S Daneshian, A Yousefi, MM ShirMohammadi | C82: 2023 | D82: academia.edu | E82: =--(ROW(A82)<>MATCH(A82,$A:$A,0)) -> 0 | F82: =IF(COUNTIF('Start Set'!A:A, A82) > 0, 1, 0) -> 0 | H82: 1
A83: Offline Task Scheduling in a Three-layer Edge-Cloud Architecture | B83: A Mahjoubi | C83: 2023 | D83: DiVA | E83: =--(ROW(A83)<>MATCH(A83,$A:$A,0)) -> 0 | F83: =IF(COUNTIF('Start Set'!A:A, A83) > 0, 1, 0) -> 0 | H83: 1
A84: Formal Verification of Peripheral Memory Isolation | B84: J Haglund | C84: 2023 | D84: diva-portal.org | E84: =--(ROW(A84)<>MATCH(A84,$A:$A,0)) -> 0 | F84: =IF(COUNTIF('Start Set'!A:A, A84) > 0, 1, 0) -> 0 | H84: 1
A85: MODELING NETWORKS OF QUEUES | B85: A Feta, A Stefanov | C85: 2023 | D85: ijtns.ibupress.com | E85: =--(ROW(A85)<>MATCH(A85,$A:$A,0)) -> 0 | F85: =IF(COUNTIF('Start Set'!A:A, A85) > 0, 1, 0) -> 0 | H85: 1
A86: Tiny Machine Learning Environment: Enabling Intelligence on Constrained Devices | B86: F Sakr | C86: 2023 | D86: tesidottorato.depositolegale.it | E86: =--(ROW(A86)<>MATCH(A86,$A:$A,0)) -> 0 | F86: =IF(COUNTIF('Start Set'!A:A, A86) > 0, 1, 0) -> 0 | H86: 1
A87: Task-oriented joint design of communication and computing for Internet of Skills | B87: B Kizilkaya | C87: 2023 | D87: theses.gla.ac.uk | E87: =--(ROW(A87)<>MATCH(A87,$A:$A,0)) -> 0 | F87: =IF(COUNTIF('Start Set'!A:A, A87) > 0, 1, 0) -> 0 | H87: 1
A88: On-board computers of tware development for PocketQubes | B88: N Rius Fortuny | C88: 2023 | D88: Universitat Politècnica de Catalunya (Citation) | E88: =--(ROW(A88)<>MATCH(A88,$A:$A,0)) -> 0 | F88: =IF(COUNTIF('Start Set'!A:A, A88) > 0, 1, 0) -> 0 | H88: 1
A89: A COMPUTATION OFFLOADING FOR IOT OF EDGE COMPUTING: A REINFORCEMENT LEARNING APPROACH BASED ON DDPG | B89: FNA AL-ZUBAIDI | C89: 2023 | D89: CITATION | E89: =--(ROW(A89)<>MATCH(A89,$A:$A,0)) -> 0 | F89: =IF(COUNTIF('Start Set'!A:A, A89) > 0, 1, 0) -> 0 | H89: 1
A90: Decision making for IoT task offload scheduling with edge computing: a survey | B90: D Wang, KBA Aakar, B Isyaku | C90: 2023 | D90: CITATION | E90: =--(ROW(A90)<>MATCH(A90,$A:$A,0)) -> 0 | F90: =IF(COUNTIF('Start Set'!A:A, A90) > 0, 1, 0) -> 0 | H90: 1
A91: Automated data validation in model-driven IoT applications | B91: C Müller | C91: 2023 | D91: elib.uni-stuttgart.de | E91: =--(ROW(A91)<>MATCH(A91,$A:$A,0)) -> 0 | F91: =IF(COUNTIF('Start Set'!A:A, A91) > 0, 1, 0) -> 0 | H91: 1
... A161: On Feasibility of Coordinated Time-Delay and False Data Injection Attacks on Cyber-Physical Systems | B161: Q Wei | C161: 2021 | D161: Citation | E161: =--(ROW(A161)<>MATCH(A161,$A:$A,0)) -> 0 | F161: =IF(COUNTIF('Start Set'!A:A, A161) > 0, 1, 0) -> 0 | H161: 1
A162: Sustainable Energy Technologies and Assessments | B162: A Maulik, D Das | C162: 2017 | D162: ResearchGate | E162: =--(ROW(A162)<>MATCH(A162,$A:$A,0)) -> 0 | F162: =IF(COUNTIF('Start Set'!A:A, A162) > 0, 1, 0) -> 0 | G162: 1 | J162: 1
A163: Distributed Rate-Control and Delay-Guaranteed Scheduling in MR-MC Wireless Mesh Networks | B163: L Li, X Zhao, S Geng, Y Zhang | C163: 2019 | D163: Sensors | E163: =--(ROW(A163)<>MATCH(A163,$A:$A,0)) -> 0 | F163: =IF(COUNTIF('Start Set'!A:A, A163) > 0, 1, 0) -> 0 | G163: 1 | J163: 1
A164: Optimal number of message transmissions for probabilistic guarantee of latency in the IoT | B164: P Minet, Y Tanaka | C164: 2019 | D164: Sensors | E164: =--(ROW(A164)<>MATCH(A164,$A:$A,0)) -> 0 | F164: =IF(COUNTIF('Start Set'!A:A, A164) > 0, 1, 0) -> 0 | G164: 1 | J164: 1
A165: Network fault tolerance by means of diverse physical layers | B165: PG Peón, W Steiner, E Uhlemann | C165: 2020 | D165: 25th IEEE … | E165: =--(ROW(A165)<>MATCH(A165,$A:$A,0)) -> 0 | F165: =IF(COUNTIF('Start Set'!A:A, A165) > 0, 1, 0) -> 0 | J165: 1
A166: Latency minimization in a fuzzy-based mobile edge orchestrator for IoT applications | B166: VD Nguyen, TT Khanh, TZ Oo, NH Tran… | C166: 2020 | D166: IEEE … | E166: =--(ROW(A166)<>MATCH(A166,$A:$A,0)) -> 0 | F166: =IF(COUNTIF('Start Set'!A:A, A166) > 0, 1, 0) -> 0 | J166: 1
A167: Towards ambient backscatter as an anti-jamming solution for IoT devices | B167: W Jang, W Lee | C167: 2020 | D167: IEEE INFOCOM | E167: =--(ROW(A167)<>MATCH(A167,$A:$A,0)) -> 0 | F167: =IF(COUNTIF('Start Set'!A:A, A167) > 0, 1, 0) -> 0 | J167: 1
A168: A response-aware traffic offloading scheme using regression machine learning for user-centric large-scale internet of things | B168: G Manogaran, G Srivastava, BA Muthu… | C168: 2020 | D168: IEEE Internet of … | E168: =--(ROW(A168)<>MATCH(A168,$A:$A,0)) -> 0 | F168: =IF(COUNTIF('Start Set'!A:A, A168) > 0, 1, 0) -> 0 | J168: 1
A169: Digital-twin-enabled intelligent distributed clock synchronization in industrial IoT systems | B169: P Jia, X Wang, X Shen | C169: 2020 | D169: IEEE Internet of Things Journal | E169: =--(ROW(A169)<>MATCH(A169,$A:$A,0)) -> 0 | F169: =IF(COUNTIF('Start Set'!A:A, A169) > 0, 1, 0) -> 0 | J169: 1
A170: Analysis and rectification of the asynchronous sampling effect in the pulse-position modulation systems | B170: K Yan, S Cheng, HC Wu, H Xiao… | C170: 2020 | D170: IEEE Sensors … | E170: =--(ROW(A170)<>MATCH(A170,$A:$A,0)) -> 0 | F170: =IF(COUNTIF('Start Set'!A:A, A170) > 0, 1, 0) -> 0 | J170: 1
A171: Intelligent signal classification in industrial distributed wireless sensor networks based industrial internet of things | B171: M Liu, K Yang, N Zhao, Y Chen… | C171: 2020 | D171: IEEE Transactions … | E171: =--(ROW(A171)<>MATCH(A171,$A:$A,0)) -> 0 | F171: =IF(COUNTIF('Start Set'!A:A, A171) > 0, 1, 0) -> 0 | J171: 1
A172: Expedient and Non-expedient Nodes in the Internet of Things | B172: A Zannou, A Boulaalam, EH Nfaoui | C172: 2020 | D172: International Conference on … | E172: =--(ROW(A172)<>MATCH(A172,$A:$A,0)) -> 0 | F172: =IF(COUNTIF('Start Set'!A:A, A172) > 0, 1, 0) -> 0 | J172: 1
A173: Seamless integration of devices in industry 4.0 environments | B173: D Del Gaudio, P Hirmer | C173: 2020 | D173: Internet of Things (Elsevier) | E173: =--(ROW(A173)<>MATCH(A173,$A:$A,0)) -> 0 | F173: =IF(COUNTIF('Start Set'!A:A, A173) > 0, 1, 0) -> 0 | J173: 1
A174: The design methodology for mac strategies and protocols supporting ultra-low delay services in next generation IEEE 802.11 WLAN | B174: B Li, GAA Mohammed, M Yang, Z Yan | C174: 2020 | D174: Internet of Things as a Service (Springer) | E174: =--(ROW(A174)<>MATCH(A174,$A:$A,0)) -> 0 | F174: =IF(COUNTIF('Start Set'!A:A, A174) > 0, 1, 0) -> 0 | J174: 1
A175: A Life Cycle Method for Device Management in Dynamic IoT Environments. | B175: D Del Gaudio, M Reichel, P Hirmer | C175: 2020 | D175: IoTBDS (SCITEPRESS) | E175: =--(ROW(A175)<>MATCH(A175,$A:$A,0)) -> 0 | F175: =IF(COUNTIF('Start Set'!A:A, A175) > 0, 1, 0) -> 0 | J175: 1
A176: Fulfilling the IoT Vision: Are We There Yet? | B176: D Del Gaudio, P Hirmer | C176: 2020 | D176: IoTBDS (SCITEPRESS) | E176: =--(ROW(A176)<>MATCH(A176,$A:$A,0)) -> 0 | F176: =IF(COUNTIF('Start Set'!A:A, A176) > 0, 1, 0) -> 0 | J176: 1
... A584: MicroFaaS: Adaptive serverless computing for Internet of Things | B584: O Krolik, T Szydlo | C584: 2026 | D584: Future Generation Computer Systems | E584: =--(ROW(A584)<>MATCH(A584,$A:$A,0)) -> 1 | F584: =IF(COUNTIF('Start Set'!A:A, A584) > 0, 1, 0) -> 0 | J584: 1
A585: Toward Low-Latency Cross-Modal Communication: A Flexible Prediction Scheme | B585: Y Chen, P Li, A Li, D Wu, L Zhou… | C585: 2024 | D585: IEEE Transactions on … | E585: =--(ROW(A585)<>MATCH(A585,$A:$A,0)) -> 0 | F585: =IF(COUNTIF('Start Set'!A:A, A585) > 0, 1, 0) -> 0 | I585: 1 | K585: 1
A586: Subcarrier power control for URLLC communication system via multi-agent deep reinforcement learning in IoT network | B586: H Wang, X Li, F Luo, J Li | C586: 2024 | D586: International Journal of (Inderscience) | E586: =--(ROW(A586)<>MATCH(A586,$A:$A,0)) -> 0 | F586: =IF(COUNTIF('Start Set'!A:A, A586) > 0, 1, 0) -> 0 | H586: 1 | K586: 1
A587: Smart Factory based on IIoT: Applications Communication Networks and Cybersecurity | B587: YS Sheet, MY Thanoun | C587: 2024 | D587: International Journal of … (ResearchGate) | E587: =--(ROW(A587)<>MATCH(A587,$A:$A,0)) -> 0 | F587: =IF(COUNTIF('Start Set'!A:A, A587) > 0, 1, 0) -> 0 | H587: 1 | K587: 1
A588: MAC protocols for industrial delay-sensitive applications in industry 4.0: Exploring challenges protocols and requirements | B588: A Chehri | C588: 2021 | D588: Procedia Computer Science (Elsevier) | E588: =--(ROW(A588)<>MATCH(A588,$A:$A,0)) -> 0 | F588: =IF(COUNTIF('Start Set'!A:A, A588) > 0, 1, 0) -> 0 | H588: 1 | K588: 1
A589: Delay and reliability analysis of p-persistent carrier sense multiple access for multi-event industrial wireless sensor networks | B589: NTT Hang, NC Trinh, NT Ban, M Raza… | C589: 2020 | D589: IEEE Sensors … | E589: =--(ROW(A589)<>MATCH(A589,$A:$A,0)) -> 0 | F589: =IF(COUNTIF('Start Set'!A:A, A589) > 0, 1, 0) -> 0 | I589: 1 | K589: 1
A590: Cloud–fog automation: Heterogenous applications over new-generation infrastructure of virtualized computing and converged networks | B590: H Lyu, J Yan, J Zhang, Z Pang, G Yang… | C590: 2024 | D590: IEEE Industrial … | E590: =--(ROW(A590)<>MATCH(A590,$A:$A,0)) -> 0 | F590: =IF(COUNTIF('Start Set'!A:A, A590) > 0, 1, 0) -> 0 | I590: 1 | K590: 1
A591: The computing continuum: Past present and future | B591: LF Bittencourt, R Rodrigues-Filho, J Spillner… | C591: 2025 | D591: Computer Science … | E591: =--(ROW(A591)<>MATCH(A591,$A:$A,0)) -> 0 | F591: =IF(COUNTIF('Start Set'!A:A, A591) > 0, 1, 0) -> 0 | K591: 1
A592: Strategies for assuring low latency scalability and interoperability in edge computing and TSN networks for critical IIoT services | B592: DL Gomez, GA Montoya, C Lozano-Garzon | C592: 2023 | D592: IEEE | E592: =--(ROW(A592)<>MATCH(A592,$A:$A,0)) -> 0 | F592: =IF(COUNTIF('Start Set'!A:A, A592) > 0, 1, 0) -> 0 | K592: 1
A593: Real-time performance of industrial IoT communication technologies: A review | B593: I Behnke, H Austad | C593: 2023 | D593: IEEE Internet of Things Journal | E593: =--(ROW(A593)<>MATCH(A593,$A:$A,0)) -> 0 | F593: =IF(COUNTIF('Start Set'!A:A, A593) > 0, 1, 0) -> 0 | K593: 1
A594: Intelligent and low overhead network synchronization for large-scale industrial IoT systems in the 6G era | B594: X Wang, P Jia, X Shen, HV Poor | C594: 2022 | D594: IEEE Network | E594: =--(ROW(A594)<>MATCH(A594,$A:$A,0)) -> 0 | F594: =IF(COUNTIF('Start Set'!A:A, A594) > 0, 1, 0) -> 0 | K594: 1
A595: URLLC and eMBB in 5G industrial IoT: A survey | B595: BS Khan, S Jangsher, A Ahmed | C595: 2022 | D595: IEEE Open Journal of … | E595: 0 | F595: =IF(COUNTIF('Start Set'!A:A, A595) > 0, 1, 0) -> 0 | K595: 1
A596: A survey of 802.15. 4 TSCH schedulers for a standardized industrial Internet of Things | B596: AR Urke, Ø Kure, K Øvsthus | C596: 2021 | D596: Sensors | E596: 0 | F596: =IF(COUNTIF('Start Set'!A:A, A596) > 0, 1, 0) -> 0 | K596: 1
A598: =COUNT(E2:E596)-SUM(E2:E596)-SUM(F2:F596) -> 568 | B598: Unique rows checked

Sheet Iteration 1 - Backward
A1: Title | B1: Authors | C1: Year | D1: Venue | E1: D | F1: DS | G1: DF | H1: EC1 | I1: EC2 | J1: EC3 | K1: EC4 | L1: EC5 | M1: EC6 | N1: IC1
A2: Networks of Waiting Lines | B2: Jackson, J.R. | C2: 1957 | D2: Operations Research | E2: =--(ROW(A2)<>MATCH(A2,$A:$A,0)) -> 0 | F2: =IF(COUNTIF('Start Set'!A:A, A2) > 0, 1, 0) -> 0 | G2: =IF(COUNTIF('Iteration 1 - Forward'!A:A, A2) > 0, 1, 0) -> 0 | H2: 1
A3: Validity of the Single-Processor Approach to Achieving Large-Scale Computing Requirements | B3: Amdahl, G. | C3: 1967 | D3: Computer Design | E3: =--(ROW(A3)<>MATCH(A3,$A:$A,0)) -> 0 | F3: =IF(COUNTIF('Start Set'!A:A, A3) > 0, 1, 0) -> 0 | G3: =IF(COUNTIF('Iteration 1 - Forward'!A:A, A3) > 0, 1, 0) -> 0 | H3: 1
A4: Complexity of Computer Computations | B4: Karp, R.M. | C4: 1972 | D4: Symposium on Complexity of Computer Computations | E4: =--(ROW(A4)<>MATCH(A4,$A:$A,0)) -> 0 | F4: =IF(COUNTIF('Start Set'!A:A, A4) > 0, 1, 0) -> 0 | G4: =IF(COUNTIF('Iteration 1 - Forward'!A:A, A4) > 0, 1, 0) -> 0 | H4: 1
A5: Queueing Systems Vol. I: Theory | B5: Kleinrock, L. | C5: 1975 | D5: Wiley Interscience | E5: =--(ROW(A5)<>MATCH(A5,$A:$A,0)) -> 0 | F5: =IF(COUNTIF('Start Set'!A:A, A5) > 0, 1, 0) -> 0 | G5: =IF(COUNTIF('Iteration 1 - Forward'!A:A, A5) > 0, 1, 0) -> 0 | H5: 1
A6: Reception through Nakagami fading multipath channels with random delays | B6: Charash, U. | C6: 1979 | D6: IEEE Transactions on Communications | E6: =--(ROW(A6)<>MATCH(A6,$A:$A,0)) -> 0 | F6: =IF(COUNTIF('Start Set'!A:A, A6) > 0, 1, 0) -> 0 | G6: =IF(COUNTIF('Iteration 1 - Forward'!A:A, A6) > 0, 1, 0) -> 0 | H6: 1
A7: Some complexity results about packet radio networks | B7: Arikan, E. | C7: 1984 | D7: IEEE Transactions on Information Theory | E7: =--(ROW(A7)<>MATCH(A7,$A:$A,0)) -> 0 | F7: =IF(COUNTIF('Start Set'!A:A, A7) > 0, 1, 0) -> 0 | G7: =IF(COUNTIF('Iteration 1 - Forward'!A:A, A7) > 0, 1, 0) -> 0 | H7: 1
A8: Minimization Methods for Non-Differentiable Functions | B8: Shor, N.Z. | C8: 1985 | D8: Springer-Verlag | E8: =--(ROW(A8)<>MATCH(A8,$A:$A,0)) -> 0 | F8: =IF(COUNTIF('Start Set'!A:A, A8) > 0, 1, 0) -> 0 | G8: =IF(COUNTIF('Iteration 1 - Forward'!A:A, A8) > 0, 1, 0) -> 0 | H8: 1
A9: Congestion Avoidance and Control | B9: Jacobson, V. | C9: 1988 | D9: ACM SIGCOMM Symposium | E9: =--(ROW(A9)<>MATCH(A9,$A:$A,0)) -> 0 | F9: =IF(COUNTIF('Start Set'!A:A, A9) > 0, 1, 0) -> 0 | G9: =IF(COUNTIF('Iteration 1 - Forward'!A:A, A9) > 0, 1, 0) -> 0 | H9: 1
A10: Probabilistic clock synchronization | B10: Cristian, F. | C10: 1989 | D10: Distributed Computing | E10: =--(ROW(A10)<>MATCH(A10,$A:$A,0)) -> 0 | F10: =IF(COUNTIF('Start Set'!A:A, A10) > 0, 1, 0) -> 0 | G10: =IF(COUNTIF('Iteration 1 - Forward'!A:A, A10) > 0, 1, 0) -> 0 | H10: 1
A11: The Tangram stream query processing system | B11: Parker, D.S.; Muntz, R.R.; Chau, H.L. | C11: 1989 | D11: IEEE International Conference on Data Engineering | E11: =--(ROW(A11)<>MATCH(A11,$A:$A,0)) -> 0 | F11: =IF(COUNTIF('Start Set'!A:A, A11) > 0, 1, 0) -> 0 | G11: =IF(COUNTIF('Iteration 1 - Forward'!A:A, A11) > 0, 1, 0) -> 0 | H11: 1
A12: Priority inheritance protocols: An approach to real-time synchronization | B12: Sha, L.; Rajkumar, R.; Lehoczky, J. | C12: 1990 | D12: IEEE Transactions on Computers | E12: =--(ROW(A12)<>MATCH(A12,$A:$A,0)) -> 0 | F12: =IF(COUNTIF('Start Set'!A:A, A12) > 0, 1, 0) -> 0 | G12: =IF(COUNTIF('Iteration 1 - Forward'!A:A, A12) > 0, 1, 0) -> 0 | H12: 1
A13: Stream Data Analysis in Prolog | B13: Parker, D.S. | C13: 1990 | D13: MIT Press (The Practice of Prolog) | E13: =--(ROW(A13)<>MATCH(A13,$A:$A,0)) -> 0 | F13: =IF(COUNTIF('Start Set'!A:A, A13) > 0, 1, 0) -> 0 | G13: =IF(COUNTIF('Iteration 1 - Forward'!A:A, A13) > 0, 1, 0) -> 0 | H13: 1
A14: Internet time synchronization: The network time protocol | B14: Mills, D.L. | C14: 1991 | D14: IEEE Transactions on Communications | E14: =--(ROW(A14)<>MATCH(A14,$A:$A,0)) -> 0 | F14: =IF(COUNTIF('Start Set'!A:A, A14) > 0, 1, 0) -> 0 | G14: =IF(COUNTIF('Iteration 1 - Forward'!A:A, A14) > 0, 1, 0) -> 0 | H14: 1
A15: Statistical Signal Processing Detection Estimation and Time Series Analysis | B15: Scharf, C.D.L. | C15: 1991 | D15: Addison-Wesley | E15: =--(ROW(A15)<>MATCH(A15,$A:$A,0)) -> 0 | F15: =IF(COUNTIF('Start Set'!A:A, A15) > 0, 1, 0) -> 0 | G15: =IF(COUNTIF('Iteration 1 - Forward'!A:A, A15) > 0, 1, 0) -> 0 | H15: 1 | I15: 1
A16: Data Networks (2nd Ed.) | B16: Bertsekas, D.; Gallager, R. | C16: 1992 | D16: Prentice-Hall | E16: =--(ROW(A16)<>MATCH(A16,$A:$A,0)) -> 0 | F16: =IF(COUNTIF('Start Set'!A:A, A16) > 0, 1, 0) -> 0 | G16: =IF(COUNTIF('Iteration 1 - Forward'!A:A, A16) > 0, 1, 0) -> 0 | H16: 1 | I16: 1
A17: A simple distributed autonomous power control algorithm and its convergence | B17: Foschini, G.J.; Miljanic, Z. | C17: 1993 | D17: IEEE Transactions on Vehicular Technology | E17: =--(ROW(A17)<>MATCH(A17,$A:$A,0)) -> 0 | F17: =IF(COUNTIF('Start Set'!A:A, A17) > 0, 1, 0) -> 0 | G17: =IF(COUNTIF('Iteration 1 - Forward'!A:A, A17) > 0, 1, 0) -> 0 | H17: 1
A18: Fundamentals of Statistical Signal Processing Volume 1 | B18: Kay, S.M. | C18: 1993 | D18: Prentice-Hall | E18: =--(ROW(A18)<>MATCH(A18,$A:$A,0)) -> 0 | F18: =IF(COUNTIF('Start Set'!A:A, A18) > 0, 1, 0) -> 0 | G18: =IF(COUNTIF('Iteration 1 - Forward'!A:A, A18) > 0, 1, 0) -> 0 | H18: 1 | I18: 1
A19: Fundamentals of Statistical Signal Processing: Estimation Theory | B19: Kay, S.M. | C19: 1993 | D19: Prentice-Hall | E19: =--(ROW(A19)<>MATCH(A19,$A:$A,0)) -> 0 | F19: =IF(COUNTIF('Start Set'!A:A, A19) > 0, 1, 0) -> 0 | G19: =IF(COUNTIF('Iteration 1 - Forward'!A:A, A19) > 0, 1, 0) -> 0 | H19: 1 | I19: 1
A20: Holistic schedulability analysis for distributed hard real-time systems | B20: Tindell, K.; Clark, J. | C20: 1994 | D20: Microprocessing and Microprogramming | E20: =--(ROW(A20)<>MATCH(A20,$A:$A,0)) -> 0 | F20: =IF(COUNTIF('Start Set'!A:A, A20) > 0, 1, 0) -> 0 | G20: =IF(COUNTIF('Iteration 1 - Forward'!A:A, A20) > 0, 1, 0) -> 0 | H20: 1
A21: An Introduction to Signal Detection and Estimation | B21: Poor, H.V. | C21: 1994 | D21: Springer | E21: =--(ROW(A21)<>MATCH(A21,$A:$A,0)) -> 0 | F21: =IF(COUNTIF('Start Set'!A:A, A21) > 0, 1, 0) -> 0 | G21: =IF(COUNTIF('Iteration 1 - Forward'!A:A, A21) > 0, 1, 0) -> 0 | H21: 1
A22: The TSQL2 Temporal Query Language | B22: Snodgrass, R.T.; Ahn, I.; Ariav, G.; Batory, D.S.; Clifford, J.; Dyreson, C.E.; Elmasri, R.; Grandi, F.; Jensen, C.S.; Käfer, W.; Kline, N.; Kulkanri, K.; Leung, C.Y.T.; Lorentzos, N.; Roddick, J.F.; Segev, A.; Soo, M.D.; Sripada, S.M. | C22: 1995 | D22: Kluwer Academic | E22: =--(ROW(A22)<>MATCH(A22,$A:$A,0)) -> 0 | F22: =IF(COUNTIF('Start Set'!A:A, A22) > 0, 1, 0) -> 0 | G22: =IF(COUNTIF('Iteration 1 - Forward'!A:A, A22) > 0, 1, 0) -> 0 | H22: 1
A23: The pipes and filters architecture | B23: Meunier, R. | C23: 1995 | D23: Pattern Languages of Program Design (ACM Press/Addison-Wesley) | E23: =--(ROW(A23)<>MATCH(A23,$A:$A,0)) -> 0 | F23: =IF(COUNTIF('Start Set'!A:A, A23) > 0, 1, 0) -> 0 | G23: =IF(COUNTIF('Iteration 1 - Forward'!A:A, A23) > 0, 1, 0) -> 0 | H23: 1
A24: Aperiodic servers in a deadline scheduling environment | B24: Ghazalie, T.M.; Baker, T.P. | C24: 1995 | D24: Real-Time Systems | E24: =--(ROW(A24)<>MATCH(A24,$A:$A,0)) -> 0 | F24: =IF(COUNTIF('Start Set'!A:A, A24) > 0, 1, 0) -> 0 | G24: =IF(COUNTIF('Iteration 1 - Forward'!A:A, A24) > 0, 1, 0) -> 0 | H24: 1
A25: Operating system architecture using multiple priority lightweight kernel task based interrupt handling | B25: Bunnell, M. | C25: 1995 | D25: US Patent 5469571 | E25: =--(ROW(A25)<>MATCH(A25,$A:$A,0)) -> 0 | F25: =IF(COUNTIF('Start Set'!A:A, A25) > 0, 1, 0) -> 0 | G25: =IF(COUNTIF('Iteration 1 - Forward'!A:A, A25) > 0, 1, 0) -> 0 | H25: 1 | I25: 1
A26: Advanced Database Systems | B26: Zaniolo, C.; Ceri, S.; Faloutsos, C.; Snodgrass, R.T.; Subrahmanian, V.S.; Zicari, R. | C26: 1997 | D26: Morgan Kaufmann | E26: =--(ROW(A26)<>MATCH(A26,$A:$A,0)) -> 0 | F26: =IF(COUNTIF('Start Set'!A:A, A26) > 0, 1, 0) -> 0 | G26: =IF(COUNTIF('Iteration 1 - Forward'!A:A, A26) > 0, 1, 0) -> 0 | H26: 1
A27: IEEE Standard for Wireless LAN Medium Access Control (MAC) and Physical Layer (PHY) Specifications | C27: 1997 | D27: IEEE Std 802.11-1997 | E27: =--(ROW(A27)<>MATCH(A27,$A:$A,0)) -> 0 | F27: =IF(COUNTIF('Start Set'!A:A, A27) > 0, 1, 0) -> 0 | G27: =IF(COUNTIF('Iteration 1 - Forward'!A:A, A27) > 0, 1, 0) -> 0 | H27: 1 | I27: 1
A28: Integer Programming | B28: Wolsey, L. | C28: 1998 | D28: Wiley | E28: =--(ROW(A28)<>MATCH(A28,$A:$A,0)) -> 0 | F28: =IF(COUNTIF('Start Set'!A:A, A28) > 0, 1, 0) -> 0 | G28: =IF(COUNTIF('Iteration 1 - Forward'!A:A, A28) > 0, 1, 0) -> 0 | H28: 1
A29: Lipschitz Algebras | B29: Weaver, N. | C29: 1999 | D29: World Scientific | E29: =--(ROW(A29)<>MATCH(A29,$A:$A,0)) -> 0 | F29: =IF(COUNTIF('Start Set'!A:A, A29) > 0, 1, 0) -> 0 | G29: =IF(COUNTIF('Iteration 1 - Forward'!A:A, A29) > 0, 1, 0) -> 0 | H29: 1
A30: Performance analysis of the IEEE 802.11 distributed coordination function | B30: Bianchi, G. | C30: 2000 | D30: IEEE Journal on Selected Areas in Communications | E30: =--(ROW(A30)<>MATCH(A30,$A:$A,0)) -> 0 | F30: =IF(COUNTIF('Start Set'!A:A, A30) > 0, 1, 0) -> 0 | G30: =IF(COUNTIF('Iteration 1 - Forward'!A:A, A30) > 0, 1, 0) -> 0 | H30: 1
A31: The capacity of wireless networks | B31: Gupta, P.; Kumar, P.R. | C31: 2000 | D31: IEEE Transactions on Information Theory | E31: =--(ROW(A31)<>MATCH(A31,$A:$A,0)) -> 0 | F31: =IF(COUNTIF('Start Set'!A:A, A31) > 0, 1, 0) -> 0 | G31: =IF(COUNTIF('Iteration 1 - Forward'!A:A, A31) > 0, 1, 0) -> 0 | H31: 1
A32: Matrix analysis and applied linear algebra | B32: Meyer, C.D. | C32: 2000 | D32: SIAM | E32: =--(ROW(A32)<>MATCH(A32,$A:$A,0)) -> 0 | F32: =IF(COUNTIF('Start Set'!A:A, A32) > 0, 1, 0) -> 0 | G32: =IF(COUNTIF('Iteration 1 - Forward'!A:A, A32) > 0, 1, 0) -> 0 | H32: 1
A33: Time Granularities in Databases Data Mining and Temporal Reasoning | B33: Bettini, C.; Jajodia, S.; Wang, S.X. | C33: 2000 | D33: Springer | E33: =--(ROW(A33)<>MATCH(A33,$A:$A,0)) -> 0 | F33: =IF(COUNTIF('Start Set'!A:A, A33) > 0, 1, 0) -> 0 | G33: =IF(COUNTIF('Iteration 1 - Forward'!A:A, A33) > 0, 1, 0) -> 0 | H33: 1
A34: Real-Time Systems | B34: Liu, J.W.S. | C34: 2000 | D34: Prentice-Hall | E34: =--(ROW(A34)<>MATCH(A34,$A:$A,0)) -> 0 | F34: =IF(COUNTIF('Start Set'!A:A, A34) > 0, 1, 0) -> 0 | G34: =IF(COUNTIF('Iteration 1 - Forward'!A:A, A34) > 0, 1, 0) -> 0 | H34: 1 | I34: 1
A35: Performance analysis of the IEEE 802.11 distributed coordination function | B35: Bianchi, G. | C35: 2000 | D35: IEEE Journal on Selected Areas in Communications | E35: =--(ROW(A35)<>MATCH(A35,$A:$A,0)) -> 1 | F35: =IF(COUNTIF('Start Set'!A:A, A35) > 0, 1, 0) -> 0 | G35: =IF(COUNTIF('Iteration 1 - Forward'!A:A, A35) > 0, 1, 0) -> 0 | H35: 1
A36: A new approach to channel access scheduling for ad hoc networks | B36: Bao, L.; Garcia-Luna-Aceves, J. | C36: 2001 | D36: ACM International Conference on Mobile Computing and Networking (MobiCom) | E36: =--(ROW(A36)<>MATCH(A36,$A:$A,0)) -> 0 | F36: =IF(COUNTIF('Start Set'!A:A, A36) > 0, 1, 0) -> 0 | G36: =IF(COUNTIF('Iteration 1 - Forward'!A:A, A36) > 0, 1, 0) -> 0 | H36: 1
A37: Highly-resilient energy-efficient multipath routing in wireless sensor networks | B37: Ganesan, D.; Govindan, R.; Shenker, S.; Estrin, D. | C37: 2001 | D37: ACM SIGMOBILE Mobile Computing and Communications Review | E37: =--(ROW(A37)<>MATCH(A37,$A:$A,0)) -> 0 | F37: =IF(COUNTIF('Start Set'!A:A, A37) > 0, 1, 0) -> 0 | G37: =IF(COUNTIF('Iteration 1 - Forward'!A:A, A37) > 0, 1, 0) -> 0 | H37: 1
A38: HIP: Hybrid interrupt-polling for the network interface | B38: Dovrolis, C.; Thayer, B.; Ramanathan, P. | C38: 2001 | D38: ACM SIGOPS Operating Systems Review | E38: =--(ROW(A38)<>MATCH(A38,$A:$A,0)) -> 0 | F38: =IF(COUNTIF('Start Set'!A:A, A38) > 0, 1, 0) -> 0 | G38: =IF(COUNTIF('Iteration 1 - Forward'!A:A, A38) > 0, 1, 0) -> 0 | H38: 1
A39: Resource partition for real-time systems | B39: Mok, A.; Feng, X.; Chen, D. | C39: 2001 | D39: IEEE RTAS | E39: =--(ROW(A39)<>MATCH(A39,$A:$A,0)) -> 0 | F39: =IF(COUNTIF('Start Set'!A:A, A39) > 0, 1, 0) -> 0 | G39: =IF(COUNTIF('Iteration 1 - Forward'!A:A, A39) > 0, 1, 0) -> 0 | H39: 1
A40: A bandwidth inheritance algorithm for real-time task synchronization in open systems | B40: Lamastra, G.; Lipari, G.; Abeni, L. | C40: 2001 | D40: IEEE RTSS | E40: =--(ROW(A40)<>MATCH(A40,$A:$A,0)) -> 0 | F40: =IF(COUNTIF('Start Set'!A:A, A40) > 0, 1, 0) -> 0 | G40: =IF(COUNTIF('Iteration 1 - Forward'!A:A, A40) > 0, 1, 0) -> 0 | H40: 1
A41: Resource sharing in reservation-based systems | B41: de Niz, D.; Abeni, L.; Saewong, S.; Rajkumar, R. | C41: 2001 | D41: IEEE RTSS | E41: =--(ROW(A41)<>MATCH(A41,$A:$A,0)) -> 0 | F41: =IF(COUNTIF('Start Set'!A:A, A41) > 0, 1, 0) -> 0 | G41: =IF(COUNTIF('Iteration 1 - Forward'!A:A, A41) > 0, 1, 0) -> 0 | H41: 1
A42: Network Calculus: A theory of deterministic queuing systems for the Internet | B42: Le Boudec, J.-Y.; Thiran, P. | C42: 2001 | D42: Springer | E42: =--(ROW(A42)<>MATCH(A42,$A:$A,0)) -> 0 | F42: =IF(COUNTIF('Start Set'!A:A, A42) > 0, 1, 0) -> 0 | G42: =IF(COUNTIF('Iteration 1 - Forward'!A:A, A42) > 0, 1, 0) -> 0 | H42: 1
A43: Ad Hoc Networking | B43: Perkins, C.E. | C43: 2001 | D43: Addison-Wesley | E43: =--(ROW(A43)<>MATCH(A43,$A:$A,0)) -> 0 | F43: =IF(COUNTIF('Start Set'!A:A, A43) > 0, 1, 0) -> 0 | G43: =IF(COUNTIF('Iteration 1 - Forward'!A:A, A43) > 0, 1, 0) -> 0 | H43: 1 | I43: 1
A44: A First Course in Electronic Warfare | B44: Adamy, D. | C44: 2001 | D44: Artech House | E44: =--(ROW(A44)<>MATCH(A44,$A:$A,0)) -> 0 | F44: =IF(COUNTIF('Start Set'!A:A, A44) > 0, 1, 0) -> 0 | G44: =IF(COUNTIF('Iteration 1 - Forward'!A:A, A44) > 0, 1, 0) -> 0 | H44: 1 | I44: 1
A45: Models and issues in data stream systems | B45: Babcock, B.; Babu, S.; Datar, M.; Motwani, R.; Widom, J. | C45: 2002 | D45: ACM SIGMOD-SIGACT-SIGART Symposium on Principles of Database Systems (PODS) | E45: =--(ROW(A45)<>MATCH(A45,$A:$A,0)) -> 0 | F45: =IF(COUNTIF('Start Set'!A:A, A45) > 0, 1, 0) -> 0 | G45: =IF(COUNTIF('Iteration 1 - Forward'!A:A, A45) > 0, 1, 0) -> 0 | H45: 1
A46: Fine-grained network time synchronization using reference broadcasts | B46: Elson, J.; Girod, L.; Estrin, D. | C46: 2002 | D46: ACM SIGOPS Operating Systems Review | E46: =--(ROW(A46)<>MATCH(A46,$A:$A,0)) -> 0 | F46: =IF(COUNTIF('Start Set'!A:A, A46) > 0, 1, 0) -> 0 | G46: =IF(COUNTIF('Iteration 1 - Forward'!A:A, A46) > 0, 1, 0) -> 0 | H46: 1
A47: Unraveling the Web Services Web: an introduction to SOAP WSDL and UDDI | B47: Curbera, F.; Duftler, M.; Khalaf, R.; Nagy, W.; Mukhi, N.; Weerawarana, S. | C47: 2002 | D47: IEEE Internet Computing | E47: =--(ROW(A47)<>MATCH(A47,$A:$A,0)) -> 0 | F47: =IF(COUNTIF('Start Set'!A:A, A47) > 0, 1, 0) -> 0 | G47: =IF(COUNTIF('Iteration 1 - Forward'!A:A, A47) > 0, 1, 0) -> 0 | H47: 1
A48: Optimal power control in interference-limited fading wireless channels with outage-probability specifications | B48: Kandukuri, S.; Boyd, S. | C48: 2002 | D48: IEEE Transactions on Wireless Communications | E48: =--(ROW(A48)<>MATCH(A48,$A:$A,0)) -> 0 | F48: =IF(COUNTIF('Start Set'!A:A, A48) > 0, 1, 0) -> 0 | G48: =IF(COUNTIF('Iteration 1 - Forward'!A:A, A48) > 0, 1, 0) -> 0 | H48: 1
A49: Probability and Statistics With Reliability Queuing and Computer Science Applications | B49: Trivedi, K. | C49: 2002 | D49: Wiley | E49: =--(ROW(A49)<>MATCH(A49,$A:$A,0)) -> 0 | F49: =IF(COUNTIF('Start Set'!A:A, A49) > 0, 1, 0) -> 0 | G49: =IF(COUNTIF('Iteration 1 - Forward'!A:A, A49) > 0, 1, 0) -> 0 | H49: 1
A50: MicroC/OS II: The Real Time Kernel | B50: Labrosse, J.J. | C50: 2002 | D50: CMP Books | E50: =--(ROW(A50)<>MATCH(A50,$A:$A,0)) -> 0 | F50: =IF(COUNTIF('Start Set'!A:A, A50) > 0, 1, 0) -> 0 | G50: =IF(COUNTIF('Iteration 1 - Forward'!A:A, A50) > 0, 1, 0) -> 0 | H50: 1 | I50: 1
A51: Coda: Congestion detection and avoidance in sensor networks | B51: Wan, C.-Y.; Eisenman, S.B.; Campbell, A.T. | C51: 2003 | D51: ACM SenSys | E51: =--(ROW(A51)<>MATCH(A51,$A:$A,0)) -> 0 | F51: =IF(COUNTIF('Start Set'!A:A, A51) > 0, 1, 0) -> 0 | G51: =IF(COUNTIF('Iteration 1 - Forward'!A:A, A51) > 0, 1, 0) -> 0 | H51: 1
A52: Timing-sync protocol for sensor networks | B52: Ganeriwal, S.; Kumar, R.; Srivastava, M.B. | C52: 2003 | D52: ACM SenSys | E52: =--(ROW(A52)<>MATCH(A52,$A:$A,0)) -> 0 | F52: =IF(COUNTIF('Start Set'!A:A, A52) > 0, 1, 0) -> 0 | G52: =IF(COUNTIF('Iteration 1 - Forward'!A:A, A52) > 0, 1, 0) -> 0 | H52: 1
A53: Continuously adaptive continuous queries over streams | B53: Madden, S.R.; Shah, M.A.; Hellerstein, J.M.; Raman, V. | C53: 2003 | D53: ACM SIGMOD Conference on Management of Data | E53: =--(ROW(A53)<>MATCH(A53,$A:$A,0)) -> 0 | F53: =IF(COUNTIF('Start Set'!A:A, A53) > 0, 1, 0) -> 0 | G53: =IF(COUNTIF('Iteration 1 - Forward'!A:A, A53) > 0, 1, 0) -> 0 | H53: 1
A54: STREAM: The Stanford Stream Data Manager | B54: Arasu, A.; Babcock, B.; Babu, S.; Datar, M.; Ito, K.; Nishizawa, I.; Rosenstein, J.; Widom, J. | C54: 2003 | D54: ACM SIGMOD Conference on Management of Data | E54: =--(ROW(A54)<>MATCH(A54,$A:$A,0)) -> 0 | F54: =IF(COUNTIF('Start Set'!A:A, A54) > 0, 1, 0) -> 0 | G54: =IF(COUNTIF('Iteration 1 - Forward'!A:A, A54) > 0, 1, 0) -> 0 | H54: 1
A55: Web services orchestration and choreography | B55: Peltz, C. | C55: 2003 | D55: Computer | E55: =--(ROW(A55)<>MATCH(A55,$A:$A,0)) -> 0 | F55: =IF(COUNTIF('Start Set'!A:A, A55) > 0, 1, 0) -> 0 | G55: =IF(COUNTIF('Iteration 1 - Forward'!A:A, A55) > 0, 1, 0) -> 0 | H55: 1
A56: Improved throughput by interference avoidance in co-located Bluetooth networks | B56: Amanquah, N.; Dunlop, J. | C56: 2003 | D56: European Personal Mobile Communications Conference (EPMCC) | E56: =--(ROW(A56)<>MATCH(A56,$A:$A,0)) -> 0 | F56: =IF(COUNTIF('Start Set'!A:A, A56) > 0, 1, 0) -> 0 | G56: =IF(COUNTIF('Iteration 1 - Forward'!A:A, A56) > 0, 1, 0) -> 0 | H56: 1
A57: A framework for reliable routing in mobile ad hoc networks | B57: Ye, Z.; Krishnamurthy, S.V.; Tripathi, S.K. | C57: 2003 | D57: IEEE INFOCOM | E57: =--(ROW(A57)<>MATCH(A57,$A:$A,0)) -> 0 | F57: =IF(COUNTIF('Start Set'!A:A, A57) > 0, 1, 0) -> 0 | G57: =IF(COUNTIF('Iteration 1 - Forward'!A:A, A57) > 0, 1, 0) -> 0 | H57: 1
A58: Periodic resource model for compositional real-time guarantees | B58: Shin, I.; Lee, I. | C58: 2003 | D58: IEEE RTSS | E58: =--(ROW(A58)<>MATCH(A58,$A:$A,0)) -> 0 | F58: =IF(COUNTIF('Start Set'!A:A, A58) > 0, 1, 0) -> 0 | G58: =IF(COUNTIF('Iteration 1 - Forward'!A:A, A58) > 0, 1, 0) -> 0 | H58: 1
A59: A utility-based power-control scheme in wireless cellular systems | B59: Xiao, M.; Shroff, N.B.; Chong, E.K.P. | C59: 2003 | D59: IEEE/ACM Transactions on Networking | E59: =--(ROW(A59)<>MATCH(A59,$A:$A,0)) -> 0 | F59: =IF(COUNTIF('Start Set'!A:A, A59) > 0, 1, 0) -> 0 | G59: =IF(COUNTIF('Iteration 1 - Forward'!A:A, A59) > 0, 1, 0) -> 0 | H59: 1
A60: Aurora: a new model and architecture for data stream management | B60: Abadi, D.J.; Carney, D.; Cetintemel, U.; Cherniack, M.; Convey, C.; Lee, S.; Stonebraker, M.; Tatbul, N.; Zdonik, S. | C60: 2003 | D60: VLDB Journal | E60: =--(ROW(A60)<>MATCH(A60,$A:$A,0)) -> 0 | F60: =IF(COUNTIF('Start Set'!A:A, A60) > 0, 1, 0) -> 0 | G60: =IF(COUNTIF('Iteration 1 - Forward'!A:A, A60) > 0, 1, 0) -> 0 | H60: 1
A61: Aurora: a new model and architecture for data stream management | B61: Abadi, D.J.; Carney, D.; Cetintemel, U.; Cherniack, M.; Convey, C.; Lee, S.; Stonebraker, M.; Tatbul, N.; Zdonik, S. | C61: 2003 | D61: VLDB Journal | E61: =--(ROW(A61)<>MATCH(A61,$A:$A,0)) -> 1 | F61: =IF(COUNTIF('Start Set'!A:A, A61) > 0, 1, 0) -> 0 | G61: =IF(COUNTIF('Iteration 1 - Forward'!A:A, A61) > 0, 1, 0) -> 0 | H61: 1
A62: The flooding time synchronization protocol | B62: Maróti, M.; Kusy, B.; Simon, G.; Lédeczi, Á. | C62: 2004 | D62: ACM SenSys | E62: =--(ROW(A62)<>MATCH(A62,$A:$A,0)) -> 0 | F62: =IF(COUNTIF('Start Set'!A:A, A62) > 0, 1, 0) -> 0 | G62: =IF(COUNTIF('Iteration 1 - Forward'!A:A, A62) > 0, 1, 0) -> 0 | H62: 1
... A77: Adaptive mitigation of self-interference in Bluetooth scatternets | B77: Popovski, P.; Yomo, H.; Guarracino, S.; Prasad, R. | C77: 2004 | D77: Wireless Personal Multimedia Communications (WPMC) | E77: =--(ROW(A77)<>MATCH(A77,$A:$A,0)) -> 0 | F77: =IF(COUNTIF('Start Set'!A:A, A77) > 0, 1, 0) -> 0 | G77: =IF(COUNTIF('Iteration 1 - Forward'!A:A, A77) > 0, 1, 0) -> 0 | H77: 1
A78: PRfc 2544 Testing of Ethernet Services in Telecom Networks—White Paper | B78: Nigel, B. | C78: 2004 | D78: Agilent Technologies (White Paper) | E78: =--(ROW(A78)<>MATCH(A78,$A:$A,0)) -> 0 | F78: =IF(COUNTIF('Start Set'!A:A, A78) > 0, 1, 0) -> 0 | G78: =IF(COUNTIF('Iteration 1 - Forward'!A:A, A78) > 0, 1, 0) -> 0 | H78: 1 | I78: 1
A79: Linear Road - Project Website | C79: 2004 | D79: Brandeis University | E79: =--(ROW(A79)<>MATCH(A79,$A:$A,0)) -> 0 | F79: =IF(COUNTIF('Start Set'!A:A, A79) > 0, 1, 0) -> 0 | G79: =IF(COUNTIF('Iteration 1 - Forward'!A:A, A79) > 0, 1, 0) -> 0 | H79: 1 | I79: 1
A80: Low-rate wireless personal area networks: enabling wireless sensors with IEEE 802.15.4 | B80: Gutierrez, J.A.; Callaway, E.H.; Barrett, R.L. | C80: 2004 | D80: IEEE Standards Association | E80: =--(ROW(A80)<>MATCH(A80,$A:$A,0)) -> 0 | F80: =IF(COUNTIF('Start Set'!A:A, A80) > 0, 1, 0) -> 0 | G80: =IF(COUNTIF('Iteration 1 - Forward'!A:A, A80) > 0, 1, 0) -> 0 | H80: 1 | I80: 1
A81: Convex Optimization | B81: Boyd, S.P.; Vandenberghe, L. | C81: 2004 | D81: Cambridge University Press | E81: =--(ROW(A81)<>MATCH(A81,$A:$A,0)) -> 1 | F81: =IF(COUNTIF('Start Set'!A:A, A81) > 0, 1, 0) -> 0 | G81: =IF(COUNTIF('Iteration 1 - Forward'!A:A, A81) > 0, 1, 0) -> 0 | H81: 1
A82: The feasibility of launching and detecting jamming attacks in wireless networks | B82: Xu, W.; Trappe, W.; Zhang, Y.; Wood, T. | C82: 2005 | D82: ACM MobiHoc | E82: =--(ROW(A82)<>MATCH(A82,$A:$A,0)) -> 0 | F82: =IF(COUNTIF('Start Set'!A:A, A82) > 0, 1, 0) -> 0 | G82: =IF(COUNTIF('Iteration 1 - Forward'!A:A, A82) > 0, 1, 0) -> 0 | H82: 1
A83: Operator placement for in-network stream query processing | B83: Srivastava, U.; Munagala, K.; Widom, J. | C83: 2005 | D83: ACM SIGMOD-SIGACT-SIGART Symposium on Principles of Database Systems (PODS) | E83: =--(ROW(A83)<>MATCH(A83,$A:$A,0)) -> 0 | F83: =IF(COUNTIF('Start Set'!A:A, A83) > 0, 1, 0) -> 0 | G83: =IF(COUNTIF('Iteration 1 - Forward'!A:A, A83) > 0, 1, 0) -> 0 | H83: 1
A84: Preventing interrupt overload | B84: Regehr, J.; Duongsaa, U. | C84: 2005 | D84: ACM SIGPLAN Notices | E84: =--(ROW(A84)<>MATCH(A84,$A:$A,0)) -> 0 | F84: =IF(COUNTIF('Start Set'!A:A, A84) > 0, 1, 0) -> 0 | G84: =IF(COUNTIF('Iteration 1 - Forward'!A:A, A84) > 0, 1, 0) -> 0 | H84: 1
A85: The design of the Borealis stream processing engine | B85: Abadi, D.J.; Ahmad, Y.; Balazinska, M.; Cetintemel, U.; Cherniack, M.; Hwang, J.-H.; Lindner, W.; Maskey, A.S.; Rasin, A.; Ryvkina, E.; Tatbul, N.; Xing, Y.; Zdonik, S. | C85: 2005 | D85: Conference on Innovative Data Systems Research (CIDR) | E85: =--(ROW(A85)<>MATCH(A85,$A:$A,0)) -> 0 | F85: =IF(COUNTIF('Start Set'!A:A, A85) > 0, 1, 0) -> 0 | G85: =IF(COUNTIF('Iteration 1 - Forward'!A:A, A85) > 0, 1, 0) -> 0 | H85: 1
A86: Influence of memory hierarchies on predictability for time constrained embedded software | B86: Wehmeyer, L.; Marwedel, P. | C86: 2005 | D86: DATE Conference | E86: =--(ROW(A86)<>MATCH(A86,$A:$A,0)) -> 0 | F86: =IF(COUNTIF('Start Set'!A:A, A86) > 0, 1, 0) -> 0 | G86: =IF(COUNTIF('Iteration 1 - Forward'!A:A, A86) > 0, 1, 0) -> 0 | H86: 1
A87: POWMAC: A single-channel power-control protocol for throughput enhancement in wireless ad hoc networks | B87: Muqattash, A.; Krunz, M. | C87: 2005 | D87: IEEE Journal on Selected Areas in Communications | E87: =--(ROW(A87)<>MATCH(A87,$A:$A,0)) -> 0 | F87: =IF(COUNTIF('Start Set'!A:A, A87) > 0, 1, 0) -> 0 | G87: =IF(COUNTIF('Iteration 1 - Forward'!A:A, A87) > 0, 1, 0) -> 0 | H87: 1
A88: Autoregressive modeling for fading channel simulation | B88: Baddour, K.E.; Beaulieu, N.C. | C88: 2005 | D88: IEEE Transactions on Wireless Communications | E88: =--(ROW(A88)<>MATCH(A88,$A:$A,0)) -> 0 | F88: =IF(COUNTIF('Start Set'!A:A, A88) > 0, 1, 0) -> 0 | G88: =IF(COUNTIF('Iteration 1 - Forward'!A:A, A88) > 0, 1, 0) -> 0 | H88: 1
A89: Peer-to-peer systems and applications | B89: Steinmetz, R.; Wehrle, K. | C89: 2005 | D89: Springer | E89: =--(ROW(A89)<>MATCH(A89,$A:$A,0)) -> 0 | F89: =IF(COUNTIF('Start Set'!A:A, A89) > 0, 1, 0) -> 0 | G89: =IF(COUNTIF('Iteration 1 - Forward'!A:A, A89) > 0, 1, 0) -> 0 | H89: 1
A90: Live migration of virtual machines | B90: Clark, C.; Fraser, K.; Hand, S.; Hansen, J.G.; Jul, E.; Limpach, C.; Pratt, I.; Warfield, A. | C90: 2005 | D90: USENIX NSDI | E90: =--(ROW(A90)<>MATCH(A90,$A:$A,0)) -> 0 | F90: =IF(COUNTIF('Start Set'!A:A, A90) > 0, 1, 0) -> 0 | G90: =IF(COUNTIF('Iteration 1 - Forward'!A:A, A90) > 0, 1, 0) -> 0 | H90: 1
A91: When NAPI comes to town | B91: Salim, J.H. | C91: 2005 | D91: Linux Conference | E91: =--(ROW(A91)<>MATCH(A91,$A:$A,0)) -> 0 | F91: =IF(COUNTIF('Start Set'!A:A, A91) > 0, 1, 0) -> 0 | G91: =IF(COUNTIF('Iteration 1 - Forward'!A:A, A91) > 0, 1, 0) -> 0 | H91: 1 | I91: 1
A92: ATPC: Adaptive transmission power control for wireless sensor networks | B92: Lin, S.; Zhang, J.; Zhou, G.; Gu, L.; Stankovic, J.A.; He, T. | C92: 2006 | D92: ACM International Conference on Embedded Networked Sensor Systems (SenSys) | E92: =--(ROW(A92)<>MATCH(A92,$A:$A,0)) -> 0 | F92: =IF(COUNTIF('Start Set'!A:A, A92) > 0, 1, 0) -> 0 | G92: =IF(COUNTIF('Iteration 1 - Forward'!A:A, A92) > 0, 1, 0) -> 0 | H92: 1
A93: Marionette: Using RPC for interactive development and debugging of wireless embedded networks | B93: Whitehouse, K.; Tolle, G.; Taneja, J.; Sharp, C.; Kim, S.; Jeong, J.; Hui, J.; Dutta, P.; Culler, D. | C93: 2006 | D93: ACM IPSN | E93: =--(ROW(A93)<>MATCH(A93,$A:$A,0)) -> 0 | F93: =IF(COUNTIF('Start Set'!A:A, A93) > 0, 1, 0) -> 0 | G93: =IF(COUNTIF('Iteration 1 - Forward'!A:A, A93) > 0, 1, 0) -> 0 | H93: 1
A94: Twist: A scalable and reconfigurable testbed for wireless indoor experiments with sensor networks | B94: Handziski, V.; Köpke, A.; Willig, A.; Wolisz, A. | C94: 2006 | D94: ACM REALMAN | E94: =--(ROW(A94)<>MATCH(A94,$A:$A,0)) -> 0 | F94: =IF(COUNTIF('Start Set'!A:A, A94) > 0, 1, 0) -> 0 | G94: =IF(COUNTIF('Iteration 1 - Forward'!A:A, A94) > 0, 1, 0) -> 0 | H94: 1
A95: Design Implementation and Evaluation of the Linear Road Benchmark on the Stream Processing Core | B95: Jain, N.; Amini, L.; Andrade, H.; King, R.; Park, Y.; Selo, P.; Venkatramani, C. | C95: 2006 | D95: ACM SIGMOD Conference on Management of Data | E95: =--(ROW(A95)<>MATCH(A95,$A:$A,0)) -> 0 | F95: =IF(COUNTIF('Start Set'!A:A, A95) > 0, 1, 0) -> 0 | G95: =IF(COUNTIF('Iteration 1 - Forward'!A:A, A95) > 0, 1, 0) -> 0 | H95: 1
A96: Performance analysis of IEEE 802.15.4 with non-beacon-enabled CSMA/CA in non-saturated condition | B96: Kim, T.O.; Kim, H.; Lee, J.; Park, J.S.; Choi, B.D. | C96: 2006 | D96: Embedded and Ubiquitous Computing (EUC 2006) Lecture Notes in Computer Science | E96: =--(ROW(A96)<>MATCH(A96,$A:$A,0)) -> 0 | F96: =IF(COUNTIF('Start Set'!A:A, A96) > 0, 1, 0) -> 0 | G96: =IF(COUNTIF('Iteration 1 - Forward'!A:A, A96) > 0, 1, 0) -> 0 | H96: 1
A97: i-GAME: An implicit GTS allocation mechanism in IEEE 802.15.4 for time-sensitive wireless sensor networks | B97: Koubâa, A.; Alves, M.; Tovar, E. | C97: 2006 | D97: Euromicro Conference on Real-Time Systems (ECRTS) | E97: =--(ROW(A97)<>MATCH(A97,$A:$A,0)) -> 0 | F97: =IF(COUNTIF('Start Set'!A:A, A97) > 0, 1, 0) -> 0 | G97: =IF(COUNTIF('Iteration 1 - Forward'!A:A, A97) > 0, 1, 0) -> 0 | H97: 1
A98: Reliability concerns in embedded system designs | B98: Narayanan, V.; Xie, Y. | C98: 2006 | D98: IEEE Computer | E98: =--(ROW(A98)<>MATCH(A98,$A:$A,0)) -> 0 | F98: =IF(COUNTIF('Start Set'!A:A, A98) > 0, 1, 0) -> 0 | G98: =IF(COUNTIF('Iteration 1 - Forward'!A:A, A98) > 0, 1, 0) -> 0 | H98: 1
A99: Cross-level sensor network simulation with COOJA | B99: Osterlind, F.; Dunkels, A.; Eriksson, J.; Finne, N.; Voigt, T. | C99: 2006 | D99: IEEE Conference on Local Computer Networks (LCN) | E99: =--(ROW(A99)<>MATCH(A99,$A:$A,0)) -> 0 | F99: =IF(COUNTIF('Start Set'!A:A, A99) > 0, 1, 0) -> 0 | G99: =IF(COUNTIF('Iteration 1 - Forward'!A:A, A99) > 0, 1, 0) -> 0 | H99: 1
A100: Performance analysis of slotted carrier sense IEEE 802.15.4 medium access layer | B100: Pollin, S.; Ergen, M.; Ergen, S.; Bougard, B.; De Perre, L.; et al. | C100: 2006 | D100: IEEE Global Communications Conference (GLOBECOM) | E100: =--(ROW(A100)<>MATCH(A100,$A:$A,0)) -> 0 | F100: =IF(COUNTIF('Start Set'!A:A, A100) > 0, 1, 0) -> 0 | G100: =IF(COUNTIF('Iteration 1 - Forward'!A:A, A100) > 0, 1, 0) -> 0 | H100: 1
A101: Worst case end-to-end response times of flows scheduled with FP/FIFO | B101: Martin, S.; Minet, P. | C101: 2006 | D101: IEEE ICN/ICMCL | E101: =--(ROW(A101)<>MATCH(A101,$A:$A,0)) -> 0 | F101: =IF(COUNTIF('Start Set'!A:A, A101) > 0, 1, 0) -> 0 | G101: =IF(COUNTIF('Iteration 1 - Forward'!A:A, A101) > 0, 1, 0) -> 0 | H101: 1
A102: Network-aware operator placement for stream-processing systems | B102: Pietzuch, P.; Ledlie, J.; Shneidman, J.; Roussopoulos, M.; Welsh, M.; Seltzer, M. | C102: 2006 | D102: IEEE International Conference on Data Engineering (ICDE) | E102: =--(ROW(A102)<>MATCH(A102,$A:$A,0)) -> 0 | F102: =IF(COUNTIF('Start Set'!A:A, A102) > 0, 1, 0) -> 0 | G102: =IF(COUNTIF('Iteration 1 - Forward'!A:A, A102) > 0, 1, 0) -> 0 | H102: 1
A103: Predictable interrupt management for real time kernels over conventional PC hardware | B103: Leyva-del Foyo, L.E.; Mejia-Alvarez, P.; de Niz, D. | C103: 2006 | D103: IEEE RTAS | E103: =--(ROW(A103)<>MATCH(A103,$A:$A,0)) -> 0 | F103: =IF(COUNTIF('Start Set'!A:A, A103) > 0, 1, 0) -> 0 | G103: =IF(COUNTIF('Iteration 1 - Forward'!A:A, A103) > 0, 1, 0) -> 0 | H103: 1
... A112: Crowded spectrum in wireless sensor networks | B112: Zhou, G.; Stankovic, J.A.; Son, S.H. | C112: 2006 | D112: Workshop on Embedded Networked Sensors (EmNets) | E112: =--(ROW(A112)<>MATCH(A112,$A:$A,0)) -> 0 | F112: =IF(COUNTIF('Start Set'!A:A, A112) > 0, 1, 0) -> 0 | G112: =IF(COUNTIF('Iteration 1 - Forward'!A:A, A112) > 0, 1, 0) -> 0 | H112: 1
A113: Modern Communications Jamming Principles and Techniques | B113: Poisel, R.A. | C113: 2006 | D113: Artech House | E113: =--(ROW(A113)<>MATCH(A113,$A:$A,0)) -> 0 | F113: =IF(COUNTIF('Start Set'!A:A, A113) > 0, 1, 0) -> 0 | G113: =IF(COUNTIF('Iteration 1 - Forward'!A:A, A113) > 0, 1, 0) -> 0 | H113: 1 | I113: 1
A114: IEEE 802.15.4-2006 Standard for WPANs | C114: 2006 | D114: IEEE Standard | E114: =--(ROW(A114)<>MATCH(A114,$A:$A,0)) -> 0 | F114: =IF(COUNTIF('Start Set'!A:A, A114) > 0, 1, 0) -> 0 | G114: =IF(COUNTIF('Iteration 1 - Forward'!A:A, A114) > 0, 1, 0) -> 0 | H114: 1 | I114: 1
A115: RFC 4689 – Terminology for Benchmarking Network-layer Traffic Control Mechanisms | B115: Poretsky, S.; Perser, J.; Erramilli, S.; Khurana, S. | C115: 2006 | D115: IETF RFC | E115: =--(ROW(A115)<>MATCH(A115,$A:$A,0)) -> 0 | F115: =IF(COUNTIF('Start Set'!A:A, A115) > 0, 1, 0) -> 0 | G115: =IF(COUNTIF('Iteration 1 - Forward'!A:A, A115) > 0, 1, 0) -> 0 | H115: 1 | I115: 1
A116: Clairvoyant: A comprehensive source-level debugger for wireless sensor networks | B116: Yang, J.; Soffa, M.L.; Selavo, L.; Whitehouse, K. | C116: 2007 | D116: ACM SenSys | E116: =--(ROW(A116)<>MATCH(A116,$A:$A,0)) -> 0 | F116: =IF(COUNTIF('Start Set'!A:A, A116) > 0, 1, 0) -> 0 | G116: =IF(COUNTIF('Iteration 1 - Forward'!A:A, A116) > 0, 1, 0) -> 0 | H116: 1
A117: SIRAP: A synchronization protocol for hierarchical resource sharing in real-time open systems | B117: Behnam, M.; Shin, I.; Nolte, T.; Nolin, M. | C117: 2007 | D117: ACM/IEEE EMSOFT | E117: =--(ROW(A117)<>MATCH(A117,$A:$A,0)) -> 0 | F117: =IF(COUNTIF('Start Set'!A:A, A117) > 0, 1, 0) -> 0 | G117: =IF(COUNTIF('Iteration 1 - Forward'!A:A, A117) > 0, 1, 0) -> 0 | H117: 1
A118: Optimal jamming attacks and network defense policies in wireless sensor networks | B118: Li, M.; Koutsopoulos, I.; Poovendran, R. | C118: 2007 | D118: IEEE INFOCOM | E118: =--(ROW(A118)<>MATCH(A118,$A:$A,0)) -> 0 | F118: =IF(COUNTIF('Start Set'!A:A, A118) > 0, 1, 0) -> 0 | G118: =IF(COUNTIF('Iteration 1 - Forward'!A:A, A118) > 0, 1, 0) -> 0 | H118: 1
A119: A comprehensive worst-case calculus for wireless sensor networks with in-network processing | B119: Schmitt, J.B.; Zdarsky, F.A.; Thiele, L. | C119: 2007 | D119: IEEE Real-Time Systems Symposium (RTSS) | E119: =--(ROW(A119)<>MATCH(A119,$A:$A,0)) -> 0 | F119: =IF(COUNTIF('Start Set'!A:A, A119) > 0, 1, 0) -> 0 | G119: =IF(COUNTIF('Iteration 1 - Forward'!A:A, A119) > 0, 1, 0) -> 0 | H119: 1
A120: A coexistence model of IEEE 802.15.4 and IEEE 802.11 B/G | B120: Yuan, W.; Wang, X.; Linnartz, J.-P.M. | C120: 2007 | D120: IEEE Symposium on Communications and Vehicular Technology (SCVT) | E120: =--(ROW(A120)<>MATCH(A120,$A:$A,0)) -> 0 | F120: =IF(COUNTIF('Start Set'!A:A, A120) > 0, 1, 0) -> 0 | G120: =IF(COUNTIF('Iteration 1 - Forward'!A:A, A120) > 0, 1, 0) -> 0 | H120: 1
A121: Power control by geometric programming | B121: Chiang, M.; Tan, C.-W.; Palomar, D.P.; O’Neill, D.; Julian, D. | C121: 2007 | D121: IEEE Transactions on Wireless Communications | E121: =--(ROW(A121)<>MATCH(A121,$A:$A,0)) -> 0 | F121: =IF(COUNTIF('Start Set'!A:A, A121) > 0, 1, 0) -> 0 | G121: =IF(COUNTIF('Iteration 1 - Forward'!A:A, A121) > 0, 1, 0) -> 0 | H121: 1
A122: Energy and delay trade-off of the GTS allocation mechanism in IEEE 802.15.4 for wireless sensor networks | B122: Koubâa, A.; Alves, M.; Tovar, E. | C122: 2007 | D122: International Journal of Communication Systems | E122: =--(ROW(A122)<>MATCH(A122,$A:$A,0)) -> 0 | F122: =IF(COUNTIF('Start Set'!A:A, A122) > 0, 1, 0) -> 0 | G122: =IF(COUNTIF('Iteration 1 - Forward'!A:A, A122) > 0, 1, 0) -> 0 | H122: 1
...

Sheet Finesort 1
A1: F/B | B1: Title | C1: Authors | D1: Year | E1: Venue | F1: Source 1 | G1: Source 2 | H1: Comment | I1: Numerical | J1: Alfabetical
A2: B | B2: A systematic survey of Industrial Internet of Things Security: Requirements and Fog Computing opportunities | C2: Tange, K.; De Donno, M.; Fafoutis, X.; Dragoni, N. | D2: 2020 | E2: IEEE Communications Surveys & Tutorials | F2: x | G2: x | H2: No Use Case+Req | I2: 0 | J2: 0
A3: B | B3: Challenges and opportunities in securing the industrial internet of things | C3: Serror, M.; Hack, S.; Henze, M.; Schuba, M.; Wehrle, K. | D3: 2020 | E3: IEEE Transactions on Industrial Informatics | F3: TABLE I COMPARISON B ETWEEN CONSUMER AND IIOT | G3: x | H3: No Use Case+Req | I3: 1 | J3: 1
A4: B | B4: Emerging wireless technologies for Internet of Things applications: Opportunities and challenges | C4: Mollah, M.B.; Zeadally, S.; Azad, M.A.K. | D4: 2020 | E4: Encyclopedia of Wireless Networks (Springer) | F4: x | G4: x | H4: Not Peer-Rev. Conf./Jour. | I4: 0 | J4: 1
A5: B | B5: Evaluation of Multi-Connectivity Schemes for URLLC Traffic over WiFi and LTE | C5: Suer, M.-T.; et al. | D5: 2020 | E5: IEEE WCNC | F5: TABLE I: QoS requirements for industrial applications as defined by 3GPP [3]. | G5: TABLE II: Requirements for URLLC for industrial applications as specified by Industry 4.0 Forum [5]. | H5: Not IoT | I5: 1 | J5: 0
A6: B | B6: Measures to Improve the Accuracy and Reliability of Clock Synchronization in Time-Sensitive Networking | C6: Zhu, H.; Liu, K.; Yan, Y.; Zhang, H.; Huang, T. | D6: 2020 | E6: IEEE Access | F6: TABLE 1. Comparison of several clock synchronization methods. | G6: x | H6: Not IoT | I6: 1 | J6: 0
A7: B | B7: Visible light communication in 6G: Advances challenges and prospects | C7: Chi, N.; Zhou, Y.; Wei, Y.; Hu, F. | D7: 2020 | E7: IEEE Vehicular Technology Magazine | F7: Figure 7 The distribution demands of VLC transmission distances and data transmission rates in different application fields. V2X: vehicle to everything. | G7: x | H7: Not IoT | I7: 1 | J7: 0
A8: B | B8: A survey of 802.15. 4 TSCH schedulers for a standardized industrial Internet of Things | C8: AR Urke, Ø Kure, K Øvsthus | D8: 2021 | E8: Sensors | F8: x | G8: x | H8: Duplicate | I8: 1 | J8: 0
A9: B | B9: A garden of cyber physical systems: Requirements challenges and implementation aspects | C9: Demir, M.O.; Pusane, A.E.; Dartmann, G.; Ascheid, G.; Kurt, G.K. | D9: 2020 | E9: IEEE Internet of Things Magazine | F9: Figure 3. Flowers of the CPS applications. Their leaves and length of roots indicate the specific requirements of application: a) IWSNs; b) smart grid; c) smart healthcare; d) V2X communications. | G9: x | H9: No Use Case+Req | I9: 0 | J9: 1
A10: B | B10: Performance of 5G Trials for Industrial Automation | C10: Ansari, J.; et al. | D10: 2022 | E10: Electronics | F10: Table 1 | G10: x | H10: Not IoT, MDPI Q2 | I10: 1 | J10: 0
A12: F | B12: MAC protocols for industrial delay-sensitive applications in industry 4.0: Exploring challenges protocols and requirements | C12: A Chehri | D12: 2021 | E12: Procedia Computer Science (Elsevier) | F12: x | G12: x | H12: Not Peer-Rev. Conf./Jour. | I12: x
A13: F | B13: Smart Factory based on IIoT: Applications Communication Networks and Cybersecurity | C13: YS Sheet, MY Thanoun | D13: 2024 | E13: International Journal of … (ResearchGate) | F13: x | G13: x | H13: Not Peer-Rev. Conf./Jour. | I13: 1 | J13: 1
A14: F | B14: Subcarrier power control for URLLC communication system via multi-agent deep reinforcement learning in IoT network | C14: H Wang, X Li, F Luo, J Li | D14: 2024 | E14: International Journal of (Inderscience) | F14: x | G14: x | H14: Not Peer-Rev. Conf./Jour. | I14: 1 | J14: 0
A15: F | B15: Toward Low-Latency Cross-Modal Communication: A Flexible Prediction Scheme | C15: Y Chen, P Li, A Li, D Wu, L Zhou… | D15: 2024 | E15: IEEE Transactions on … | F15: TABLE I COMPARISON OF BASIC R EQUIREMENTS FOR DIFFERENT MULTI-MODAL SERVICES | G15: Fig. 1. Two challenging problems for prediction in cross-modal communication. Firstly, the prediction framework lacks the flexibility to be applied to multi-modal services with diversity. Secondly, it is difficult to fully explore and effectively utilize the correlation features of multi-modal signals for accurate cross-modal signal prediction. | H15: Not IoT | I15: 1 | J15: 0
A16: F | B16: Delay and reliability analysis of p-persistent carrier sense multiple access for multi-event industrial wireless sensor networks | C16: NTT Hang, NC Trinh, NT Ban, M Raza… | D16: 2020 | E16: IEEE Sensors Journal | F16: TABLE I QOS REQUIREMENTS FOR DIFFERENT PRIORITY APPLICATIONS | G16: x | H16: Not IoT | I16: 1 | J16: 1
A17: F | B17: Cloud–fog automation: Heterogenous applications over new-generation infrastructure of virtualized computing and converged networks | C17: H Lyu, J Yan, J Zhang, Z Pang, G Yang… | D17: 2024 | E17: IEEE Industrial Electronics Magazine | F17: FIGURE 3 – The selected representative automation application cases for Cloud-Fog Automation verification. | G17: x | H17: Not IoT | I17: 1 | J17: 0
A19: B | B19: Comparing Wi-Fi 6 and 5G Downlink Performance for Industrial IoT | C19: Maldonado, R.; et al. | D19: 2021 | E19: IEEE Access | F19: TABLE 1. Considered IIoT reference applications, example use-cases could be motion control (I), collaborative AGVs or robotic control (II and III), and asset/process monitoring or autonomous AGVs (IV). | G19: x | H19: OK | I19: 1 | J19: 0
A20: B | B20: Investigating messaging protocols for the Internet of Things (IoT) | C20: Al-Masri, E.; Kalyanam, K.R.; Batts, J.; Kim, J.; Singh, S.; Vo, T.; Yan, C. | D20: 2020 | E20: IEEE Access | F20: TABLE 2. IoT application range requirements [120]–[123], [130]–[140]. | G20: x | H20: OK | I20: 1 | J20: 0
A22: F | B22: Real-time performance of industrial IoT communication technologies: A review | C22: I Behnke, H Austad | D22: 2023 | E22: IEEE Internet of Things Journal | F22: TABLE I IIOT SCENARIO CLASSES | G22: x | H22: OK, has mapped use case -> technologies already | I22: 0 | J22: 1
A23: F | B23: A survey of 802.15.4 TSCH schedulers for a standardized Industrial Internet of Things | C23: Urke, A.R.; Kure, Ø.; Øvsthus, K. | D23: 2022 | E23: Sensors | F23: Table 1 | G23: x | H23: OK, MDPI Q1 | I23: 1 | J23: 0
A24: F | B24: Intelligent and low overhead network synchronization for large-scale industrial IoT systems in the 6G era | C24: X Wang, P Jia, X Shen, HV Poor | D24: 2022 | E24: IEEE Network | F24: TABLE 1. Application-dependent synchronization requirements in large-scale IIoT systems. | G24: x | H24: OK | I24: 1 | J24: 0
A25: F | B25: The computing continuum: Past present and future | C25: LF Bittencourt, R Rodrigues-Filho, J Spillner… | D25: 2025 | E25: Computer Science Review | F25: Table 4 Expected requirements for emerging use cases | G25: Table 3 Distributed computing infrastructures in an updated, snapshot perspective: how each type of system currently presents itself to the users in terms of access latency, location of the infrastructure, computational and storage capacity, what is the cost to access each infrastructure, connectivity/reliability, and if the expected performance guarantees for each type of system. | H25: OK | I25: 1 | J25: 0
A26: F | B26: URLLC and eMBB in 5G industrial IoT: A survey | C26: BS Khan, S Jangsher, A Ahmed | D26: 2022 | E26: IEEE Open Journal of the Communications Society | F26: TABLE 4. URLLC and eMBB based B5G-IIoT applications; Lat.: latency, Rel.: reliability, Tp.: throughput, cell dens.: cell density. | G26: x | H26: OK | I26: 1 | J26: 0
A27: F | B27: Strategies for assuring low latency scalability and interoperability in edge computing and TSN networks for critical IIoT services | C27: DL Gomez, GA Montoya, C Lozano-Garzon | D27: 2023 | E27: IEEE Access | F27: TABLE 1. Network requirements for industrial services [3]. | G27: x | H27: OK | I27: 1 | J27: 0
B29: =SUM(1191+568) -> 1759 | C29: Unique rows checked

Sheet Iteration 2 - Forward-Forward
A1: Title | B1: Authors | C1: Year | D1: Venue | E1: D | F1: DS | G1: DF | H1: DB | I1: EC1 | J1: EC2 | K1: EC3 | L1: EC4 | M1: EC5 | N1: EC6 | O1: IC1
A2: 基于增强型最大比例混合接收机的硅基调制器线性度补偿方法 | B2: 秦军， 陶源盛， 金明， 韩昌灏， 李月琴， 孙剑… | C2: 2023 | D2: Acta Optica … | E2: =--(ROW(A2)<>MATCH(A2,$A:$A,0)) -> 0 | F2: =IF(COUNTIF('Start Set'!A:A, A2) > 0, 1, 0) -> 0 | G2: =IF(COUNTIF('Iteration 1 - Forward'!A:A, A2) > 0, 1, 0) -> 0 | H2: =IF(COUNTIF('Iteration 1 - Backward'!A:A, A2) > 0, 1, 0) -> 0 | L2: 1
A3: PrioMQTT: A prioritized version of the MQTT protocol | B3: G Patti; L Leonardi; G Testa; LL Bello | C3: 2024 | D3: Computer Communications (Elsevier) | E3: =--(ROW(A3)<>MATCH(A3,$A:$A,0)) -> 0 | F3: =IF(COUNTIF('Start Set'!A:A, A3) > 0, 1, 0) -> 1 | G3: =IF(COUNTIF('Iteration 1 - Forward'!A:A, A3) > 0, 1, 0) -> 1 | H3: =IF(COUNTIF('Iteration 1 - Backward'!A:A, A3) > 0, 1, 0) -> 0
A4: A Dynamic IIoT Framework Based on the Publish–Subscribe Paradigm | B4: I Ungurean; NC Gaitan | C4: 2023 | D4: Sensors (MDPI) | E4: =--(ROW(A4)<>MATCH(A4,$A:$A,0)) -> 0 | F4: =IF(COUNTIF('Start Set'!A:A, A4) > 0, 1, 0) -> 0 | G4: =IF(COUNTIF('Iteration 1 - Forward'!A:A, A4) > 0, 1, 0) -> 1 | H4: =IF(COUNTIF('Iteration 1 - Backward'!A:A, A4) > 0, 1, 0) -> 0
A5: Subcarrier power control for URLLC communication system via multi-agent deep reinforcement learning in IoT network | B5: H Wang, X Li, F Luo, J Li… | C5: 2024 | D5: International Journal of … | E5: =--(ROW(A5)<>MATCH(A5,$A:$A,0)) -> 0 | F5: =IF(COUNTIF('Start Set'!A:A, A5) > 0, 1, 0) -> 0 | G5: =IF(COUNTIF('Iteration 1 - Forward'!A:A, A5) > 0, 1, 0) -> 1 | H5: =IF(COUNTIF('Iteration 1 - Backward'!A:A, A5) > 0, 1, 0) -> 0
A6: Robust Networked Control Adopting Prediction-Compensation Mechanism for IoT-Based Building Field-Level Control Concerning Network Uncertainties | B6: X Li, H Li, J Cao, S Wang | C6: 2025 | D6: IEEE Internet of Things Journal | E6: =--(ROW(A6)<>MATCH(A6,$A:$A,0)) -> 0 | F6: =IF(COUNTIF('Start Set'!A:A, A6) > 0, 1, 0) -> 0 | G6: =IF(COUNTIF('Iteration 1 - Forward'!A:A, A6) > 0, 1, 0) -> 1 | H6: =IF(COUNTIF('Iteration 1 - Backward'!A:A, A6) > 0, 1, 0) -> 0
A7: Beyond diagonal RIS-aided wireless communications systems: State-of-the-art and future research directions | B7: O Maraqa, MH Khoshafa, OO Oyerinde… | C7: 2025 | D7: arXiv preprint | E7: =--(ROW(A7)<>MATCH(A7,$A:$A,0)) -> 0 | F7: =IF(COUNTIF('Start Set'!A:A, A7) > 0, 1, 0) -> 0 | G7: =IF(COUNTIF('Iteration 1 - Forward'!A:A, A7) > 0, 1, 0) -> 0 | H7: =IF(COUNTIF('Iteration 1 - Backward'!A:A, A7) > 0, 1, 0) -> 0 | J7: 1
A8: Edge General Intelligence Through World Models and Agentic AI: Fundamentals, Solutions, and Challenges | B8: C Zhao, G Liu, R Zhang, Y Liu, J Wang, J Kang… | C8: 2025 | D8: arXiv preprint | E8: =--(ROW(A8)<>MATCH(A8,$A:$A,0)) -> 0 | F8: =IF(COUNTIF('Start Set'!A:A, A8) > 0, 1, 0) -> 0 | G8: =IF(COUNTIF('Iteration 1 - Forward'!A:A, A8) > 0, 1, 0) -> 0 | H8: =IF(COUNTIF('Iteration 1 - Backward'!A:A, A8) > 0, 1, 0) -> 0 | J8: 1
A9: Failure analysis in next-generation critical cellular communication infrastructures | B9: S Bi; X Yuan; S Hu; K Li; W Ni; E Hossain | C9: 2024 | D9: arXiv preprint arXiv | E9: =--(ROW(A9)<>MATCH(A9,$A:$A,0)) -> 0 | F9: =IF(COUNTIF('Start Set'!A:A, A9) > 0, 1, 0) -> 0 | G9: =IF(COUNTIF('Iteration 1 - Forward'!A:A, A9) > 0, 1, 0) -> 0 | H9: =IF(COUNTIF('Iteration 1 - Backward'!A:A, A9) > 0, 1, 0) -> 0 | J9: 1
A10: A Comprehensive Survey of 5G URLLC and Challenges in the 6G Era | B10: ME Haque, F Tariq, MRA Khandaker… | C10: 2025 | D10: arXiv preprint arXiv … | E10: =--(ROW(A10)<>MATCH(A10,$A:$A,0)) -> 0 | F10: =IF(COUNTIF('Start Set'!A:A, A10) > 0, 1, 0) -> 0 | G10: =IF(COUNTIF('Iteration 1 - Forward'!A:A, A10) > 0, 1, 0) -> 0 | H10: =IF(COUNTIF('Iteration 1 - Backward'!A:A, A10) > 0, 1, 0) -> 0 | J10: 1
A11: Performance analysis of UAV-assisted RF-UOWC systems | B11: T Devaja, M Petkovic, M Beko… | C11: 2024 | D11: arXiv preprint arXiv … | E11: =--(ROW(A11)<>MATCH(A11,$A:$A,0)) -> 0 | F11: =IF(COUNTIF('Start Set'!A:A, A11) > 0, 1, 0) -> 0 | G11: =IF(COUNTIF('Iteration 1 - Forward'!A:A, A11) > 0, 1, 0) -> 0 | H11: =IF(COUNTIF('Iteration 1 - Backward'!A:A, A11) > 0, 1, 0) -> 0 | J11: 1
A12: Communication Architecture for Autonomous Power-to-X Platforms: Enhancing Inspection and Operation With Legged Robots and 5G | B12: P Frank, F Dettinger, D Dittler, P Häbig, N Jazdi… | C12: 2025 | D12: arXiv preprint arXiv … | E12: =--(ROW(A12)<>MATCH(A12,$A:$A,0)) -> 0 | F12: =IF(COUNTIF('Start Set'!A:A, A12) > 0, 1, 0) -> 0 | G12: =IF(COUNTIF('Iteration 1 - Forward'!A:A, A12) > 0, 1, 0) -> 0 | H12: =IF(COUNTIF('Iteration 1 - Backward'!A:A, A12) > 0, 1, 0) -> 0 | J12: 1
A13: Energy, Scalability, Data and Security in Massive IoT: Current Landscape and Future Directions | B13: I Cheikh, S Roy, E Sabir, R Aouami | C13: 2025 | D13: arXiv preprint arXiv … | E13: =--(ROW(A13)<>MATCH(A13,$A:$A,0)) -> 0 | F13: =IF(COUNTIF('Start Set'!A:A, A13) > 0, 1, 0) -> 0 | G13: =IF(COUNTIF('Iteration 1 - Forward'!A:A, A13) > 0, 1, 0) -> 0 | H13: =IF(COUNTIF('Iteration 1 - Backward'!A:A, A13) > 0, 1, 0) -> 0 | J13: 1
A14: A Hierarchical Optimization Framework Using Deep Reinforcement Learning for Task-Driven Bandwidth Allocation in 5G Teleoperation | B14: N Golmohammadi, MM Rayguru, S Baidya | C14: 2025 | D14: arXiv preprint arXiv … | E14: =--(ROW(A14)<>MATCH(A14,$A:$A,0)) -> 0 | F14: =IF(COUNTIF('Start Set'!A:A, A14) > 0, 1, 0) -> 0 | G14: =IF(COUNTIF('Iteration 1 - Forward'!A:A, A14) > 0, 1, 0) -> 0 | H14: =IF(COUNTIF('Iteration 1 - Backward'!A:A, A14) > 0, 1, 0) -> 0 | J14: 1
A15: QoS-Aware Proportional Fairness Scheduling for Multi-Flow 5G UEs: A Smart Factory Perspective | B15: M Seliem, U Roedig, C Sreenan, D Pesch | C15: 2025 | D15: arXiv preprint arXiv … | E15: =--(ROW(A15)<>MATCH(A15,$A:$A,0)) -> 0 | F15: =IF(COUNTIF('Start Set'!A:A, A15) > 0, 1, 0) -> 0 | G15: =IF(COUNTIF('Iteration 1 - Forward'!A:A, A15) > 0, 1, 0) -> 0 | H15: =IF(COUNTIF('Iteration 1 - Backward'!A:A, A15) > 0, 1, 0) -> 0 | J15: 1
A16: On Enhancing Network Throughput using Reinforcement Learning in Sliced Testbeds | B16: DP Monteiro, LNFB Saar, LFR Moreira… | C16: 2024 | D16: arXiv preprint arXiv … | E16: =--(ROW(A16)<>MATCH(A16,$A:$A,0)) -> 0 | F16: =IF(COUNTIF('Start Set'!A:A, A16) > 0, 1, 0) -> 0 | G16: =IF(COUNTIF('Iteration 1 - Forward'!A:A, A16) > 0, 1, 0) -> 0 | H16: =IF(COUNTIF('Iteration 1 - Backward'!A:A, A16) > 0, 1, 0) -> 0 | J16: 1
A17: Ultra-reliable low-latency millimeter-wave communications with sliding window network coding | B17: E Dias, D Raposo, H Esfahanizadeh, A Cohen… | C17: 2022 | D17: arXiv preprint arXiv … | E17: =--(ROW(A17)<>MATCH(A17,$A:$A,0)) -> 0 | F17: =IF(COUNTIF('Start Set'!A:A, A17) > 0, 1, 0) -> 0 | G17: =IF(COUNTIF('Iteration 1 - Forward'!A:A, A17) > 0, 1, 0) -> 0 | H17: =IF(COUNTIF('Iteration 1 - Backward'!A:A, A17) > 0, 1, 0) -> 0 | J17: 1
A18: Admission Control with Reconfigurable Intelligent Surfaces for 6G Mobile Edge Computing | B18: Y Zhang, B Xiao, J Sahni, A Valera, W Li… | C18: 2025 | D18: arXiv preprint arXiv … | E18: =--(ROW(A18)<>MATCH(A18,$A:$A,0)) -> 0 | F18: =IF(COUNTIF('Start Set'!A:A, A18) > 0, 1, 0) -> 0 | G18: =IF(COUNTIF('Iteration 1 - Forward'!A:A, A18) > 0, 1, 0) -> 0 | H18: =IF(COUNTIF('Iteration 1 - Backward'!A:A, A18) > 0, 1, 0) -> 0 | J18: 1
... A25: Exploring Scientific Principles and Laws of Artificial Intelligence, World Model, and Artificial General Intelligence (AGI) in Future Intelligence Networking | B25: D Zhang; W Shi; X Jia | C25: 2025 | D25: Authorea Preprints (TechRxiv) | E25: =--(ROW(A25)<>MATCH(A25,$A:$A,0)) -> 0 | F25: =IF(COUNTIF('Start Set'!A:A, A25) > 0, 1, 0) -> 0 | G25: =IF(COUNTIF('Iteration 1 - Forward'!A:A, A25) > 0, 1, 0) -> 0 | H25: =IF(COUNTIF('Iteration 1 - Backward'!A:A, A25) > 0, 1, 0) -> 0 | J25: 1
A26: OFFLOADING DE APLICAÇÕES ESTRUTURADAS COMO DAGS PARA A BORDA DA REDE | B26: GFC de Queiroz | C26: 2024 | D26: cos.ufrj.br | E26: =--(ROW(A26)<>MATCH(A26,$A:$A,0)) -> 0 | F26: =IF(COUNTIF('Start Set'!A:A, A26) > 0, 1, 0) -> 0 | G26: =IF(COUNTIF('Iteration 1 - Forward'!A:A, A26) > 0, 1, 0) -> 0 | H26: =IF(COUNTIF('Iteration 1 - Backward'!A:A, A26) > 0, 1, 0) -> 0 | L26: 1
A27: Ultra-Reliable and Resilient Communication Service for Cyber-Physical Systems | B27: M Ganjalizadeh | C27: 2023 | D27: diva-portal.org | E27: =--(ROW(A27)<>MATCH(A27,$A:$A,0)) -> 0 | F27: =IF(COUNTIF('Start Set'!A:A, A27) > 0, 1, 0) -> 0 | G27: =IF(COUNTIF('Iteration 1 - Forward'!A:A, A27) > 0, 1, 0) -> 0 | H27: =IF(COUNTIF('Iteration 1 - Backward'!A:A, A27) > 0, 1, 0) -> 0 | J27: 1
A28: АНАЛИЗ ПОКАЗАТЕЛЕЙ ЭФФЕКТИВНОСТИ ПЕРЕДАЧИ ШИРОКОПОЛОСНОГО ТРАФИКА ПРИ ПРИОРИТЕТНЫХ СЕССИЯХ С НИЗКОЙ ЗАДЕРЖКОЙ В … | B28: КА Леонтьева; ЕД Макеева; ОД Лизюра | C28: 2023 | D28: elibrary.ru | E28: =--(ROW(A28)<>MATCH(A28,$A:$A,0)) -> 0 | F28: =IF(COUNTIF('Start Set'!A:A, A28) > 0, 1, 0) -> 0 | G28: =IF(COUNTIF('Iteration 1 - Forward'!A:A, A28) > 0, 1, 0) -> 0 | H28: =IF(COUNTIF('Iteration 1 - Backward'!A:A, A28) > 0, 1, 0) -> 0 | L28: 1
A29: Towards Accessible and Inclusive Remote Musical Interactions | B29: M Sacchetto | C29: 2025 | D29: PhD Thesis (depositolegale.it) | E29: =--(ROW(A29)<>MATCH(A29,$A:$A,0)) -> 0 | F29: =IF(COUNTIF('Start Set'!A:A, A29) > 0, 1, 0) -> 0 | G29: =IF(COUNTIF('Iteration 1 - Forward'!A:A, A29) > 0, 1, 0) -> 0 | H29: =IF(COUNTIF('Iteration 1 - Backward'!A:A, A29) > 0, 1, 0) -> 0 | J29: 1
A30: Sistema SCADA para mejorar el proceso de filtrado y extracción de agua en una empresa agroindustrial en Olmos | B30: CR Aguilar García; MC Maquén Perleche | C30: 2025 | D30: Repositorio UNPRG (Peru) | E30: =--(ROW(A30)<>MATCH(A30,$A:$A,0)) -> 0 | F30: =IF(COUNTIF('Start Set'!A:A, A30) > 0, 1, 0) -> 0 | G30: =IF(COUNTIF('Iteration 1 - Forward'!A:A, A30) > 0, 1, 0) -> 0 | H30: =IF(COUNTIF('Iteration 1 - Backward'!A:A, A30) > 0, 1, 0) -> 0 | L30: 1
A31: Caracterización y análisis de rendimiento del protocolo Zenoh para su aplicación a entornos IIoT | B31: M Barón Herrá | C31: 2024 | D31: repositorio.unican.es | E31: =--(ROW(A31)<>MATCH(A31,$A:$A,0)) -> 0 | F31: =IF(COUNTIF('Start Set'!A:A, A31) > 0, 1, 0) -> 0 | G31: =IF(COUNTIF('Iteration 1 - Forward'!A:A, A31) > 0, 1, 0) -> 0 | H31: =IF(COUNTIF('Iteration 1 - Backward'!A:A, A31) > 0, 1, 0) -> 0 | L31: 1
A32: Privatna 5G mreža zasnovana na programski definiranom radio uređaju | B32: T Karimović | C32: 2023 | D32: repozitorij.unios.hr | E32: =--(ROW(A32)<>MATCH(A32,$A:$A,0)) -> 0 | F32: =IF(COUNTIF('Start Set'!A:A, A32) > 0, 1, 0) -> 0 | G32: =IF(COUNTIF('Iteration 1 - Forward'!A:A, A32) > 0, 1, 0) -> 0 | H32: =IF(COUNTIF('Iteration 1 - Backward'!A:A, A32) > 0, 1, 0) -> 0 | L32: 1
A33: URLLC in Next-Generation Wireless Networks: Current Progress and Open Challenges | B33: A Saeed | C33: 2025 | D33: techrxiv.org | E33: =--(ROW(A33)<>MATCH(A33,$A:$A,0)) -> 0 | F33: =IF(COUNTIF('Start Set'!A:A, A33) > 0, 1, 0) -> 0 | G33: =IF(COUNTIF('Iteration 1 - Forward'!A:A, A33) > 0, 1, 0) -> 0 | H33: =IF(COUNTIF('Iteration 1 - Backward'!A:A, A33) > 0, 1, 0) -> 0 | J33: 1
A34: Task-oriented communication for edge intelligence enabled connected robotics systems | B34: Y Diao | C34: 2025 | D34: theses.gla.ac.uk | E34: =--(ROW(A34)<>MATCH(A34,$A:$A,0)) -> 0 | F34: =IF(COUNTIF('Start Set'!A:A, A34) > 0, 1, 0) -> 0 | G34: =IF(COUNTIF('Iteration 1 - Forward'!A:A, A34) > 0, 1, 0) -> 0 | H34: =IF(COUNTIF('Iteration 1 - Backward'!A:A, A34) > 0, 1, 0) -> 0 | J34: 1
A35: DISEÑO CONCEPTUAL DE UNA LÍNEA PILOTO DE INDUSTRIA 4.0 PARA LA CAPACITACIÓN Y LA INVESTIGACIÓN | B35: T Pérez Sosa; R Quiza Sardiñas; M Rivas Santana | C35: 2025 | D35: Universidad de Matanzas (rein.umcc.cu) | E35: =--(ROW(A35)<>MATCH(A35,$A:$A,0)) -> 0 | F35: =IF(COUNTIF('Start Set'!A:A, A35) > 0, 1, 0) -> 0 | G35: =IF(COUNTIF('Iteration 1 - Forward'!A:A, A35) > 0, 1, 0) -> 0 | H35: =IF(COUNTIF('Iteration 1 - Backward'!A:A, A35) > 0, 1, 0) -> 0 | L35: 1
A36: Contribution to the enhancement of IoT-based application development and optimization of underwater communications, by artificial intelligence, edge … | B36: JC Cepeda Pacheco | C36: 2024 | D36: Universitat Politècnica de Catalunya | E36: =--(ROW(A36)<>MATCH(A36,$A:$A,0)) -> 0 | F36: =IF(COUNTIF('Start Set'!A:A, A36) > 0, 1, 0) -> 0 | G36: =IF(COUNTIF('Iteration 1 - Forward'!A:A, A36) > 0, 1, 0) -> 0 | H36: =IF(COUNTIF('Iteration 1 - Backward'!A:A, A36) > 0, 1, 0) -> 0 | J36: 1
A37: Sicurezza e safety in ambienti industriali basati su IoT | B37: F Tommasin | D37: University of Padova (thesis.unipd.it) | E37: =--(ROW(A37)<>MATCH(A37,$A:$A,0)) -> 0 | F37: =IF(COUNTIF('Start Set'!A:A, A37) > 0, 1, 0) -> 0 | G37: =IF(COUNTIF('Iteration 1 - Forward'!A:A, A37) > 0, 1, 0) -> 0 | H37: =IF(COUNTIF('Iteration 1 - Backward'!A:A, A37) > 0, 1, 0) -> 0 | L37: 1
A38: 실외 디지털트윈을 활용하는 캠퍼스 특화망 구성 및 전송 성능 최적화 방안 | B38: 고제우; 이정윤; 노현석; 성원진 | C38: 2023 | D38: 한국통신학회 학술대회논문집 (dbpia.co.kr) | E38: =--(ROW(A38)<>MATCH(A38,$A:$A,0)) -> 0 | F38: =IF(COUNTIF('Start Set'!A:A, A38) > 0, 1, 0) -> 0 | G38: =IF(COUNTIF('Iteration 1 - Forward'!A:A, A38) > 0, 1, 0) -> 0 | H38: =IF(COUNTIF('Iteration 1 - Backward'!A:A, A38) > 0, 1, 0) -> 0 | L38: 1
A39: Enhancing Reliability and Energy Efficiency for IndustrialIoT Using IRSA-PSO | B39: WJ Ryu, JH Lee, JH Yu, DS Kim | C39: 2023 | D39: 한국통신학회논문지 | E39: =--(ROW(A39)<>MATCH(A39,$A:$A,0)) -> 0 | F39: =IF(COUNTIF('Start Set'!A:A, A39) > 0, 1, 0) -> 0 | G39: =IF(COUNTIF('Iteration 1 - Forward'!A:A, A39) > 0, 1, 0) -> 0 | H39: =IF(COUNTIF('Iteration 1 - Backward'!A:A, A39) > 0, 1, 0) -> 0 | L39: 1
A40: URLLC in Future Wireless Systems: Achievements, Gaps, and the Path Forward | B40: A Saeed | D40: academia.edu | E40: =--(ROW(A40)<>MATCH(A40,$A:$A,0)) -> 0 | F40: =IF(COUNTIF('Start Set'!A:A, A40) > 0, 1, 0) -> 0 | G40: =IF(COUNTIF('Iteration 1 - Forward'!A:A, A40) > 0, 1, 0) -> 0 | H40: =IF(COUNTIF('Iteration 1 - Backward'!A:A, A40) > 0, 1, 0) -> 0 | J40: 1
A41: Resource Allocation and Adaptive Channel Scheduling for 5G New Radio | B41: S Pandit, A Kumar | C41: 2024 | D41: ir.juit.ac.in | E41: =--(ROW(A41)<>MATCH(A41,$A:$A,0)) -> 0 | F41: =IF(COUNTIF('Start Set'!A:A, A41) > 0, 1, 0) -> 0 | G41: =IF(COUNTIF('Iteration 1 - Forward'!A:A, A41) > 0, 1, 0) -> 0 | H41: =IF(COUNTIF('Iteration 1 - Backward'!A:A, A41) > 0, 1, 0) -> 0 | J41: 1
A42: Iterative decoding of short low-density parity-check codes based on differential evolution | B42: M Shtompel, S Prykhodko | C42: 2024 | D42: lib.kart.edu.ua | E42: =--(ROW(A42)<>MATCH(A42,$A:$A,0)) -> 0 | F42: =IF(COUNTIF('Start Set'!A:A, A42) > 0, 1, 0) -> 0 | G42: =IF(COUNTIF('Iteration 1 - Forward'!A:A, A42) > 0, 1, 0) -> 0 | H42: =IF(COUNTIF('Iteration 1 - Backward'!A:A, A42) > 0, 1, 0) -> 0 | J42: 1
A43: Advancements in Ultra-Reliable Low-Latency Communication (URLLC) and Integrated Sensing and Communication (ISAC) in the 6G Era | B43: HA Jasim, SA Khudhair, NK Aljbur, W Fadhil | D43: magazine.iuc.edu.iq | E43: =--(ROW(A43)<>MATCH(A43,$A:$A,0)) -> 0 | F43: =IF(COUNTIF('Start Set'!A:A, A43) > 0, 1, 0) -> 0 | G43: =IF(COUNTIF('Iteration 1 - Forward'!A:A, A43) > 0, 1, 0) -> 0 | H43: =IF(COUNTIF('Iteration 1 - Backward'!A:A, A43) > 0, 1, 0) -> 0 | J43: 1
A44: Artificial Intelligence (AI)-enabled Smart Radio Environments for 6G Wireless Networks | B44: F Kavehmadavani | C44: 2024 | D44: orbilu.uni.lu | E44: =--(ROW(A44)<>MATCH(A44,$A:$A,0)) -> 0 | F44: =IF(COUNTIF('Start Set'!A:A, A44) > 0, 1, 0) -> 0 | G44: =IF(COUNTIF('Iteration 1 - Forward'!A:A, A44) > 0, 1, 0) -> 0 | H44: =IF(COUNTIF('Iteration 1 - Backward'!A:A, A44) > 0, 1, 0) -> 0 | J44: 1
A45: Analytical evaluation of the performance of a high-loaded 5G-IoT ecosystem functioning | B45: V Kovtun, O Kovtun, M Yukhimchuk | C45: 2025 | D45: ceur-ws.org | E45: =--(ROW(A45)<>MATCH(A45,$A:$A,0)) -> 0 | F45: =IF(COUNTIF('Start Set'!A:A, A45) > 0, 1, 0) -> 0 | G45: =IF(COUNTIF('Iteration 1 - Forward'!A:A, A45) > 0, 1, 0) -> 0 | H45: =IF(COUNTIF('Iteration 1 - Backward'!A:A, A45) > 0, 1, 0) -> 0 | J45: 1
A46: Orchestrating a Smart Agriculture System with Optimized Sensor Allocations and Heterogeneous Wireless Coverage | B46: MH Naeem; MA El-Khoreby; HM ELAttar | C46: 2025 | D46: Cureus (ResearchGate) | E46: =--(ROW(A46)<>MATCH(A46,$A:$A,0)) -> 0 | F46: =IF(COUNTIF('Start Set'!A:A, A46) > 0, 1, 0) -> 0 | G46: =IF(COUNTIF('Iteration 1 - Forward'!A:A, A46) > 0, 1, 0) -> 0 | H46: =IF(COUNTIF('Iteration 1 - Backward'!A:A, A46) > 0, 1, 0) -> 0 | J46: 1
A47: The Internet of Things and Real-Time Process Monitoring | B47: SK Basu; R Mandal; A Kar; S Patra | C47: 2026 | D47: IGI Global – Navigating Digital Transformation | E47: =--(ROW(A47)<>MATCH(A47,$A:$A,0)) -> 0 | F47: =IF(COUNTIF('Start Set'!A:A, A47) > 0, 1, 0) -> 0 | G47: =IF(COUNTIF('Iteration 1 - Forward'!A:A, A47) > 0, 1, 0) -> 0 | H47: =IF(COUNTIF('Iteration 1 - Backward'!A:A, A47) > 0, 1, 0) -> 0 | J47: 1
A48: Transforming Business Process Management Through Artificial Intelligence and Predictive Analytics | B48: R Murugan | C48: 2026 | D48: IGI Global – Navigating Digital Transformation | E48: =--(ROW(A48)<>MATCH(A48,$A:$A,0)) -> 0 | F48: =IF(COUNTIF('Start Set'!A:A, A48) > 0, 1, 0) -> 0 | G48: =IF(COUNTIF('Iteration 1 - Forward'!A:A, A48) > 0, 1, 0) -> 0 | H48: =IF(COUNTIF('Iteration 1 - Backward'!A:A, A48) > 0, 1, 0) -> 0 | J48: 1
A49: Real-Time Communication Protocols for IoT and Wireless Sensor Networks: A Short Survey | B49: V Stangaciu | C49: 2025 | D49: IntechOpen | E49: =--(ROW(A49)<>MATCH(A49,$A:$A,0)) -> 0 | F49: =IF(COUNTIF('Start Set'!A:A, A49) > 0, 1, 0) -> 0 | G49: =IF(COUNTIF('Iteration 1 - Forward'!A:A, A49) > 0, 1, 0) -> 0 | H49: =IF(COUNTIF('Iteration 1 - Backward'!A:A, A49) > 0, 1, 0) -> 0 | J49: 1
A50: Performance Evaluation of Managed Switch Configurations for Secure and Efficient PLC-Based Industrial Automation Networks | B50: A Salama | C50: 2025 | D50: ProQuest Thesis | E50: =--(ROW(A50)<>MATCH(A50,$A:$A,0)) -> 0 | F50: =IF(COUNTIF('Start Set'!A:A, A50) > 0, 1, 0) -> 0 | G50: =IF(COUNTIF('Iteration 1 - Forward'!A:A, A50) > 0, 1, 0) -> 0 | H50: =IF(COUNTIF('Iteration 1 - Backward'!A:A, A50) > 0, 1, 0) -> 0 | J50: 1
A51: 6G Cellular Networks: Mapping the Landscape for the IMT-2030 Framework | B51: E Hossain, A Vera-Rivera | D51: researchgate.net | E51: =--(ROW(A51)<>MATCH(A51,$A:$A,0)) -> 0 | F51: =IF(COUNTIF('Start Set'!A:A, A51) > 0, 1, 0) -> 0 | G51: =IF(COUNTIF('Iteration 1 - Forward'!A:A, A51) > 0, 1, 0) -> 0 | H51: =IF(COUNTIF('Iteration 1 - Backward'!A:A, A51) > 0, 1, 0) -> 0 | J51: 1
A52: A survey of generative adversarial network on next generation network | B52: G Heidary, B Masoudi, N Karimi, R Alipour, AP Rabiei… | D52: researchgate.net | E52: =--(ROW(A52)<>MATCH(A52,$A:$A,0)) -> 0 | F52: =IF(COUNTIF('Start Set'!A:A, A52) > 0, 1, 0) -> 0 | G52: =IF(COUNTIF('Iteration 1 - Forward'!A:A, A52) > 0, 1, 0) -> 0 | H52: =IF(COUNTIF('Iteration 1 - Backward'!A:A, A52) > 0, 1, 0) -> 0 | J52: 1
A53: IoT Technologies and Wireless | B53: B Singh, PK Dubey, V Kumar, AK Dubey | D53: researchgate.net | E53: =--(ROW(A53)<>MATCH(A53,$A:$A,0)) -> 0 | F53: =IF(COUNTIF('Start Set'!A:A, A53) > 0, 1, 0) -> 0 | G53: =IF(COUNTIF('Iteration 1 - Forward'!A:A, A53) > 0, 1, 0) -> 0 | H53: =IF(COUNTIF('Iteration 1 - Backward'!A:A, A53) > 0, 1, 0) -> 0 | J53: 1
A54: Private 5G Networks: Multi-connectivity Driven Aggregation for Services, Deployment and Management | B54: H Frank | C54: 2024 | D54: research-information.bris.ac.uk | E54: =--(ROW(A54)<>MATCH(A54,$A:$A,0)) -> 0 | F54: =IF(COUNTIF('Start Set'!A:A, A54) > 0, 1, 0) -> 0 | G54: =IF(COUNTIF('Iteration 1 - Forward'!A:A, A54) > 0, 1, 0) -> 0 | H54: =IF(COUNTIF('Iteration 1 - Backward'!A:A, A54) > 0, 1, 0) -> 0 | J54: 1
A55: Device Management in the Internet of Medical Things: A Systematic Review | B55: M Ostermann; O Freyer; F Jahed; S Gilbert | C55: 2024 | D55: ResearchSquare preprint | E55: =--(ROW(A55)<>MATCH(A55,$A:$A,0)) -> 0 | F55: =IF(COUNTIF('Start Set'!A:A, A55) > 0, 1, 0) -> 0 | G55: =IF(COUNTIF('Iteration 1 - Forward'!A:A, A55) > 0, 1, 0) -> 0 | H55: =IF(COUNTIF('Iteration 1 - Backward'!A:A, A55) > 0, 1, 0) -> 0 | J55: 1
A56: Secure Data Transmission and Message Authentication Codes for Industrial Automation and Control Systems | B56: HB Lekkala; VV Bandari | C56: 2024 | D56: SSRN preprint | E56: =--(ROW(A56)<>MATCH(A56,$A:$A,0)) -> 0 | F56: =IF(COUNTIF('Start Set'!A:A, A56) > 0, 1, 0) -> 0 | G56: =IF(COUNTIF('Iteration 1 - Forward'!A:A, A56) > 0, 1, 0) -> 0 | H56: =IF(COUNTIF('Iteration 1 - Backward'!A:A, A56) > 0, 1, 0) -> 0 | J56: 1
A57: Multi-Access Edge Computing for Mobile Robots | B57: P Sossalla | C57: 2025 | D57: tud.qucosa.de | E57: =--(ROW(A57)<>MATCH(A57,$A:$A,0)) -> 0 | F57: =IF(COUNTIF('Start Set'!A:A, A57) > 0, 1, 0) -> 0 | G57: =IF(COUNTIF('Iteration 1 - Forward'!A:A, A57) > 0, 1, 0) -> 0 | H57: =IF(COUNTIF('Iteration 1 - Backward'!A:A, A57) > 0, 1, 0) -> 0 | J57: 1
A58: Multi-Dimensional QoS and Collaborative Mac Layer Design for Dense Diverse and Dynamic IoT Network | B58: J Bai | C58: 2023 | E58: =--(ROW(A58)<>MATCH(A58,$A:$A,0)) -> 0 | F58: =IF(COUNTIF('Start Set'!A:A, A58) > 0, 1, 0) -> 0 | G58: =IF(COUNTIF('Iteration 1 - Forward'!A:A, A58) > 0, 1, 0) -> 0 | H58: =IF(COUNTIF('Iteration 1 - Backward'!A:A, A58) > 0, 1, 0) -> 0 | J58: 1
A59: RSA-DLT for Secure and Privacy-Preserving 6G Communications | B59: D Amer, MAN Shukur, HA Mohammed… | C59: 0 | D59: ssrn.com | E59: =--(ROW(A59)<>MATCH(A59,$A:$A,0)) -> 0 | F59: =IF(COUNTIF('Start Set'!A:A, A59) > 0, 1, 0) -> 0 | G59: =IF(COUNTIF('Iteration 1 - Forward'!A:A, A59) > 0, 1, 0) -> 0 | H59: =IF(COUNTIF('Iteration 1 - Backward'!A:A, A59) > 0, 1, 0) -> 0 | K59: 1
A60: Ultra-reliable low-latency communications: Foundations, enablers, system design, and evolution towards 6G | B60: NH Mahmood, I Atzeni, EA Jorswieck… | C60: 2023 | D60: … and Trends® in … | E60: =--(ROW(A60)<>MATCH(A60,$A:$A,0)) -> 0 | F60: =IF(COUNTIF('Start Set'!A:A, A60) > 0, 1, 0) -> 0 | G60: =IF(COUNTIF('Iteration 1 - Forward'!A:A, A60) > 0, 1, 0) -> 0 | H60: =IF(COUNTIF('Iteration 1 - Backward'!A:A, A60) > 0, 1, 0) -> 0 | K60: 1
A61: 5 Applications of Wireless | B61: PK Dubey, B Singh, V Kumar… | C61: 2023 | D61: AI-Aided IoT … | E61: =--(ROW(A61)<>MATCH(A61,$A:$A,0)) -> 0 | F61: =IF(COUNTIF('Start Set'!A:A, A61) > 0, 1, 0) -> 0 | G61: =IF(COUNTIF('Iteration 1 - Forward'!A:A, A61) > 0, 1, 0) -> 0 | H61: =IF(COUNTIF('Iteration 1 - Backward'!A:A, A61) > 0, 1, 0) -> 0 | K61: 1
A62: Applications of Wireless, 5G, 6G, and Internet of Things Technologies | B62: PK Dubey, B Singh, V Kumar… | C62: 2023 | D62: AI-Aided IoT Technologies … | E62: =--(ROW(A62)<>MATCH(A62,$A:$A,0)) -> 0 | F62: =IF(COUNTIF('Start Set'!A:A, A62) > 0, 1, 0) -> 0 | G62: =IF(COUNTIF('Iteration 1 - Forward'!A:A, A62) > 0, 1, 0) -> 0 | H62: =IF(COUNTIF('Iteration 1 - Backward'!A:A, A62) > 0, 1, 0) -> 0 | K62: 1
A63: 5G-AIoT artificial intelligence of things: opportunity and challenges | B63: DA Milovanovic, V Pantovic | C63: 2023 | D63: Driving 5G Mobile Communications … | E63: =--(ROW(A63)<>MATCH(A63,$A:$A,0)) -> 0 | F63: =IF(COUNTIF('Start Set'!A:A, A63) > 0, 1, 0) -> 0 | G63: =IF(COUNTIF('Iteration 1 - Forward'!A:A, A63) > 0, 1, 0) -> 0 | H63: =IF(COUNTIF('Iteration 1 - Backward'!A:A, A63) > 0, 1, 0) -> 0 | K63: 1
A64: 5G Ultrareliable and Low-Latency Communication in Vertical Domain Expansion | B64: DA Milovanovic, ZS Bojkovic | C64: 2023 | D64: Driving 5G Mobile Communications … | E64: =--(ROW(A64)<>MATCH(A64,$A:$A,0)) -> 0 | F64: =IF(COUNTIF('Start Set'!A:A, A64) > 0, 1, 0) -> 0 | G64: =IF(COUNTIF('Iteration 1 - Forward'!A:A, A64) > 0, 1, 0) -> 0 | H64: =IF(COUNTIF('Iteration 1 - Backward'!A:A, A64) > 0, 1, 0) -> 0 | K64: 1
A65: 6 5G-AIoT Artificial | B65: DA Milovanovic, V Pantovic | C65: 2023 | D65: Driving 5G Mobile Communications … | E65: =--(ROW(A65)<>MATCH(A65,$A:$A,0)) -> 0 | F65: =IF(COUNTIF('Start Set'!A:A, A65) > 0, 1, 0) -> 0 | G65: =IF(COUNTIF('Iteration 1 - Forward'!A:A, A65) > 0, 1, 0) -> 0 | H65: =IF(COUNTIF('Iteration 1 - Backward'!A:A, A65) > 0, 1, 0) -> 0 | K65: 1
A66: 5G Advanced Mobile Broadband: New Multimedia Delivery Platform | B66: DA Milovanovic, ZS Bojkovic | C66: 2023 | D66: Driving 5G Mobile Communications … | E66: =--(ROW(A66)<>MATCH(A66,$A:$A,0)) -> 0 | F66: =IF(COUNTIF('Start Set'!A:A, A66) > 0, 1, 0) -> 0 | G66: =IF(COUNTIF('Iteration 1 - Forward'!A:A, A66) > 0, 1, 0) -> 0 | H66: =IF(COUNTIF('Iteration 1 - Backward'!A:A, A66) > 0, 1, 0) -> 0 | K66: 1
A67: A Bandwidth and Gain Enhanced Hexagonal Patch Antenna using Hexagonal Shape SRR | B67: HH Ryanu, S Hafizha, A Maulani… | C67: 2024 | D67: JURNAL … | E67: =--(ROW(A67)<>MATCH(A67,$A:$A,0)) -> 0 | F67: =IF(COUNTIF('Start Set'!A:A, A67) > 0, 1, 0) -> 0 | G67: =IF(COUNTIF('Iteration 1 - Forward'!A:A, A67) > 0, 1, 0) -> 0 | H67: =IF(COUNTIF('Iteration 1 - Backward'!A:A, A67) > 0, 1, 0) -> 0 | K67: 1
A68: A Comprehensive Survey of DoS/DDoS | B68: SS Mahdi, AA Abdullah, SA Hussein… | C68: 2025 | D68: Proceedings of Data … | E68: 1 | F68: =IF(COUNTIF('Start Set'!A:A, A68) > 0, 1, 0) -> 0 | G68: =IF(COUNTIF('Iteration 1 - Forward'!A:A, A68) > 0, 1, 0) -> 0 | H68: =IF(COUNTIF('Iteration 1 - Backward'!A:A, A68) > 0, 1, 0) -> 0 | K68: 1
A69: A Comprehensive Survey of DoS/DDoS Detection Methods for Enhanced Security in 5G Network Slicing | B69: SS Mahdi, AA Abdullah, SA Hussein, S Ali | C69: 2024 | D69: International Conference on … | E69: =--(ROW(A69)<>MATCH(A69,$A:$A,0)) -> 0 | F69: =IF(COUNTIF('Start Set'!A:A, A69) > 0, 1, 0) -> 0 | G69: =IF(COUNTIF('Iteration 1 - Forward'!A:A, A69) > 0, 1, 0) -> 0 | H69: =IF(COUNTIF('Iteration 1 - Backward'!A:A, A69) > 0, 1, 0) -> 0 | K69: 1
A70: A Deep Learning Framework for Blockage Mitigation in mmWave Wireless | B70: AH Almutairi | C70: 2024 | D70: search.proquest.com | E70: =--(ROW(A70)<>MATCH(A70,$A:$A,0)) -> 0 | F70: =IF(COUNTIF('Start Set'!A:A, A70) > 0, 1, 0) -> 0 | G70: =IF(COUNTIF('Iteration 1 - Forward'!A:A, A70) > 0, 1, 0) -> 0 | H70: =IF(COUNTIF('Iteration 1 - Backward'!A:A, A70) > 0, 1, 0) -> 0 | J70: 1
A71: Attacks Against Industrial Control Systems in Wireless Networks | B71: MA Azeez, S Katzenbeisser, E Geloczi | C71: 2025 | D71: ssrn.com | E71: =--(ROW(A71)<>MATCH(A71,$A:$A,0)) -> 0 | F71: =IF(COUNTIF('Start Set'!A:A, A71) > 0, 1, 0) -> 0 | G71: =IF(COUNTIF('Iteration 1 - Forward'!A:A, A71) > 0, 1, 0) -> 0 | H71: =IF(COUNTIF('Iteration 1 - Backward'!A:A, A71) > 0, 1, 0) -> 0 | J71: 1
A72: Cross-Technology Interference-Aware Rate Adaptation in Time-Triggered Wireless Local Area Networks | B72: H Kim; YJ Kim; WT Kim | C72: 2025 | D72: Applied Sciences (MDPI) | E72: =--(ROW(A72)<>MATCH(A72,$A:$A,0)) -> 0 | F72: =IF(COUNTIF('Start Set'!A:A, A72) > 0, 1, 0) -> 0 | G72: =IF(COUNTIF('Iteration 1 - Forward'!A:A, A72) > 0, 1, 0) -> 0 | H72: =IF(COUNTIF('Iteration 1 - Backward'!A:A, A72) > 0, 1, 0) -> 0 | K72: 1
A73: Deep Reinforcement Learning Implementation for Video Transmission Optimization in New Generation Networks | B73: A del Río Ponce | C73: 2024 | D73: oa.upm.es | E73: =--(ROW(A73)<>MATCH(A73,$A:$A,0)) -> 0 | F73: =IF(COUNTIF('Start Set'!A:A, A73) > 0, 1, 0) -> 0 | G73: =IF(COUNTIF('Iteration 1 - Forward'!A:A, A73) > 0, 1, 0) -> 0 | H73: =IF(COUNTIF('Iteration 1 - Backward'!A:A, A73) > 0, 1, 0) -> 0 | K73: 1
A74: Design of Efficient Signal Detection Schemes for Large-Scale MU-MIMO System | B74: NR Challa, K Bagadi, V Annepu… | C74: 2024 | D74: 5G and Beyond … | E74: =--(ROW(A74)<>MATCH(A74,$A:$A,0)) -> 0 | F74: =IF(COUNTIF('Start Set'!A:A, A74) > 0, 1, 0) -> 0 | G74: =IF(COUNTIF('Iteration 1 - Forward'!A:A, A74) > 0, 1, 0) -> 0 | H74: =IF(COUNTIF('Iteration 1 - Backward'!A:A, A74) > 0, 1, 0) -> 0 | K74: 1
A75: Design strategy for narrowband internet of things with its scope and challenges of security solutions | B75: R Reshma, N Mohanasundaram… | C75: 2025 | D75: Smart Factories for … | E75: =--(ROW(A75)<>MATCH(A75,$A:$A,0)) -> 0 | F75: =IF(COUNTIF('Start Set'!A:A, A75) > 0, 1, 0) -> 0 | G75: =IF(COUNTIF('Iteration 1 - Forward'!A:A, A75) > 0, 1, 0) -> 0 | H75: =IF(COUNTIF('Iteration 1 - Backward'!A:A, A75) > 0, 1, 0) -> 0 | K75: 1
A76: Dynamic Puncturing for eMBB and URLLC Services in UAV Wireless Networks based on SDN | B76: MA Ouamri, A Bounceur, Y Himeur, MY Saidi… | C76: 2025 | D76: ssrn.com | E76: =--(ROW(A76)<>MATCH(A76,$A:$A,0)) -> 0 | F76: =IF(COUNTIF('Start Set'!A:A, A76) > 0, 1, 0) -> 0 | G76: =IF(COUNTIF('Iteration 1 - Forward'!A:A, A76) > 0, 1, 0) -> 0 | H76: =IF(COUNTIF('Iteration 1 - Backward'!A:A, A76) > 0, 1, 0) -> 0 | K76: 1
A77: Dynamic sleep strategy for gNBs in ultra-dense networks based on multilevel sleep modes and load-balancing associations | B77: D Lei, H Tian | C77: 2024 | D77: 4th International Conference on Internet of … | E77: =--(ROW(A77)<>MATCH(A77,$A:$A,0)) -> 0 | F77: =IF(COUNTIF('Start Set'!A:A, A77) > 0, 1, 0) -> 0 | G77: =IF(COUNTIF('Iteration 1 - Forward'!A:A, A77) > 0, 1, 0) -> 0 | H77: =IF(COUNTIF('Iteration 1 - Backward'!A:A, A77) > 0, 1, 0) -> 0 | K77: 1
A78: Evolution and advancements in fifth generation (5G) systems: A comprehensive overview | B78: AM Al-Saegh, AT Mohammed, TA Elwi | C78: 2024 | D78: AIP Conference Proceedings | E78: =--(ROW(A78)<>MATCH(A78,$A:$A,0)) -> 0 | F78: =IF(COUNTIF('Start Set'!A:A, A78) > 0, 1, 0) -> 0 | G78: =IF(COUNTIF('Iteration 1 - Forward'!A:A, A78) > 0, 1, 0) -> 0 | H78: =IF(COUNTIF('Iteration 1 - Backward'!A:A, A78) > 0, 1, 0) -> 0 | J78: 1
A79: Optimization of Resource Scheduling in the Coexistence of eMBB and uRLLC for 5G Networks: A Comprehensive Performance Evaluation | B79: R Chandrasekhar, P Singh | C79: 2025 | D79: Recent Trends in Intelligent Systems … | E79: =--(ROW(A79)<>MATCH(A79,$A:$A,0)) -> 0 | F79: =IF(COUNTIF('Start Set'!A:A, A79) > 0, 1, 0) -> 0 | G79: =IF(COUNTIF('Iteration 1 - Forward'!A:A, A79) > 0, 1, 0) -> 0 | H79: =IF(COUNTIF('Iteration 1 - Backward'!A:A, A79) > 0, 1, 0) -> 0 | J79: 1
A80: Fundamental Limits of Ultra-Reliable Low-Latency Communication | B80: AO Kislal | C80: 2024 | D80: search.proquest.com | E80: =--(ROW(A80)<>MATCH(A80,$A:$A,0)) -> 0 | F80: =IF(COUNTIF('Start Set'!A:A, A80) > 0, 1, 0) -> 0 | G80: =IF(COUNTIF('Iteration 1 - Forward'!A:A, A80) > 0, 1, 0) -> 0 | H80: =IF(COUNTIF('Iteration 1 - Backward'!A:A, A80) > 0, 1, 0) -> 0 | J80: 1
A81: Integrating Deep Learning and IoT for Enhanced Monitoring and Sustainable Mining Practices | B81: MN Rahman; K Lo | C81: 2025 | D81: Emerging AI Applications in Earth Sciences (Springer) | E81: =--(ROW(A81)<>MATCH(A81,$A:$A,0)) -> 0 | F81: =IF(COUNTIF('Start Set'!A:A, A81) > 0, 1, 0) -> 0 | G81: =IF(COUNTIF('Iteration 1 - Forward'!A:A, A81) > 0, 1, 0) -> 0 | H81: =IF(COUNTIF('Iteration 1 - Backward'!A:A, A81) > 0, 1, 0) -> 0 | K81: 1
A82: Multi-source energy harvesting for wireless IIoT sensors | B82: SS Spindler, RH Schmitt, D Lange | C82: 2025 | D82: publications.rwth-aachen.de | E82: =--(ROW(A82)<>MATCH(A82,$A:$A,0)) -> 0 | F82: =IF(COUNTIF('Start Set'!A:A, A82) > 0, 1, 0) -> 0 | G82: =IF(COUNTIF('Iteration 1 - Forward'!A:A, A82) > 0, 1, 0) -> 0 | H82: =IF(COUNTIF('Iteration 1 - Backward'!A:A, A82) > 0, 1, 0) -> 0 | J82: 1
A83: Optimization of Resource Scheduling in the Coexistence of eMBB and uRLLC for 5G Networks: A Comprehensive Performance Evaluation | B83: R Chandrasekhar, P Singh | C83: 2024 | D83: International Conference on Intelligent Systems, IoT, and … | E83: =--(ROW(A83)<>MATCH(A83,$A:$A,0)) -> 1 | F83: =IF(COUNTIF('Start Set'!A:A, A83) > 0, 1, 0) -> 0 | G83: =IF(COUNTIF('Iteration 1 - Forward'!A:A, A83) > 0, 1, 0) -> 0 | H83: =IF(COUNTIF('Iteration 1 - Backward'!A:A, A83) > 0, 1, 0) -> 0
A84: QMIDCD: Design of an Efficient QoS-Aware Model for High-Speed IoT D2D Communications Over 5G Deployments | B84: A Venkata Mahesh, S Bhargava | C84: 2024 | D84: International Conference on Smart … | E84: =--(ROW(A84)<>MATCH(A84,$A:$A,0)) -> 0 | F84: =IF(COUNTIF('Start Set'!A:A, A84) > 0, 1, 0) -> 0 | G84: =IF(COUNTIF('Iteration 1 - Forward'!A:A, A84) > 0, 1, 0) -> 0 | H84: =IF(COUNTIF('Iteration 1 - Backward'!A:A, A84) > 0, 1, 0) -> 0 | K84: 1
A85: Shared-resource Generative Adversarial Network (GAN) training for 5g Ultra Reliable Low Latency Communication (URLLC) deep reinforcement learning … | B85: K Mehdipourchari | C85: 2024 | D85: espace.etsmtl.ca | E85: =--(ROW(A85)<>MATCH(A85,$A:$A,0)) -> 0 | F85: =IF(COUNTIF('Start Set'!A:A, A85) > 0, 1, 0) -> 0 | G85: =IF(COUNTIF('Iteration 1 - Forward'!A:A, A85) > 0, 1, 0) -> 0 | H85: =IF(COUNTIF('Iteration 1 - Backward'!A:A, A85) > 0, 1, 0) -> 0 | J85: 1
A86: The computing continuum: Past present and future | B86: LF Bittencourt, R Rodrigues-Filho, J Spillner… | C86: 2025 | D86: Computer Science … | E86: =--(ROW(A86)<>MATCH(A86,$A:$A,0)) -> 0 | F86: =IF(COUNTIF('Start Set'!A:A, A86) > 0, 1, 0) -> 0 | G86: =IF(COUNTIF('Iteration 1 - Forward'!A:A, A86) > 0, 1, 0) -> 1 | H86: =IF(COUNTIF('Iteration 1 - Backward'!A:A, A86) > 0, 1, 0) -> 0
A87: TRACE: A Reference Architecture for Intelligent Logistics Operations in B5G Networks | B87: K Papachristopoulou, T Anagnostopoulos… | C87: 2025 | D87: … Conference on Artificial … | E87: =--(ROW(A87)<>MATCH(A87,$A:$A,0)) -> 0 | F87: =IF(COUNTIF('Start Set'!A:A, A87) > 0, 1, 0) -> 0 | G87: =IF(COUNTIF('Iteration 1 - Forward'!A:A, A87) > 0, 1, 0) -> 0 | H87: =IF(COUNTIF('Iteration 1 - Backward'!A:A, A87) > 0, 1, 0) -> 0 | K87: 1
A88: Age-of-Event Aware: Sampling Period Optimization in a Three-Stage Wireless Cyber-Physical System With Diverse Parallelisms | B88: Y Zhang; M Mei; D Yan; X Zhang | C88: 2024 | D88: IEEE Transactions on … | E88: =--(ROW(A88)<>MATCH(A88,$A:$A,0)) -> 0 | F88: =IF(COUNTIF('Start Set'!A:A, A88) > 0, 1, 0) -> 0 | G88: =IF(COUNTIF('Iteration 1 - Forward'!A:A, A88) > 0, 1, 0) -> 0 | H88: =IF(COUNTIF('Iteration 1 - Backward'!A:A, A88) > 0, 1, 0) -> 0
A89: Design of Efficient Signal Detection Schemes for Large-Scale MU-MIMO System | B89: NR Challa; K Bagadi; V Annepu; KV Chandra | C89: 2025 | D89: 5G and Beyond … (CRC Press) | E89: =--(ROW(A89)<>MATCH(A89,$A:$A,0)) -> 1 | F89: =IF(COUNTIF('Start Set'!A:A, A89) > 0, 1, 0) -> 0 | G89: =IF(COUNTIF('Iteration 1 - Forward'!A:A, A89) > 0, 1, 0) -> 0 | H89: =IF(COUNTIF('Iteration 1 - Backward'!A:A, A89) > 0, 1, 0) -> 0
A90: GA-optimized JT-CoMP F-NOMA in HetNets: Adaptive resource allocation with imperfect SIC | B90: A Akbar, A Ahmed, A Zafar, S Jangsher | C90: 2025 | D90: Physical Communication | E90: =--(ROW(A90)<>MATCH(A90,$A:$A,0)) -> 0 | F90: =IF(COUNTIF('Start Set'!A:A, A90) > 0, 1, 0) -> 0 | G90: =IF(COUNTIF('Iteration 1 - Forward'!A:A, A90) > 0, 1, 0) -> 0 | H90: =IF(COUNTIF('Iteration 1 - Backward'!A:A, A90) > 0, 1, 0) -> 0
A91: A Survey of Scheduling in 5G URLLC and Outlook for Emerging 6G Systems | B91: Y ZHANG | C91: 2023 | D91: pure.hw.ac.uk | E91: 1 | F91: =IF(COUNTIF('Start Set'!A:A, A91) > 0, 1, 0) -> 0 | G91: =IF(COUNTIF('Iteration 1 - Forward'!A:A, A91) > 0, 1, 0) -> 0 | H91: =IF(COUNTIF('Iteration 1 - Backward'!A:A, A91) > 0, 1, 0) -> 0
A92: Experimental 5G Network Performance Analysis in a Semi-Anechoic and Semi-Reverberation Chamber | B92: F Delgado-Ferro, A Ramírez-Arroyo… | C92: 2025 | D92: IEEE … | E92: =--(ROW(A92)<>MATCH(A92,$A:$A,0)) -> 0 | F92: =IF(COUNTIF('Start Set'!A:A, A92) > 0, 1, 0) -> 0 | G92: =IF(COUNTIF('Iteration 1 - Forward'!A:A, A92) > 0, 1, 0) -> 0 | H92: =IF(COUNTIF('Iteration 1 - Backward'!A:A, A92) > 0, 1, 0) -> 0 | M92: 1
A93: Real-time performance evaluation for 5G multi-link communication in industrial application | B93: D Liu; Y Zhao; G Liu; C Wang; L Zhou; Y Qian | C93: 2025 | D93: IEEE Access | E93: =--(ROW(A93)<>MATCH(A93,$A:$A,0)) -> 0 | F93: =IF(COUNTIF('Start Set'!A:A, A93) > 0, 1, 0) -> 0 | G93: =IF(COUNTIF('Iteration 1 - Forward'!A:A, A93) > 0, 1, 0) -> 0 | H93: =IF(COUNTIF('Iteration 1 - Backward'!A:A, A93) > 0, 1, 0) -> 0 | M93: 1
A94: Optimizing Wireless Networks for Automated Guided Vehicles and Remote-Control Systems in Smart Factory | B94: YS Sheet; FS Alsharbaty | C94: 2025 | D94: IEEE Conference on New Industrial Applications | E94: =--(ROW(A94)<>MATCH(A94,$A:$A,0)) -> 0 | F94: =IF(COUNTIF('Start Set'!A:A, A94) > 0, 1, 0) -> 0 | G94: =IF(COUNTIF('Iteration 1 - Forward'!A:A, A94) > 0, 1, 0) -> 0 | H94: =IF(COUNTIF('Iteration 1 - Backward'!A:A, A94) > 0, 1, 0) -> 0 | M94: 1
A95: A Case Study of API Design for Interoperability and Security of the Internet of Things | B95: D Kim; C Lee; H Kim | C95: 2024 | D95: International Conference on Security and Privacy in … | E95: =--(ROW(A95)<>MATCH(A95,$A:$A,0)) -> 0 | F95: =IF(COUNTIF('Start Set'!A:A, A95) > 0, 1, 0) -> 0 | G95: =IF(COUNTIF('Iteration 1 - Forward'!A:A, A95) > 0, 1, 0) -> 0 | H95: =IF(COUNTIF('Iteration 1 - Backward'!A:A, A95) > 0, 1, 0) -> 0 | K95: 1
A96: A Case Study of API Design for Interoperability and Security | B96: D Kim; C Lee; H Kim | C96: 2025 | D96: Security and Privacy in Cyber-Physical … | E96: 1 | F96: =IF(COUNTIF('Start Set'!A:A, A96) > 0, 1, 0) -> 0 | G96: =IF(COUNTIF('Iteration 1 - Forward'!A:A, A96) > 0, 1, 0) -> 0 | H96: =IF(COUNTIF('Iteration 1 - Backward'!A:A, A96) > 0, 1, 0) -> 0
A97: Edge computing in CPS | B97: AA Musa; U Musa; AMVV Sai; W Yu | C97: 2025 | D97: Edge Intelligence in Cyber-Physical … | E97: =--(ROW(A97)<>MATCH(A97,$A:$A,0)) -> 0 | F97: =IF(COUNTIF('Start Set'!A:A, A97) > 0, 1, 0) -> 0 | G97: =IF(COUNTIF('Iteration 1 - Forward'!A:A, A97) > 0, 1, 0) -> 0 | H97: =IF(COUNTIF('Iteration 1 - Backward'!A:A, A97) > 0, 1, 0) -> 0 | J97: 1 | K97: 1
A98: Characterization of Multipath Composition of Sub-6 GHz and mmWave Channels in an Industrial Scenario Using Ray Tracing Simulations | B98: HTP da Silva, RD Gomes | C98: 2024 | D98: biblioteca.sbrt.org.br | E98: =--(ROW(A98)<>MATCH(A98,$A:$A,0)) -> 0 | F98: =IF(COUNTIF('Start Set'!A:A, A98) > 0, 1, 0) -> 0 | G98: =IF(COUNTIF('Iteration 1 - Forward'!A:A, A98) > 0, 1, 0) -> 0 | H98: =IF(COUNTIF('Iteration 1 - Backward'!A:A, A98) > 0, 1, 0) -> 0 | N98: 1
A99: Energy-Delay Optimization for Ultra-Reliable Low Latency Communication | B99: M Alfaqawi, H Ibn-Khedher… | C99: 2022 | D99: 2022 IEEE Symposium … | E99: =--(ROW(A99)<>MATCH(A99,$A:$A,0)) -> 0 | F99: =IF(COUNTIF('Start Set'!A:A, A99) > 0, 1, 0) -> 0 | G99: =IF(COUNTIF('Iteration 1 - Forward'!A:A, A99) > 0, 1, 0) -> 0 | H99: =IF(COUNTIF('Iteration 1 - Backward'!A:A, A99) > 0, 1, 0) -> 0 | N99: 1
A100: Capacity Maximization of the mmWave Networks Deploying Intelligent Reflecting Surfaces: An Enhancement Approach for 6G Internet of Things | B100: M Mahbub, RM Shubair | C100: 2022 | D100: 2022 International Conference on … | E100: =--(ROW(A100)<>MATCH(A100,$A:$A,0)) -> 0 | F100: =IF(COUNTIF('Start Set'!A:A, A100) > 0, 1, 0) -> 0 | G100: =IF(COUNTIF('Iteration 1 - Forward'!A:A, A100) > 0, 1, 0) -> 0 | H100: =IF(COUNTIF('Iteration 1 - Backward'!A:A, A100) > 0, 1, 0) -> 0 | N100: 1
A101: 5G ultra-reliable low-latency communication: Use cases, concepts and challenges | B101: S Akhila | C101: 2023 | D101: 10th International Conference on Computing … | E101: =--(ROW(A101)<>MATCH(A101,$A:$A,0)) -> 0 | F101: =IF(COUNTIF('Start Set'!A:A, A101) > 0, 1, 0) -> 0 | G101: =IF(COUNTIF('Iteration 1 - Forward'!A:A, A101) > 0, 1, 0) -> 0 | H101: =IF(COUNTIF('Iteration 1 - Backward'!A:A, A101) > 0, 1, 0) -> 0 | N101: 1
A102: Slotted aloha for optical wireless communications in internet of underwater things | B102: M Petkovic, SA Tegos… | C102: 2023 | D102: 2023 32nd Wireless … | E102: =--(ROW(A102)<>MATCH(A102,$A:$A,0)) -> 0 | F102: =IF(COUNTIF('Start Set'!A:A, A102) > 0, 1, 0) -> 0 | G102: =IF(COUNTIF('Iteration 1 - Forward'!A:A, A102) > 0, 1, 0) -> 0 | H102: =IF(COUNTIF('Iteration 1 - Backward'!A:A, A102) > 0, 1, 0) -> 0 | N102: 1
A103: URLLC in B5G networks: Use cases, TSN/DetNet extension, and pending issues | B103: AN Abbou, K Samdanis… | C103: 2023 | D103: 2023 33rd International … | E103: =--(ROW(A103)<>MATCH(A103,$A:$A,0)) -> 0 | F103: =IF(COUNTIF('Start Set'!A:A, A103) > 0, 1, 0) -> 0 | G103: =IF(COUNTIF('Iteration 1 - Forward'!A:A, A103) > 0, 1, 0) -> 0 | H103: =IF(COUNTIF('Iteration 1 - Backward'!A:A, A103) > 0, 1, 0) -> 0 | N103: 1
A104: A Study on Adaptive User Equipment Aggregation Mechanism for Future Internet of Things Network | B104: X Zhao, H Chen, R Fang, H Li, T Chen… | C104: 2023 | D104: 2023 3rd International … | E104: =--(ROW(A104)<>MATCH(A104,$A:$A,0)) -> 0 | F104: =IF(COUNTIF('Start Set'!A:A, A104) > 0, 1, 0) -> 0 | G104: =IF(COUNTIF('Iteration 1 - Forward'!A:A, A104) > 0, 1, 0) -> 0 | H104: =IF(COUNTIF('Iteration 1 - Backward'!A:A, A104) > 0, 1, 0) -> 0 | N104: 1
A105: Statistical URLLC provisioning in 6G network over fading channels | B105: RA Lashkarian, A Pourkabirian… | C105: 2023 | D105: 2023 IEEE … | E105: =--(ROW(A105)<>MATCH(A105,$A:$A,0)) -> 0 | F105: =IF(COUNTIF('Start Set'!A:A, A105) > 0, 1, 0) -> 0 | G105: =IF(COUNTIF('Iteration 1 - Forward'!A:A, A105) > 0, 1, 0) -> 0 | H105: =IF(COUNTIF('Iteration 1 - Backward'!A:A, A105) > 0, 1, 0) -> 0 | N105: 1
A106: An intelligent industrial vision scheme for flexible manufacturing based on 5g edge cloud collaboration | B106: Y Shen, Z Zhang, P Ding | C106: 2023 | D106: 2023 IEEE International Symposium … | E106: =--(ROW(A106)<>MATCH(A106,$A:$A,0)) -> 0 | F106: =IF(COUNTIF('Start Set'!A:A, A106) > 0, 1, 0) -> 0 | G106: =IF(COUNTIF('Iteration 1 - Forward'!A:A, A106) > 0, 1, 0) -> 0 | H106: =IF(COUNTIF('Iteration 1 - Backward'!A:A, A106) > 0, 1, 0) -> 0 | M106: 1 | N106: 1
...

Sheet Iteration 2 - Forward-Backward
A1: Title | B1: Authors | C1: Year | D1: Venue | E1: D | F1: DS | G1: DF | H1: DB | I1: DFF | J1: EC1 | K1: EC2 | L1: EC3 | M1: EC4 | N1: EC5 | O1: EC6 | P1: IC1
A2: Specification of Internet transmission control program | B2: V. Cerf, Y. Dalal, C. Sunshine | C2: 1974 | D2: RFC 675 (ETSI) | E2: =--(ROW(A2)<>MATCH(A2,$A:$A,0)) -> 0 | F2: =IF(COUNTIF('Start Set'!A:A, A2) > 0, 1, 0) -> 0 | G2: =IF(COUNTIF('Iteration 1 - Forward'!A:A, A2) > 0, 1, 0) -> 0 | H2: =IF(COUNTIF('Iteration 1 - Backward'!A:A, A2) > 0, 1, 0) -> 0 | I2: =IF(COUNTIF('Iteration 2 - Forward-Forward'!A:A, A2) > 0, 1, 0) -> 0 | J2: 1
A3: Long short-term memory | B3: S. Hochreiter, J. Schmidhuber | C3: 1997 | D3: Neural Comput. | E3: =--(ROW(A3)<>MATCH(A3,$A:$A,0)) -> 0 | F3: =IF(COUNTIF('Start Set'!A:A, A3) > 0, 1, 0) -> 0 | G3: =IF(COUNTIF('Iteration 1 - Forward'!A:A, A3) > 0, 1, 0) -> 0 | H3: =IF(COUNTIF('Iteration 1 - Backward'!A:A, A3) > 0, 1, 0) -> 0 | I3: =IF(COUNTIF('Iteration 2 - Forward-Forward'!A:A, A3) > 0, 1, 0) -> 0 | J3: 1
A4: The MOSIX multicomputer operating system for high performance cluster computing | B4: A. Barak, O. La’adan | C4: 1998 | D4: Future Gener. Comput. Syst. | E4: =--(ROW(A4)<>MATCH(A4,$A:$A,0)) -> 0 | F4: =IF(COUNTIF('Start Set'!A:A, A4) > 0, 1, 0) -> 0 | G4: =IF(COUNTIF('Iteration 1 - Forward'!A:A, A4) > 0, 1, 0) -> 0 | H4: =IF(COUNTIF('Iteration 1 - Backward'!A:A, A4) > 0, 1, 0) -> 0 | I4: =IF(COUNTIF('Iteration 2 - Forward-Forward'!A:A, A4) > 0, 1, 0) -> 0 | J4: 1
A5: The high-performance computing continuum | B5: S. Karin, S. Graham | C5: 1998 | D5: Commun. ACM | E5: =--(ROW(A5)<>MATCH(A5,$A:$A,0)) -> 0 | F5: =IF(COUNTIF('Start Set'!A:A, A5) > 0, 1, 0) -> 0 | G5: =IF(COUNTIF('Iteration 1 - Forward'!A:A, A5) > 0, 1, 0) -> 0 | H5: =IF(COUNTIF('Iteration 1 - Backward'!A:A, A5) > 0, 1, 0) -> 0 | I5: =IF(COUNTIF('Iteration 2 - Forward-Forward'!A:A, A5) > 0, 1, 0) -> 0 | J5: 1
A6: Performance evaluation of four field buses | B6: M. Rubio Benito, J. Fuertes, E. Kahoraho, N. P. Arzoz | C6: 1999 | D6: 7th IEEE International Conference on Emerging Technologies and Factory Automation (ETFA) | E6: =--(ROW(A6)<>MATCH(A6,$A:$A,0)) -> 0 | F6: =IF(COUNTIF('Start Set'!A:A, A6) > 0, 1, 0) -> 0 | G6: =IF(COUNTIF('Iteration 1 - Forward'!A:A, A6) > 0, 1, 0) -> 0 | H6: =IF(COUNTIF('Iteration 1 - Backward'!A:A, A6) > 0, 1, 0) -> 0 | I6: =IF(COUNTIF('Iteration 2 - Forward-Forward'!A:A, A6) > 0, 1, 0) -> 0 | J6: 1
A7: Co-operation and comparison of DiffServ and IntServ: Performance measurements | B7: J. Harju, P. Kivimaki | C7: 2000 | D7: 25th Conference on Local Computer Networks (LCN) | E7: =--(ROW(A7)<>MATCH(A7,$A:$A,0)) -> 0 | F7: =IF(COUNTIF('Start Set'!A:A, A7) > 0, 1, 0) -> 0 | G7: =IF(COUNTIF('Iteration 1 - Forward'!A:A, A7) > 0, 1, 0) -> 0 | H7: =IF(COUNTIF('Iteration 1 - Backward'!A:A, A7) > 0, 1, 0) -> 0 | I7: =IF(COUNTIF('Iteration 2 - Forward-Forward'!A:A, A7) > 0, 1, 0) -> 0 | J7: 1
A8: Beowulf Cluster Computing with Linux | B8: T.L. Sterling | C8: 2002 | D8: MIT Press | E8: =--(ROW(A8)<>MATCH(A8,$A:$A,0)) -> 0 | F8: =IF(COUNTIF('Start Set'!A:A, A8) > 0, 1, 0) -> 0 | G8: =IF(COUNTIF('Iteration 1 - Forward'!A:A, A8) > 0, 1, 0) -> 0 | H8: =IF(COUNTIF('Iteration 1 - Backward'!A:A, A8) > 0, 1, 0) -> 0 | I8: =IF(COUNTIF('Iteration 2 - Forward-Forward'!A:A, A8) > 0, 1, 0) -> 0 | J8: 1
A9: Ubiquitous computing | B9: K. Lyytinen, Y. Yoo | C9: 2002 | D9: Commun. ACM | E9: =--(ROW(A9)<>MATCH(A9,$A:$A,0)) -> 0 | F9: =IF(COUNTIF('Start Set'!A:A, A9) > 0, 1, 0) -> 0 | G9: =IF(COUNTIF('Iteration 1 - Forward'!A:A, A9) > 0, 1, 0) -> 0 | H9: =IF(COUNTIF('Iteration 1 - Backward'!A:A, A9) > 0, 1, 0) -> 0 | I9: =IF(COUNTIF('Iteration 2 - Forward-Forward'!A:A, A9) > 0, 1, 0) -> 0 | J9: 1
A10: Gridsim: A toolkit for the modeling and simulation of distributed resource management and scheduling for grid computing | B10: R. Buyya, M. Murshed | C10: 2002 | D10: Concurr. Comput.: Pract. Exp. | E10: =--(ROW(A10)<>MATCH(A10,$A:$A,0)) -> 0 | F10: =IF(COUNTIF('Start Set'!A:A, A10) > 0, 1, 0) -> 0 | G10: =IF(COUNTIF('Iteration 1 - Forward'!A:A, A10) > 0, 1, 0) -> 0 | H10: =IF(COUNTIF('Iteration 1 - Backward'!A:A, A10) > 0, 1, 0) -> 0 | I10: =IF(COUNTIF('Iteration 2 - Forward-Forward'!A:A, A10) > 0, 1, 0) -> 0 | J10: 1
A11: The fieldbus standards: History and structures | B11: M. Felser | C11: 2002 | D11: Technology Leadership Day (MICROSWISS Network) | E11: =--(ROW(A11)<>MATCH(A11,$A:$A,0)) -> 0 | F11: =IF(COUNTIF('Start Set'!A:A, A11) > 0, 1, 0) -> 0 | G11: =IF(COUNTIF('Iteration 1 - Forward'!A:A, A11) > 0, 1, 0) -> 0 | H11: =IF(COUNTIF('Iteration 1 - Backward'!A:A, A11) > 0, 1, 0) -> 0 | I11: =IF(COUNTIF('Iteration 2 - Forward-Forward'!A:A, A11) > 0, 1, 0) -> 0 | J11: 1
A12: Content delivery networks: status and trends | B12: A. Vakali, G. Pallis | C12: 2003 | D12: IEEE Internet Comput. | E12: =--(ROW(A12)<>MATCH(A12,$A:$A,0)) -> 0 | F12: =IF(COUNTIF('Start Set'!A:A, A12) > 0, 1, 0) -> 0 | G12: =IF(COUNTIF('Iteration 1 - Forward'!A:A, A12) > 0, 1, 0) -> 0 | H12: =IF(COUNTIF('Iteration 1 - Backward'!A:A, A12) > 0, 1, 0) -> 0 | I12: =IF(COUNTIF('Iteration 2 - Forward-Forward'!A:A, A12) > 0, 1, 0) -> 0 | J12: 1
A13: Autonomic computing: An overview | B13: M. Parashar, S. Hariri | C13: 2004 | D13: International Workshop on Unconventional Programming Paradigms | E13: =--(ROW(A13)<>MATCH(A13,$A:$A,0)) -> 0 | F13: =IF(COUNTIF('Start Set'!A:A, A13) > 0, 1, 0) -> 0 | G13: =IF(COUNTIF('Iteration 1 - Forward'!A:A, A13) > 0, 1, 0) -> 0 | H13: =IF(COUNTIF('Iteration 1 - Backward'!A:A, A13) > 0, 1, 0) -> 0 | I13: =IF(COUNTIF('Iteration 2 - Forward-Forward'!A:A, A13) > 0, 1, 0) -> 0 | J13: 1
... A50: Security and privacy challenges in Industrial Internet of Things | B50: A.-R. Sadeghi, C. Wachsmann, M. Waidner | C50: 2015 | D50: DAC: ACM/EDAC/IEEE Design Automation Conference | E50: =--(ROW(A50)<>MATCH(A50,$A:$A,0)) -> 0 | F50: =IF(COUNTIF('Start Set'!A:A, A50) > 0, 1, 0) -> 0 | G50: =IF(COUNTIF('Iteration 1 - Forward'!A:A, A50) > 0, 1, 0) -> 0 | H50: =IF(COUNTIF('Iteration 1 - Backward'!A:A, A50) > 0, 1, 0) -> 1 | I50: =IF(COUNTIF('Iteration 2 - Forward-Forward'!A:A, A50) > 0, 1, 0) -> 0 | J50: 1
A51: Energy consumption optimization in cloud data centers | B51: D. Kliazovich, P. Bouvry, F. Granelli, N.L. da Fonseca | C51: 2015 | D51: Cloud Serv. Netw. Manag. | E51: =--(ROW(A51)<>MATCH(A51,$A:$A,0)) -> 0 | F51: =IF(COUNTIF('Start Set'!A:A, A51) > 0, 1, 0) -> 0 | G51: =IF(COUNTIF('Iteration 1 - Forward'!A:A, A51) > 0, 1, 0) -> 0 | H51: =IF(COUNTIF('Iteration 1 - Backward'!A:A, A51) > 0, 1, 0) -> 0 | I51: =IF(COUNTIF('Iteration 2 - Forward-Forward'!A:A, A51) > 0, 1, 0) -> 0 | J51: 1 | K51: 0
A52: Faster R-CNN: Towards real-time object detection with region proposal networks | B52: S. Ren, K. He, R. Girshick, J. Sun | C52: 2015 | D52: Proc. Adv. Neural Inf. Process. Syst. | E52: =--(ROW(A52)<>MATCH(A52,$A:$A,0)) -> 0 | F52: =IF(COUNTIF('Start Set'!A:A, A52) > 0, 1, 0) -> 0 | G52: =IF(COUNTIF('Iteration 1 - Forward'!A:A, A52) > 0, 1, 0) -> 0 | H52: =IF(COUNTIF('Iteration 1 - Backward'!A:A, A52) > 0, 1, 0) -> 0 | I52: =IF(COUNTIF('Iteration 2 - Forward-Forward'!A:A, A52) > 0, 1, 0) -> 0 | J52: 1 | K52: 0
A53: PISA: Protocol independent switch architecture | B53: N. McKeown | C53: 2015 | D53: P4 Workshop | E53: =--(ROW(A53)<>MATCH(A53,$A:$A,0)) -> 0 | F53: =IF(COUNTIF('Start Set'!A:A, A53) > 0, 1, 0) -> 0 | G53: =IF(COUNTIF('Iteration 1 - Forward'!A:A, A53) > 0, 1, 0) -> 0 | H53: =IF(COUNTIF('Iteration 1 - Backward'!A:A, A53) > 0, 1, 0) -> 0 | I53: =IF(COUNTIF('Iteration 2 - Forward-Forward'!A:A, A53) > 0, 1, 0) -> 0 | J53: 1 | K53: 0
A54: An industrial big data pipeline for data-driven analytics maintenance applications in large-scale smart manufacturing facilities | B54: P. O’Donovan, K. Leahy, K. Bruton, D. O’Sullivan | C54: 2015 | D54: Journal of Big Data | E54: =--(ROW(A54)<>MATCH(A54,$A:$A,0)) -> 0 | F54: =IF(COUNTIF('Start Set'!A:A, A54) > 0, 1, 0) -> 0 | G54: =IF(COUNTIF('Iteration 1 - Forward'!A:A, A54) > 0, 1, 0) -> 0 | H54: =IF(COUNTIF('Iteration 1 - Backward'!A:A, A54) > 0, 1, 0) -> 0 | I54: =IF(COUNTIF('Iteration 2 - Forward-Forward'!A:A, A54) > 0, 1, 0) -> 0 | J54: 1 | K54: 0
A55: On the ergodic capacity of MIMO NOMA systems | B55: Q. Sun, S. Han, C.-L. I, Z. Pan | C55: 2015 | D55: IEEE Wireless Communications Letters | E55: =--(ROW(A55)<>MATCH(A55,$A:$A,0)) -> 0 | F55: =IF(COUNTIF('Start Set'!A:A, A55) > 0, 1, 0) -> 0 | G55: =IF(COUNTIF('Iteration 1 - Forward'!A:A, A55) > 0, 1, 0) -> 0 | H55: =IF(COUNTIF('Iteration 1 - Backward'!A:A, A55) > 0, 1, 0) -> 0 | I55: =IF(COUNTIF('Iteration 2 - Forward-Forward'!A:A, A55) > 0, 1, 0) -> 0 | J55: 1 | K55: 0
A56: CometCloud: Enabling software-defined federations for end-to-end application workflows | B56: J. Diaz-Montes, M. AbdelBaky, M. Zou, M. Parashar | C56: 2015 | D56: IEEE Internet Comput. | E56: =--(ROW(A56)<>MATCH(A56,$A:$A,0)) -> 0 | F56: =IF(COUNTIF('Start Set'!A:A, A56) > 0, 1, 0) -> 0 | G56: =IF(COUNTIF('Iteration 1 - Forward'!A:A, A56) > 0, 1, 0) -> 0 | H56: =IF(COUNTIF('Iteration 1 - Backward'!A:A, A56) > 0, 1, 0) -> 0 | I56: =IF(COUNTIF('Iteration 2 - Forward-Forward'!A:A, A56) > 0, 1, 0) -> 0 | J56: 1 | K56: 0
A57: Deployment strategies for ultra-reliable and low-latency communication in factory automation | B57: N. Brahmi, O. N. C. Yilmaz, K. W. Helmersson, S. A. Ashraf, J. Torsner | C57: 2015 | D57: IEEE GLOBECOM Workshops | E57: =--(ROW(A57)<>MATCH(A57,$A:$A,0)) -> 0 | F57: =IF(COUNTIF('Start Set'!A:A, A57) > 0, 1, 0) -> 0 | G57: =IF(COUNTIF('Iteration 1 - Forward'!A:A, A57) > 0, 1, 0) -> 0 | H57: =IF(COUNTIF('Iteration 1 - Backward'!A:A, A57) > 0, 1, 0) -> 0 | I57: =IF(COUNTIF('Iteration 2 - Forward-Forward'!A:A, A57) > 0, 1, 0) -> 0 | J57: 1 | K57: 0
A58: M2M communications in 3GPP LTE/LTE-A networks: Architectures, service requirements, challenges, and applications | B58: F. Ghavimi, H.-H. Chen | C58: 2015 | D58: IEEE Communications Surveys & Tutorials | E58: =--(ROW(A58)<>MATCH(A58,$A:$A,0)) -> 0 | F58: =IF(COUNTIF('Start Set'!A:A, A58) > 0, 1, 0) -> 0 | G58: =IF(COUNTIF('Iteration 1 - Forward'!A:A, A58) > 0, 1, 0) -> 0 | H58: =IF(COUNTIF('Iteration 1 - Backward'!A:A, A58) > 0, 1, 0) -> 0 | I58: =IF(COUNTIF('Iteration 2 - Forward-Forward'!A:A, A58) > 0, 1, 0) -> 0 | J58: 1 | K58: 0
A59: Large-scale antenna systems with hybrid analog and digital beamforming for millimeter wave 5G | B59: S. Han, C.-L. I, Z. Xu, C. Rowell | C59: 2015 | D59: IEEE Communications Magazine | E59: =--(ROW(A59)<>MATCH(A59,$A:$A,0)) -> 0 | F59: =IF(COUNTIF('Start Set'!A:A, A59) > 0, 1, 0) -> 0 | G59: =IF(COUNTIF('Iteration 1 - Forward'!A:A, A59) > 0, 1, 0) -> 0 | H59: =IF(COUNTIF('Iteration 1 - Backward'!A:A, A59) > 0, 1, 0) -> 0 | I59: =IF(COUNTIF('Iteration 2 - Forward-Forward'!A:A, A59) > 0, 1, 0) -> 0 | J59: 1 | K59: 0
A60: 802.11n performance analysis for a real multimedia industrial application | B60: J. S. Blanes, J. Berenguer-Sebastiá, V. Sempere-Paya, D. T. Ferrandis | C60: 2015 | D60: Computers in Industry | E60: =--(ROW(A60)<>MATCH(A60,$A:$A,0)) -> 0 | F60: =IF(COUNTIF('Start Set'!A:A, A60) > 0, 1, 0) -> 0 | G60: =IF(COUNTIF('Iteration 1 - Forward'!A:A, A60) > 0, 1, 0) -> 0 | H60: =IF(COUNTIF('Iteration 1 - Backward'!A:A, A60) > 0, 1, 0) -> 0 | I60: =IF(COUNTIF('Iteration 2 - Forward-Forward'!A:A, A60) > 0, 1, 0) -> 0 | J60: 1 | K60: 0
A61: Resource management in dense heterogeneous networks | B61: S. M. A. Kazmi, et al. | C61: 2015 | D61: APNOMS (Asia-Pacific Network Operations and Management Symposium) | E61: =--(ROW(A61)<>MATCH(A61,$A:$A,0)) -> 0 | F61: =IF(COUNTIF('Start Set'!A:A, A61) > 0, 1, 0) -> 0 | G61: =IF(COUNTIF('Iteration 1 - Forward'!A:A, A61) > 0, 1, 0) -> 0 | H61: =IF(COUNTIF('Iteration 1 - Backward'!A:A, A61) > 0, 1, 0) -> 0 | I61: =IF(COUNTIF('Iteration 2 - Forward-Forward'!A:A, A61) > 0, 1, 0) -> 0 | J61: 1 | K61: 0
A62: Edge computing: Vision and challenges | B62: W. Shi, J. Cao, Q. Zhang, Y. Li, L. Xu | C62: 2016 | D62: IEEE Internet Things J. | E62: =--(ROW(A62)<>MATCH(A62,$A:$A,0)) -> 0 | F62: =IF(COUNTIF('Start Set'!A:A, A62) > 0, 1, 0) -> 0 | G62: =IF(COUNTIF('Iteration 1 - Forward'!A:A, A62) > 0, 1, 0) -> 0 | H62: =IF(COUNTIF('Iteration 1 - Backward'!A:A, A62) > 0, 1, 0) -> 1 | I62: =IF(COUNTIF('Iteration 2 - Forward-Forward'!A:A, A62) > 0, 1, 0) -> 0 | J62: 1
A63: Low Power Wide Area Networks, NB-IoT and the Internet of Things | B63: P. Chang | C63: 2016 | D63: Online Resource | E63: =--(ROW(A63)<>MATCH(A63,$A:$A,0)) -> 0 | F63: =IF(COUNTIF('Start Set'!A:A, A63) > 0, 1, 0) -> 0 | G63: =IF(COUNTIF('Iteration 1 - Forward'!A:A, A63) > 0, 1, 0) -> 0 | H63: =IF(COUNTIF('Iteration 1 - Backward'!A:A, A63) > 0, 1, 0) -> 0 | I63: =IF(COUNTIF('Iteration 2 - Forward-Forward'!A:A, A63) > 0, 1, 0) -> 0 | J63: 1 | K63: 1
A64: IEEE Standard for Local and Metropolitan Area Networks–Bridges and Bridged Networks-Amendment 25: Enhancements for Scheduled Traffic | B64: M. J. Teener, J. Farkas | C64: 2016 | D64: IEEE 802.1Qbv-2015 | E64: =--(ROW(A64)<>MATCH(A64,$A:$A,0)) -> 0 | F64: =IF(COUNTIF('Start Set'!A:A, A64) > 0, 1, 0) -> 0 | G64: =IF(COUNTIF('Iteration 1 - Forward'!A:A, A64) > 0, 1, 0) -> 0 | H64: =IF(COUNTIF('Iteration 1 - Backward'!A:A, A64) > 0, 1, 0) -> 0 | I64: =IF(COUNTIF('Iteration 2 - Forward-Forward'!A:A, A64) > 0, 1, 0) -> 0 | J64: 1 | K64: 1
A65: State of the art in LP-WAN solutions for industrial IoT services | B65: R. Sanchez-Iborra, M.-D. Cano | C65: 2016 | D65: Sensors | E65: =--(ROW(A65)<>MATCH(A65,$A:$A,0)) -> 0 | F65: =IF(COUNTIF('Start Set'!A:A, A65) > 0, 1, 0) -> 0 | G65: =IF(COUNTIF('Iteration 1 - Forward'!A:A, A65) > 0, 1, 0) -> 0 | H65: =IF(COUNTIF('Iteration 1 - Backward'!A:A, A65) > 0, 1, 0) -> 0 | I65: =IF(COUNTIF('Iteration 2 - Forward-Forward'!A:A, A65) > 0, 1, 0) -> 0 | J65: 1 | K65: 0
A66: Industrial wireless IP-based cyber–physical systems | B66: T. Watteyne et al. | C66: 2016 | D66: Proceedings of the IEEE | E66: =--(ROW(A66)<>MATCH(A66,$A:$A,0)) -> 0 | F66: =IF(COUNTIF('Start Set'!A:A, A66) > 0, 1, 0) -> 0 | G66: =IF(COUNTIF('Iteration 1 - Forward'!A:A, A66) > 0, 1, 0) -> 0 | H66: =IF(COUNTIF('Iteration 1 - Backward'!A:A, A66) > 0, 1, 0) -> 0 | I66: =IF(COUNTIF('Iteration 2 - Forward-Forward'!A:A, A66) > 0, 1, 0) -> 0 | J66: 1 | K66: 0
A67: Full-duplex wireless communications: Challenges, solutions, and future research directions | B67: Z. Zhang, K. Long, A. V. Vasilakos, L. Hanzo | C67: 2016 | D67: Proceedings of the IEEE | E67: =--(ROW(A67)<>MATCH(A67,$A:$A,0)) -> 0 | F67: =IF(COUNTIF('Start Set'!A:A, A67) > 0, 1, 0) -> 0 | G67: =IF(COUNTIF('Iteration 1 - Forward'!A:A, A67) > 0, 1, 0) -> 0 | H67: =IF(COUNTIF('Iteration 1 - Backward'!A:A, A67) > 0, 1, 0) -> 0 | I67: =IF(COUNTIF('Iteration 2 - Forward-Forward'!A:A, A67) > 0, 1, 0) -> 0 | J67: 1 | K67: 0
A68: Creating values out of Internet of Things: An industrial perspective | B68: P. P. Ray | C68: 2016 | D68: Journal of Computer Networks and Communications | E68: =--(ROW(A68)<>MATCH(A68,$A:$A,0)) -> 0 | F68: =IF(COUNTIF('Start Set'!A:A, A68) > 0, 1, 0) -> 0 | G68: =IF(COUNTIF('Iteration 1 - Forward'!A:A, A68) > 0, 1, 0) -> 0 | H68: =IF(COUNTIF('Iteration 1 - Backward'!A:A, A68) > 0, 1, 0) -> 0 | I68: =IF(COUNTIF('Iteration 2 - Forward-Forward'!A:A, A68) > 0, 1, 0) -> 0 | J68: 1 | K68: 0
A69: PAPR reduction and digital predistortion for non-contiguous waveforms with well-localized spectrum | B69: M. Abdelaziz, L. Anttila, M. Renfors, M. Valkama | C69: 2016 | D69: International Symposium on Wireless Communication Systems (ISWCS) | E69: =--(ROW(A69)<>MATCH(A69,$A:$A,0)) -> 0 | F69: =IF(COUNTIF('Start Set'!A:A, A69) > 0, 1, 0) -> 0 | G69: =IF(COUNTIF('Iteration 1 - Forward'!A:A, A69) > 0, 1, 0) -> 0 | H69: =IF(COUNTIF('Iteration 1 - Backward'!A:A, A69) > 0, 1, 0) -> 0 | I69: =IF(COUNTIF('Iteration 2 - Forward-Forward'!A:A, A69) > 0, 1, 0) -> 0 | J69: 1 | K69: 0
A70: EtherCAT network latency analysis | B70: V. Q. Nguyen, J. W. Jeon | C70: 2016 | D70: International Conference on Computing, Communication and Automation (ICCCA) | E70: =--(ROW(A70)<>MATCH(A70,$A:$A,0)) -> 0 | F70: =IF(COUNTIF('Start Set'!A:A, A70) > 0, 1, 0) -> 0 | G70: =IF(COUNTIF('Iteration 1 - Forward'!A:A, A70) > 0, 1, 0) -> 0 | H70: =IF(COUNTIF('Iteration 1 - Backward'!A:A, A70) > 0, 1, 0) -> 0 | I70: =IF(COUNTIF('Iteration 2 - Forward-Forward'!A:A, A70) > 0, 1, 0) -> 0 | J70: 1 | K70: 0
A71: Multi-objective optimization for robust power efficient and secure full-duplex wireless communication systems | B71: Y. Sun, D. W. K. Ng, J. Zhu, R. Schober | C71: 2016 | D71: IEEE Transactions on Wireless Communications | E71: =--(ROW(A71)<>MATCH(A71,$A:$A,0)) -> 0 | F71: =IF(COUNTIF('Start Set'!A:A, A71) > 0, 1, 0) -> 0 | G71: =IF(COUNTIF('Iteration 1 - Forward'!A:A, A71) > 0, 1, 0) -> 0 | H71: =IF(COUNTIF('Iteration 1 - Backward'!A:A, A71) > 0, 1, 0) -> 0 | I71: =IF(COUNTIF('Iteration 2 - Forward-Forward'!A:A, A71) > 0, 1, 0) -> 0 | J71: 1 | K71: 0
A72: Coding in the finite-blocklength regime: Bounds based on Laplace integrals and their asymptotic approximations | B72: T. Erseghe | C72: 2016 | D72: IEEE Transactions on Information Theory | E72: =--(ROW(A72)<>MATCH(A72,$A:$A,0)) -> 0 | F72: =IF(COUNTIF('Start Set'!A:A, A72) > 0, 1, 0) -> 0 | G72: =IF(COUNTIF('Iteration 1 - Forward'!A:A, A72) > 0, 1, 0) -> 0 | H72: =IF(COUNTIF('Iteration 1 - Backward'!A:A, A72) > 0, 1, 0) -> 0 | I72: =IF(COUNTIF('Iteration 2 - Forward-Forward'!A:A, A72) > 0, 1, 0) -> 0 | J72: 1 | K72: 0
A73: Internet of Things in the 5G era: Enablers, architecture, and business models | B73: M. R. Palattella, et al. | C73: 2016 | D73: IEEE Journal on Selected Areas in Communications | E73: =--(ROW(A73)<>MATCH(A73,$A:$A,0)) -> 0 | F73: =IF(COUNTIF('Start Set'!A:A, A73) > 0, 1, 0) -> 0 | G73: =IF(COUNTIF('Iteration 1 - Forward'!A:A, A73) > 0, 1, 0) -> 0 | H73: =IF(COUNTIF('Iteration 1 - Backward'!A:A, A73) > 0, 1, 0) -> 0 | I73: =IF(COUNTIF('Iteration 2 - Forward-Forward'!A:A, A73) > 0, 1, 0) -> 0 | J73: 1 | K73: 0
A74: Ultra-reliable and low-latency communication for wireless factory automation: From LTE to 5G | B74: S. A. Ashraf, I. Aktas, E. Eriksson, K. W. Helmersson, J. Ansari | C74: 2016 | D74: IEEE International Conference on Emerging Technologies and Factory Automation (ETFA) | E74: =--(ROW(A74)<>MATCH(A74,$A:$A,0)) -> 0 | F74: =IF(COUNTIF('Start Set'!A:A, A74) > 0, 1, 0) -> 0 | G74: =IF(COUNTIF('Iteration 1 - Forward'!A:A, A74) > 0, 1, 0) -> 0 | H74: =IF(COUNTIF('Iteration 1 - Backward'!A:A, A74) > 0, 1, 0) -> 0 | I74: =IF(COUNTIF('Iteration 2 - Forward-Forward'!A:A, A74) > 0, 1, 0) -> 0 | J74: 1 | K74: 0
... A84: Urgency-based scheduler for time-sensitive switched Ethernet networks | B84: J. Specht, S. Samii | C84: 2016 | D84: 28th Euromicro Conference on Real-Time Systems (ECRTS) | E84: =--(ROW(A84)<>MATCH(A84,$A:$A,0)) -> 0 | F84: =IF(COUNTIF('Start Set'!A:A, A84) > 0, 1, 0) -> 0 | G84: =IF(COUNTIF('Iteration 1 - Forward'!A:A, A84) > 0, 1, 0) -> 0 | H84: =IF(COUNTIF('Iteration 1 - Backward'!A:A, A84) > 0, 1, 0) -> 0 | I84: =IF(COUNTIF('Iteration 2 - Forward-Forward'!A:A, A84) > 0, 1, 0) -> 0 | J84: 1 | K84: 0
A85: Timing analysis of rate-constrained traffic in TTEthernet using network calculus | B85: L. Zhao, P. Pop, Q. Li, J. Chen, H. Xiong | C85: 2017 | D85: Real-Time Systems | E85: =--(ROW(A85)<>MATCH(A85,$A:$A,0)) -> 0 | F85: =IF(COUNTIF('Start Set'!A:A, A85) > 0, 1, 0) -> 0 | G85: =IF(COUNTIF('Iteration 1 - Forward'!A:A, A85) > 0, 1, 0) -> 0 | H85: =IF(COUNTIF('Iteration 1 - Backward'!A:A, A85) > 0, 1, 0) -> 1 | I85: =IF(COUNTIF('Iteration 2 - Forward-Forward'!A:A, A85) > 0, 1, 0) -> 0 | J85: 1
A86: Evaluating Bluetooth low energy suitability for time-critical industrial IoT applications | B86: R. Rondón, M. Gidlund, K. Landernäs | C86: 2017 | D86: International Journal of Wireless Information Networks | E86: =--(ROW(A86)<>MATCH(A86,$A:$A,0)) -> 0 | F86: =IF(COUNTIF('Start Set'!A:A, A86) > 0, 1, 0) -> 0 | G86: =IF(COUNTIF('Iteration 1 - Forward'!A:A, A86) > 0, 1, 0) -> 0 | H86: =IF(COUNTIF('Iteration 1 - Backward'!A:A, A86) > 0, 1, 0) -> 1 | I86: =IF(COUNTIF('Iteration 2 - Forward-Forward'!A:A, A86) > 0, 1, 0) -> 0 | J86: 1
A87: Latency critical IoT applications in 5G: Perspective on the design of radio interface and network architecture | B87: P. Schulz, et al. | C87: 2017 | D87: IEEE Communications Magazine | E87: =--(ROW(A87)<>MATCH(A87,$A:$A,0)) -> 0 | F87: =IF(COUNTIF('Start Set'!A:A, A87) > 0, 1, 0) -> 0 | G87: =IF(COUNTIF('Iteration 1 - Forward'!A:A, A87) > 0, 1, 0) -> 0 | H87: =IF(COUNTIF('Iteration 1 - Backward'!A:A, A87) > 0, 1, 0) -> 1 | I87: =IF(COUNTIF('Iteration 2 - Forward-Forward'!A:A, A87) > 0, 1, 0) -> 0 | J87: 1
A88: Future scenarios and value network configurations for industrial 5G | B88: J. S. Walia, H. Hammainen, H. Flinck | C88: 2017 | D88: International Conference on Network of the Future (NoF) | E88: =--(ROW(A88)<>MATCH(A88,$A:$A,0)) -> 0 | F88: =IF(COUNTIF('Start Set'!A:A, A88) > 0, 1, 0) -> 0 | G88: =IF(COUNTIF('Iteration 1 - Forward'!A:A, A88) > 0, 1, 0) -> 0 | H88: =IF(COUNTIF('Iteration 1 - Backward'!A:A, A88) > 0, 1, 0) -> 1 | I88: =IF(COUNTIF('Iteration 2 - Forward-Forward'!A:A, A88) > 0, 1, 0) -> 0 | J88: 1
A89: OpenFog reference architecture for fog computing | B89: OpenFog Consortium | C89: 2017 | E89: =--(ROW(A89)<>MATCH(A89,$A:$A,0)) -> 0 | F89: =IF(COUNTIF('Start Set'!A:A, A89) > 0, 1, 0) -> 0 | G89: =IF(COUNTIF('Iteration 1 - Forward'!A:A, A89) > 0, 1, 0) -> 0 | H89: =IF(COUNTIF('Iteration 1 - Backward'!A:A, A89) > 0, 1, 0) -> 0 | I89: =IF(COUNTIF('Iteration 2 - Forward-Forward'!A:A, A89) > 0, 1, 0) -> 0 | J89: 1 | K89: 1
A90: Vehicle-to-everything (V2X) services supported by LTE-based systems and 5G | B90: S. Chen, et al. | C90: 2017 | D90: IEEE Communications Standards Magazine | E90: =--(ROW(A90)<>MATCH(A90,$A:$A,0)) -> 0 | F90: =IF(COUNTIF('Start Set'!A:A, A90) > 0, 1, 0) -> 0 | G90: =IF(COUNTIF('Iteration 1 - Forward'!A:A, A90) > 0, 1, 0) -> 0 | H90: =IF(COUNTIF('Iteration 1 - Backward'!A:A, A90) > 0, 1, 0) -> 0 | I90: =IF(COUNTIF('Iteration 2 - Forward-Forward'!A:A, A90) > 0, 1, 0) -> 0 | J90: 1 | K90: 1
A91: NR: The new 5G radio access technology | B91: S. Parkvall, E. Dahlman, A. Furuskar, M. Frenne | C91: 2017 | D91: IEEE Communications Standards Magazine | E91: =--(ROW(A91)<>MATCH(A91,$A:$A,0)) -> 0 | F91: =IF(COUNTIF('Start Set'!A:A, A91) > 0, 1, 0) -> 0 | G91: =IF(COUNTIF('Iteration 1 - Forward'!A:A, A91) > 0, 1, 0) -> 0 | H91: =IF(COUNTIF('Iteration 1 - Backward'!A:A, A91) > 0, 1, 0) -> 0 | I91: =IF(COUNTIF('Iteration 2 - Forward-Forward'!A:A, A91) > 0, 1, 0) -> 0 | J91: 1 | K91: 1
A92: Full-Duplex Protocol Design for 5G Networks | B92: T. Riihonen, R. Wichman | C92: 2017 | D92: Cambridge University Press | E92: =--(ROW(A92)<>MATCH(A92,$A:$A,0)) -> 0 | F92: =IF(COUNTIF('Start Set'!A:A, A92) > 0, 1, 0) -> 0 | G92: =IF(COUNTIF('Iteration 1 - Forward'!A:A, A92) > 0, 1, 0) -> 0 | H92: =IF(COUNTIF('Iteration 1 - Backward'!A:A, A92) > 0, 1, 0) -> 0 | I92: =IF(COUNTIF('Iteration 2 - Forward-Forward'!A:A, A92) > 0, 1, 0) -> 0 | J92: 1 | K92: 1
A93: New physical-layer waveforms for 5G | B93: R. Vannithamby, S. Talwar | C93: 2017 | D93: Book Chapter (Wiley) | E93: =--(ROW(A93)<>MATCH(A93,$A:$A,0)) -> 0 | F93: =IF(COUNTIF('Start Set'!A:A, A93) > 0, 1, 0) -> 0 | G93: =IF(COUNTIF('Iteration 1 - Forward'!A:A, A93) > 0, 1, 0) -> 0 | H93: =IF(COUNTIF('Iteration 1 - Backward'!A:A, A93) > 0, 1, 0) -> 0 | I93: =IF(COUNTIF('Iteration 2 - Forward-Forward'!A:A, A93) > 0, 1, 0) -> 0 | J93: 1 | K93: 1
A94: Study on new radio access technology physical layer aspects (Release 14) | C94: 2017 | D94: 3GPP TR 38.802 | E94: =--(ROW(A94)<>MATCH(A94,$A:$A,0)) -> 0 | F94: =IF(COUNTIF('Start Set'!A:A, A94) > 0, 1, 0) -> 0 | G94: =IF(COUNTIF('Iteration 1 - Forward'!A:A, A94) > 0, 1, 0) -> 0 | H94: =IF(COUNTIF('Iteration 1 - Backward'!A:A, A94) > 0, 1, 0) -> 0 | I94: =IF(COUNTIF('Iteration 2 - Forward-Forward'!A:A, A94) > 0, 1, 0) -> 0 | J94: 1 | K94: 1
A95: Technical specification group radio access network, NR (Release 15) | C95: 2017 | D95: 3GPP TR 38.211 | E95: =--(ROW(A95)<>MATCH(A95,$A:$A,0)) -> 0 | F95: =IF(COUNTIF('Start Set'!A:A, A95) > 0, 1, 0) -> 0 | G95: =IF(COUNTIF('Iteration 1 - Forward'!A:A, A95) > 0, 1, 0) -> 0 | H95: =IF(COUNTIF('Iteration 1 - Backward'!A:A, A95) > 0, 1, 0) -> 0 | I95: =IF(COUNTIF('Iteration 2 - Forward-Forward'!A:A, A95) > 0, 1, 0) -> 0 | J95: 1 | K95: 1
A96: A survey on real-time communications in wireless sensor networks | B96: B.-S. Kim, H. Park, K. H. Kim, D. Godfrey, K.-I. Kim | C96: 2017 | D96: Wireless Communications and Mobile Computing | E96: =--(ROW(A96)<>MATCH(A96,$A:$A,0)) -> 0 | F96: =IF(COUNTIF('Start Set'!A:A, A96) > 0, 1, 0) -> 0 | G96: =IF(COUNTIF('Iteration 1 - Forward'!A:A, A96) > 0, 1, 0) -> 0 | H96: =IF(COUNTIF('Iteration 1 - Backward'!A:A, A96) > 0, 1, 0) -> 0 | I96: =IF(COUNTIF('Iteration 2 - Forward-Forward'!A:A, A96) > 0, 1, 0) -> 0 | J96: 1 | K96: 0
A97: iFogSim: A toolkit for modeling and simulation of resource management techniques in the Internet of Things, Edge and Fog computing environments | B97: H. Gupta, A. Vahid Dastjerdi, S.K. Ghosh, R. Buyya | C97: 2017 | D97: Softw.: Pract. Exp. | E97: =--(ROW(A97)<>MATCH(A97,$A:$A,0)) -> 0 | F97: =IF(COUNTIF('Start Set'!A:A, A97) > 0, 1, 0) -> 0 | G97: =IF(COUNTIF('Iteration 1 - Forward'!A:A, A97) > 0, 1, 0) -> 0 | H97: =IF(COUNTIF('Iteration 1 - Backward'!A:A, A97) > 0, 1, 0) -> 0 | I97: =IF(COUNTIF('Iteration 2 - Forward-Forward'!A:A, A97) > 0, 1, 0) -> 0 | J97: 1 | K97: 0
A98: RT-SANE: Real time security aware scheduling on the network edge | B98: A. Singh, N. Auluck, O. Rana, A. Jones, S. Nepal | C98: 2017 | D98: Proceedings of the 10th IEEE/ACM International Conference on Utility and Cloud Computing (UCC ’17) | E98: =--(ROW(A98)<>MATCH(A98,$A:$A,0)) -> 0 | F98: =IF(COUNTIF('Start Set'!A:A, A98) > 0, 1, 0) -> 0 | G98: =IF(COUNTIF('Iteration 1 - Forward'!A:A, A98) > 0, 1, 0) -> 0 | H98: =IF(COUNTIF('Iteration 1 - Backward'!A:A, A98) > 0, 1, 0) -> 0 | I98: =IF(COUNTIF('Iteration 2 - Forward-Forward'!A:A, A98) > 0, 1, 0) -> 0 | J98: 1 | K98: 0
A99: Attention is all you need | B99: A. Vaswani, et al. | C99: 2017 | D99: Proc. Conf. Workshop Neural Inf. Process. Syst. | E99: =--(ROW(A99)<>MATCH(A99,$A:$A,0)) -> 0 | F99: =IF(COUNTIF('Start Set'!A:A, A99) > 0, 1, 0) -> 0 | G99: =IF(COUNTIF('Iteration 1 - Forward'!A:A, A99) > 0, 1, 0) -> 0 | H99: =IF(COUNTIF('Iteration 1 - Backward'!A:A, A99) > 0, 1, 0) -> 0 | I99: =IF(COUNTIF('Iteration 2 - Forward-Forward'!A:A, A99) > 0, 1, 0) -> 0 | J99: 1 | K99: 0
A100: Big Iron, big data, and big identity | B100: C.A. Lee, M. Assis, L.F. Bittencourt, S. Nativi, R. Tolosana-Calasanz | C100: 2017 | D100: New Front. High Perform. Comput. Big Data | E100: =--(ROW(A100)<>MATCH(A100,$A:$A,0)) -> 0 | F100: =IF(COUNTIF('Start Set'!A:A, A100) > 0, 1, 0) -> 0 | G100: =IF(COUNTIF('Iteration 1 - Forward'!A:A, A100) > 0, 1, 0) -> 0 | H100: =IF(COUNTIF('Iteration 1 - Backward'!A:A, A100) > 0, 1, 0) -> 0 | I100: =IF(COUNTIF('Iteration 2 - Forward-Forward'!A:A, A100) > 0, 1, 0) -> 0 | J100: 1 | K100: 0
A101: Industrial Internet of Things (IIoT) applications in underground coal mines | B101: C. Zhou, N. Damiano, B. Whisner, M. Reyes | C101: 2017 | D101: Mining Engineering | E101: =--(ROW(A101)<>MATCH(A101,$A:$A,0)) -> 0 | F101: =IF(COUNTIF('Start Set'!A:A, A101) > 0, 1, 0) -> 0 | G101: =IF(COUNTIF('Iteration 1 - Forward'!A:A, A101) > 0, 1, 0) -> 0 | H101: =IF(COUNTIF('Iteration 1 - Backward'!A:A, A101) > 0, 1, 0) -> 0 | I101: =IF(COUNTIF('Iteration 2 - Forward-Forward'!A:A, A101) > 0, 1, 0) -> 0 | J101: 1 | K101: 0
A102: Technologies for 5G networks: Challenges and opportunities | B102: N. Al-Falahy, O. Y. Alani | C102: 2017 | D102: IT Professional | E102: =--(ROW(A102)<>MATCH(A102,$A:$A,0)) -> 0 | F102: =IF(COUNTIF('Start Set'!A:A, A102) > 0, 1, 0) -> 0 | G102: =IF(COUNTIF('Iteration 1 - Forward'!A:A, A102) > 0, 1, 0) -> 0 | H102: =IF(COUNTIF('Iteration 1 - Backward'!A:A, A102) > 0, 1, 0) -> 0 | I102: =IF(COUNTIF('Iteration 2 - Forward-Forward'!A:A, A102) > 0, 1, 0) -> 0 | J102: 1 | K102: 0
A103: 5G for robotics: Ultra-low latency control of distributed robotic systems | B103: F. Voigtlander, A. Ramadan, J. Eichinger, C. Lenz, D. Pensky, A. Knoll | C103: 2017 | D103: International Symposium on Computer Science and Intelligent Controls | E103: =--(ROW(A103)<>MATCH(A103,$A:$A,0)) -> 0 | F103: =IF(COUNTIF('Start Set'!A:A, A103) > 0, 1, 0) -> 0 | G103: =IF(COUNTIF('Iteration 1 - Forward'!A:A, A103) > 0, 1, 0) -> 0 | H103: =IF(COUNTIF('Iteration 1 - Backward'!A:A, A103) > 0, 1, 0) -> 0 | I103: =IF(COUNTIF('Iteration 2 - Forward-Forward'!A:A, A103) > 0, 1, 0) -> 0 | J103: 1 | K103: 0
A104: Demo: A realistic use-case for wireless industrial automation and control | B104: J. Ansari, et al. | C104: 2017 | D104: International Conference on Networked Systems (NetSys) | E104: =--(ROW(A104)<>MATCH(A104,$A:$A,0)) -> 0 | F104: =IF(COUNTIF('Start Set'!A:A, A104) > 0, 1, 0) -> 0 | G104: =IF(COUNTIF('Iteration 1 - Forward'!A:A, A104) > 0, 1, 0) -> 0 | H104: =IF(COUNTIF('Iteration 1 - Backward'!A:A, A104) > 0, 1, 0) -> 0 | I104: =IF(COUNTIF('Iteration 2 - Forward-Forward'!A:A, A104) > 0, 1, 0) -> 0 | J104: 1 | K104: 0
A105: Narrowband wireless access for low-power massive Internet of Things: A bandwidth perspective | B105: W. Yang, et al. | C105: 2017 | D105: IEEE Wireless Communications | E105: =--(ROW(A105)<>MATCH(A105,$A:$A,0)) -> 0 | F105: =IF(COUNTIF('Start Set'!A:A, A105) > 0, 1, 0) -> 0 | G105: =IF(COUNTIF('Iteration 1 - Forward'!A:A, A105) > 0, 1, 0) -> 0 | H105: =IF(COUNTIF('Iteration 1 - Backward'!A:A, A105) > 0, 1, 0) -> 0 | I105: =IF(COUNTIF('Iteration 2 - Forward-Forward'!A:A, A105) > 0, 1, 0) -> 0 | J105: 1 | K105: 0
A106: LTE-V for sidelink 5G V2X vehicular communications: A new 5G technology for short-range vehicle-to-everything communications | B106: R. Molina-Masegosa, J. Gozalvez | C106: 2017 | D106: IEEE Vehicular Technology Magazine | E106: =--(ROW(A106)<>MATCH(A106,$A:$A,0)) -> 0 | F106: =IF(COUNTIF('Start Set'!A:A, A106) > 0, 1, 0) -> 0 | G106: =IF(COUNTIF('Iteration 1 - Forward'!A:A, A106) > 0, 1, 0) -> 0 | H106: =IF(COUNTIF('Iteration 1 - Backward'!A:A, A106) > 0, 1, 0) -> 0 | I106: =IF(COUNTIF('Iteration 2 - Forward-Forward'!A:A, A106) > 0, 1, 0) -> 0 | J106: 1 | K106: 0
A107: Performance evaluation of grant-free transmission for uplink URLLC services | B107: C. Wang, Y. Chen, Y. Wu, L. Zhang | C107: 2017 | D107: IEEE Vehicular Technology Conference (VTC) | E107: =--(ROW(A107)<>MATCH(A107,$A:$A,0)) -> 0 | F107: =IF(COUNTIF('Start Set'!A:A, A107) > 0, 1, 0) -> 0 | G107: =IF(COUNTIF('Iteration 1 - Forward'!A:A, A107) > 0, 1, 0) -> 0 | H107: =IF(COUNTIF('Iteration 1 - Backward'!A:A, A107) > 0, 1, 0) -> 0 | I107: =IF(COUNTIF('Iteration 2 - Forward-Forward'!A:A, A107) > 0, 1, 0) -> 0 | J107: 1 | K107: 0
... A137: Pulsar: Enabling dynamic data-driven IoT applications | B137: E. Renart, D. Balouek-Thomert, M. Parashar | C137: 2017 | D137: 2017 IEEE 2nd International Workshops on Foundations and Applications of Self* Systems (FAS*W) | E137: =--(ROW(A137)<>MATCH(A137,$A:$A,0)) -> 0 | F137: =IF(COUNTIF('Start Set'!A:A, A137) > 0, 1, 0) -> 0 | G137: =IF(COUNTIF('Iteration 1 - Forward'!A:A, A137) > 0, 1, 0) -> 0 | H137: =IF(COUNTIF('Iteration 1 - Backward'!A:A, A137) > 0, 1, 0) -> 0 | I137: =IF(COUNTIF('Iteration 2 - Forward-Forward'!A:A, A137) > 0, 1, 0) -> 0 | J137: 1 | K137: 0
A138: Minimizing wireless resource consumption for packetized predictive control in real-time cyber physical systems | B138: X. Tong, G. Zhao, M. A. Imran, Z. Pang, Z. Chen | C138: 2018 | D138: IEEE Int. Conf. Commun. Workshops | E138: =--(ROW(A138)<>MATCH(A138,$A:$A,0)) -> 0 | F138: =IF(COUNTIF('Start Set'!A:A, A138) > 0, 1, 0) -> 0 | G138: =IF(COUNTIF('Iteration 1 - Forward'!A:A, A138) > 0, 1, 0) -> 0 | H138: =IF(COUNTIF('Iteration 1 - Backward'!A:A, A138) > 0, 1, 0) -> 1 | I138: =IF(COUNTIF('Iteration 2 - Forward-Forward'!A:A, A138) > 0, 1, 0) -> 0 | J138: 1
A139: A survey on 5G networks for the Internet of Things: Communication technologies and challenges | B139: G. A. Akpakwu, B. J. Silva, G. P. Hancke, A. M. Abu-Mahfouz | C139: 2018 | D139: IEEE Access | E139: =--(ROW(A139)<>MATCH(A139,$A:$A,0)) -> 0 | F139: =IF(COUNTIF('Start Set'!A:A, A139) > 0, 1, 0) -> 0 | G139: =IF(COUNTIF('Iteration 1 - Forward'!A:A, A139) > 0, 1, 0) -> 0 | H139: =IF(COUNTIF('Iteration 1 - Backward'!A:A, A139) > 0, 1, 0) -> 1 | I139: =IF(COUNTIF('Iteration 2 - Forward-Forward'!A:A, A139) > 0, 1, 0) -> 0 | J139: 1
A140: 5G radio network design for ultra-reliable low-latency communication | B140: J. Sachs, G. Wikstrom, T. Dudda, R. Baldemair, K. Kittichokechai | C140: 2018 | D140: IEEE Network | E140: =--(ROW(A140)<>MATCH(A140,$A:$A,0)) -> 0 | F140: =IF(COUNTIF('Start Set'!A:A, A140) > 0, 1, 0) -> 0 | G140: =IF(COUNTIF('Iteration 1 - Forward'!A:A, A140) > 0, 1, 0) -> 0 | H140: =IF(COUNTIF('Iteration 1 - Backward'!A:A, A140) > 0, 1, 0) -> 1 | I140: =IF(COUNTIF('Iteration 2 - Forward-Forward'!A:A, A140) > 0, 1, 0) -> 0 | J140: 1
A141: A D2D-based protocol for ultra-reliable wireless communications for industrial automation | B141: L. Liu, W. Yu | C141: 2018 | D141: IEEE Transactions on Wireless Communications | E141: =--(ROW(A141)<>MATCH(A141,$A:$A,0)) -> 0 | F141: =IF(COUNTIF('Start Set'!A:A, A141) > 0, 1, 0) -> 0 | G141: =IF(COUNTIF('Iteration 1 - Forward'!A:A, A141) > 0, 1, 0) -> 0 | H141: =IF(COUNTIF('Iteration 1 - Backward'!A:A, A141) > 0, 1, 0) -> 1 | I141: =IF(COUNTIF('Iteration 2 - Forward-Forward'!A:A, A141) > 0, 1, 0) -> 0 | J141: 1
A142: Industrial Internet of Things: Challenges, opportunities, and directions | B142: E. Sisinni, A. Saifullah, S. Han, U. Jennehag, M. Gidlund | C142: 2018 | D142: IEEE Transactions on Industrial Informatics | E142: =--(ROW(A142)<>MATCH(A142,$A:$A,0)) -> 0 | F142: =IF(COUNTIF('Start Set'!A:A, A142) > 0, 1, 0) -> 0 | G142: =IF(COUNTIF('Iteration 1 - Forward'!A:A, A142) > 0, 1, 0) -> 0 | H142: =IF(COUNTIF('Iteration 1 - Backward'!A:A, A142) > 0, 1, 0) -> 0 | I142: =IF(COUNTIF('Iteration 2 - Forward-Forward'!A:A, A142) > 0, 1, 0) -> 0 | J142: 1
A143: Enabling fog computing for industrial automation through time-sensitive networking (TSN) | B143: P. Pop, M. L. Raagaard, M. Gutierrez, W. Steiner | C143: 2018 | D143: IEEE Commun. Standards Mag. | E143: =--(ROW(A143)<>MATCH(A143,$A:$A,0)) -> 0 | F143: =IF(COUNTIF('Start Set'!A:A, A143) > 0, 1, 0) -> 0 | G143: =IF(COUNTIF('Iteration 1 - Forward'!A:A, A143) > 0, 1, 0) -> 0 | H143: =IF(COUNTIF('Iteration 1 - Backward'!A:A, A143) > 0, 1, 0) -> 0 | I143: =IF(COUNTIF('Iteration 2 - Forward-Forward'!A:A, A143) > 0, 1, 0) -> 0 | J143: 1 | K143: 1
A144: The road to 5G V2X: Ultra-high reliable communications | B144: S. Husain, A. Kunz, A. Prasad, E. Pateromichelakis, K. Samdanis, J. Song | C144: 2018 | D144: IEEE Conference on Standards for Communications and Networking (CSCN) | E144: =--(ROW(A144)<>MATCH(A144,$A:$A,0)) -> 0 | F144: =IF(COUNTIF('Start Set'!A:A, A144) > 0, 1, 0) -> 0 | G144: =IF(COUNTIF('Iteration 1 - Forward'!A:A, A144) > 0, 1, 0) -> 0 | H144: =IF(COUNTIF('Iteration 1 - Backward'!A:A, A144) > 0, 1, 0) -> 0 | I144: =IF(COUNTIF('Iteration 2 - Forward-Forward'!A:A, A144) > 0, 1, 0) -> 0 | J144: 1 | K144: 1
A145: IEEE Standard for Local and Metropolitan Area Network–Bridges and Bridged Networks | B145: IEEE | C145: 2018 | D145: IEEE 802.1Q-2018 | E145: =--(ROW(A145)<>MATCH(A145,$A:$A,0)) -> 0 | F145: =IF(COUNTIF('Start Set'!A:A, A145) > 0, 1, 0) -> 0 | G145: =IF(COUNTIF('Iteration 1 - Forward'!A:A, A145) > 0, 1, 0) -> 0 | H145: =IF(COUNTIF('Iteration 1 - Backward'!A:A, A145) > 0, 1, 0) -> 0 | I145: =IF(COUNTIF('Iteration 2 - Forward-Forward'!A:A, A145) > 0, 1, 0) -> 0 | J145: 1 | K145: 1
A146: Exploiting a Natural Network Effect for Scalable, Fine-Grained Clock Synchronization | B146: Y. Geng, et al. | C146: 2018 | D146: USENIX NSDI | E146: =--(ROW(A146)<>MATCH(A146,$A:$A,0)) -> 0 | F146: =IF(COUNTIF('Start Set'!A:A, A146) > 0, 1, 0) -> 0 | G146: =IF(COUNTIF('Iteration 1 - Forward'!A:A, A146) > 0, 1, 0) -> 0 | H146: =IF(COUNTIF('Iteration 1 - Backward'!A:A, A146) > 0, 1, 0) -> 0 | I146: =IF(COUNTIF('Iteration 2 - Forward-Forward'!A:A, A146) > 0, 1, 0) -> 0 | J146: 1 | K146: 0
A147: Adaptive computing optimization in software-defined network-based Industrial Internet of Things with fog computing | B147: J. Wang, D. Li | C147: 2018 | D147: Sensors | E147: =--(ROW(A147)<>MATCH(A147,$A:$A,0)) -> 0 | F147: =IF(COUNTIF('Start Set'!A:A, A147) > 0, 1, 0) -> 0 | G147: =IF(COUNTIF('Iteration 1 - Forward'!A:A, A147) > 0, 1, 0) -> 0 | H147: =IF(COUNTIF('Iteration 1 - Backward'!A:A, A147) > 0, 1, 0) -> 0 | I147: =IF(COUNTIF('Iteration 2 - Forward-Forward'!A:A, A147) > 0, 1, 0) -> 0 | J147: 1 | K147: 0
A148: Resource management in energy harvesting cooperative IoT network under QoS constraints | B148: M. Amjad, A. Ahmed, M. Naeem, M. Awais, W. Ejaz, A. Anpalagan | C148: 2018 | D148: Sensors | E148: =--(ROW(A148)<>MATCH(A148,$A:$A,0)) -> 0 | F148: =IF(COUNTIF('Start Set'!A:A, A148) > 0, 1, 0) -> 0 | G148: =IF(COUNTIF('Iteration 1 - Forward'!A:A, A148) > 0, 1, 0) -> 0 | H148: =IF(COUNTIF('Iteration 1 - Backward'!A:A, A148) > 0, 1, 0) -> 0 | I148: =IF(COUNTIF('Iteration 2 - Forward-Forward'!A:A, A148) > 0, 1, 0) -> 0 | J148: 1 | K148: 0
A149: Ultrareliable and low-latency wireless communication: Tail, risk, and scale | B149: M. Bennis, M. Debbah, H. V. Poor | C149: 2018 | D149: Proceedings of the IEEE | E149: =--(ROW(A149)<>MATCH(A149,$A:$A,0)) -> 0 | F149: =IF(COUNTIF('Start Set'!A:A, A149) > 0, 1, 0) -> 0 | G149: =IF(COUNTIF('Iteration 1 - Forward'!A:A, A149) > 0, 1, 0) -> 0 | H149: =IF(COUNTIF('Iteration 1 - Backward'!A:A, A149) > 0, 1, 0) -> 0 | I149: =IF(COUNTIF('Iteration 2 - Forward-Forward'!A:A, A149) > 0, 1, 0) -> 0 | J149: 1 | K149: 0
A150: Cutting process monitoring with an instrumented boring bar measuring cutting force and vibration | B150: D. Östling, T. Jensen, M. Tjomsland, O. Standal, T. Mugaas | C150: 2018 | D150: Procedia CIRP | E150: =--(ROW(A150)<>MATCH(A150,$A:$A,0)) -> 0 | F150: =IF(COUNTIF('Start Set'!A:A, A150) > 0, 1, 0) -> 0 | G150: =IF(COUNTIF('Iteration 1 - Forward'!A:A, A150) > 0, 1, 0) -> 0 | H150: =IF(COUNTIF('Iteration 1 - Backward'!A:A, A150) > 0, 1, 0) -> 0 | I150: =IF(COUNTIF('Iteration 2 - Forward-Forward'!A:A, A150) > 0, 1, 0) -> 0 | J150: 1 | K150: 0
A151: 5 G URLLC: Design challenges and system concepts | B151: Z. Li, M. A. Uusitalo, H. Shariatmadari, B. Singh | C151: 2018 | D151: Proc. 15th Int. Symp. Wireless Commun. Syst. | E151: =--(ROW(A151)<>MATCH(A151,$A:$A,0)) -> 0 | F151: =IF(COUNTIF('Start Set'!A:A, A151) > 0, 1, 0) -> 0 | G151: =IF(COUNTIF('Iteration 1 - Forward'!A:A, A151) > 0, 1, 0) -> 0 | H151: =IF(COUNTIF('Iteration 1 - Backward'!A:A, A151) > 0, 1, 0) -> 0 | I151: =IF(COUNTIF('Iteration 2 - Forward-Forward'!A:A, A151) > 0, 1, 0) -> 0 | J151: 1 | K151: 0
A152: A practical approach to teaching industry 4.0 technologies | B152: T. Wanyama, I. Singh, D. Centea | C152: 2018 | D152: Online Engineering & Internet of Things (Springer) | E152: =--(ROW(A152)<>MATCH(A152,$A:$A,0)) -> 0 | F152: =IF(COUNTIF('Start Set'!A:A, A152) > 0, 1, 0) -> 0 | G152: =IF(COUNTIF('Iteration 1 - Forward'!A:A, A152) > 0, 1, 0) -> 0 | H152: =IF(COUNTIF('Iteration 1 - Backward'!A:A, A152) > 0, 1, 0) -> 0 | I152: =IF(COUNTIF('Iteration 2 - Forward-Forward'!A:A, A152) > 0, 1, 0) -> 0 | J152: 1 | K152: 0
A153: Towards an approach for assuring machinery safety in the IIoT-age | B153: T. Kivelä, M. Golder, K. Furmans | C153: 2018 | D153: Logistics Journal Proceedings | E153: =--(ROW(A153)<>MATCH(A153,$A:$A,0)) -> 0 | F153: =IF(COUNTIF('Start Set'!A:A, A153) > 0, 1, 0) -> 0 | G153: =IF(COUNTIF('Iteration 1 - Forward'!A:A, A153) > 0, 1, 0) -> 0 | H153: =IF(COUNTIF('Iteration 1 - Backward'!A:A, A153) > 0, 1, 0) -> 0 | I153: =IF(COUNTIF('Iteration 2 - Forward-Forward'!A:A, A153) > 0, 1, 0) -> 0 | J153: 1 | K153: 0
A154: Industrial IoT in 5G environment towards smart manufacturing | B154: J. Cheng, W. Chen, F. Tao, C.-L. Lin | C154: 2018 | D154: Journal of Industrial Information Integration | E154: =--(ROW(A154)<>MATCH(A154,$A:$A,0)) -> 0 | F154: =IF(COUNTIF('Start Set'!A:A, A154) > 0, 1, 0) -> 0 | G154: =IF(COUNTIF('Iteration 1 - Forward'!A:A, A154) > 0, 1, 0) -> 0 | H154: =IF(COUNTIF('Iteration 1 - Backward'!A:A, A154) > 0, 1, 0) -> 0 | I154: =IF(COUNTIF('Iteration 2 - Forward-Forward'!A:A, A154) > 0, 1, 0) -> 0 | J154: 1 | K154: 0
... A209: Runtime management of data quality for scientific observatories using edge and in-transit resources | B209: A.R. Zamani, D. Balouek-Thomert, J.J. Villalobos, I. Rodero, M. Parashar | C209: 2018 | D209: 2018 30th International Symposium on Computer Architecture and High Performance Computing (SBAC-PAD) | E209: =--(ROW(A209)<>MATCH(A209,$A:$A,0)) -> 0 | F209: =IF(COUNTIF('Start Set'!A:A, A209) > 0, 1, 0) -> 0 | G209: =IF(COUNTIF('Iteration 1 - Forward'!A:A, A209) > 0, 1, 0) -> 0 | H209: =IF(COUNTIF('Iteration 1 - Backward'!A:A, A209) > 0, 1, 0) -> 0 | I209: =IF(COUNTIF('Iteration 2 - Forward-Forward'!A:A, A209) > 0, 1, 0) -> 0 | J209: 1 | K209: 0
A210: The tactile internet for industries: A review | B210: A. Aijaz, M. Sooriyabandara | C210: 2019 | D210: Proc. IEEE | E210: =--(ROW(A210)<>MATCH(A210,$A:$A,0)) -> 0 | F210: =IF(COUNTIF('Start Set'!A:A, A210) > 0, 1, 0) -> 0 | G210: =IF(COUNTIF('Iteration 1 - Forward'!A:A, A210) > 0, 1, 0) -> 0 | H210: =IF(COUNTIF('Iteration 1 - Backward'!A:A, A210) > 0, 1, 0) -> 1 | I210: =IF(COUNTIF('Iteration 2 - Forward-Forward'!A:A, A210) > 0, 1, 0) -> 0 | J210: 1
A211: Data transmission reduction schemes in WSNs for efficient IoT systems | B211: A. Jarwan, A. Sabbah, M. Ibnkahla | C211: 2019 | D211: IEEE J. Sel. Areas Commun. | E211: =--(ROW(A211)<>MATCH(A211,$A:$A,0)) -> 0 | F211: =IF(COUNTIF('Start Set'!A:A, A211) > 0, 1, 0) -> 0 | G211: =IF(COUNTIF('Iteration 1 - Forward'!A:A, A211) > 0, 1, 0) -> 0 | H211: =IF(COUNTIF('Iteration 1 - Backward'!A:A, A211) > 0, 1, 0) -> 1 | I211: =IF(COUNTIF('Iteration 2 - Forward-Forward'!A:A, A211) > 0, 1, 0) -> 0 | J211: 1
A212: A perspective on IEEE time-sensitive networking for industrial communication and automation systems | B212: L. Lo Bello, W. Steiner | C212: 2019 | D212: Proceedings of the IEEE | E212: =--(ROW(A212)<>MATCH(A212,$A:$A,0)) -> 0 | F212: =IF(COUNTIF('Start Set'!A:A, A212) > 0, 1, 0) -> 0 | G212: =IF(COUNTIF('Iteration 1 - Forward'!A:A, A212) > 0, 1, 0) -> 0 | H212: =IF(COUNTIF('Iteration 1 - Backward'!A:A, A212) > 0, 1, 0) -> 1 | I212: =IF(COUNTIF('Iteration 2 - Forward-Forward'!A:A, A212) > 0, 1, 0) -> 0 | J212: 1
A213: Ultra-low latency (ULL) networks: The IEEE TSN and IETF DetNet standards and related 5G ULL research | B213: A. Nasrallah et al. | C213: 2019 | D213: IEEE Communications Surveys & Tutorials | E213: =--(ROW(A213)<>MATCH(A213,$A:$A,0)) -> 0 | F213: =IF(COUNTIF('Start Set'!A:A, A213) > 0, 1, 0) -> 0 | G213: =IF(COUNTIF('Iteration 1 - Forward'!A:A, A213) > 0, 1, 0) -> 0 | H213: =IF(COUNTIF('Iteration 1 - Backward'!A:A, A213) > 0, 1, 0) -> 1 | I213: =IF(COUNTIF('Iteration 2 - Forward-Forward'!A:A, A213) > 0, 1, 0) -> 0 | J213: 1
A214: An introduction to OPC UA TSN for industrial communication systems | B214: D. Bruckner et al. | C214: 2019 | D214: Proceedings of the IEEE | E214: =--(ROW(A214)<>MATCH(A214,$A:$A,0)) -> 0 | F214: =IF(COUNTIF('Start Set'!A:A, A214) > 0, 1, 0) -> 0 | G214: =IF(COUNTIF('Iteration 1 - Forward'!A:A, A214) > 0, 1, 0) -> 0 | H214: =IF(COUNTIF('Iteration 1 - Backward'!A:A, A214) > 0, 1, 0) -> 1 | I214: =IF(COUNTIF('Iteration 2 - Forward-Forward'!A:A, A214) > 0, 1, 0) -> 0 | J214: 1
A215: Communication protocols of an Industrial Internet of Things environment: A comparative study | B215: S. Jaloudi | C215: 2019 | D215: Future Internet | E215: =--(ROW(A215)<>MATCH(A215,$A:$A,0)) -> 0 | F215: =IF(COUNTIF('Start Set'!A:A, A215) > 0, 1, 0) -> 0 | G215: =IF(COUNTIF('Iteration 1 - Forward'!A:A, A215) > 0, 1, 0) -> 0 | H215: =IF(COUNTIF('Iteration 1 - Backward'!A:A, A215) > 0, 1, 0) -> 1 | I215: =IF(COUNTIF('Iteration 2 - Forward-Forward'!A:A, A215) > 0, 1, 0) -> 0 | J215: 1
A216: Prioritized Clock Synchronization for Event Critical Applications in Wireless IoT Networks | B216: S. Bhandari, X. Wang | C216: 2019 | D216: IEEE Sensors Journal | E216: =--(ROW(A216)<>MATCH(A216,$A:$A,0)) -> 0 | F216: =IF(COUNTIF('Start Set'!A:A, A216) > 0, 1, 0) -> 1 | G216: =IF(COUNTIF('Iteration 1 - Forward'!A:A, A216) > 0, 1, 0) -> 0 | H216: =IF(COUNTIF('Iteration 1 - Backward'!A:A, A216) > 0, 1, 0) -> 0 | I216: =IF(COUNTIF('Iteration 2 - Forward-Forward'!A:A, A216) > 0, 1, 0) -> 0 | J216: 1
A217: A comparative study of LPWAN technologies for large-scale IoT deployment | B217: K. Mekki, E. Bajic, F. Chaxel, F. Meyer | C217: 2019 | D217: ICT Express | E217: =--(ROW(A217)<>MATCH(A217,$A:$A,0)) -> 0 | F217: =IF(COUNTIF('Start Set'!A:A, A217) > 0, 1, 0) -> 0 | G217: =IF(COUNTIF('Iteration 1 - Forward'!A:A, A217) > 0, 1, 0) -> 0 | H217: =IF(COUNTIF('Iteration 1 - Backward'!A:A, A217) > 0, 1, 0) -> 0 | I217: =IF(COUNTIF('Iteration 2 - Forward-Forward'!A:A, A217) > 0, 1, 0) -> 0 | J217: 1 | K217: 1
A218: Demystifying 5G in industrial IoT | B218: P. Grossetete | C218: 2019 | D218: Cisco White Paper | E218: =--(ROW(A218)<>MATCH(A218,$A:$A,0)) -> 0 | F218: =IF(COUNTIF('Start Set'!A:A, A218) > 0, 1, 0) -> 0 | G218: =IF(COUNTIF('Iteration 1 - Forward'!A:A, A218) > 0, 1, 0) -> 0 | H218: =IF(COUNTIF('Iteration 1 - Backward'!A:A, A218) > 0, 1, 0) -> 0 | I218: =IF(COUNTIF('Iteration 2 - Forward-Forward'!A:A, A218) > 0, 1, 0) -> 0 | J218: 1 | K218: 1
A219: An experimental evaluation of LTE-A throughput for drones | B219: S. Hayat, C. Bettstetter, A. Fakhreddine, R. Muzaffar, D. Emini | C219: 2019 | D219: Workshop on Micro Aerial Vehicle Networks, Systems, and Applications (DroNet) | E219: =--(ROW(A219)<>MATCH(A219,$A:$A,0)) -> 0 | F219: =IF(COUNTIF('Start Set'!A:A, A219) > 0, 1, 0) -> 0 | G219: =IF(COUNTIF('Iteration 1 - Forward'!A:A, A219) > 0, 1, 0) -> 0 | H219: =IF(COUNTIF('Iteration 1 - Backward'!A:A, A219) > 0, 1, 0) -> 0 | I219: =IF(COUNTIF('Iteration 2 - Forward-Forward'!A:A, A219) > 0, 1, 0) -> 0 | J219: 1 | K219: 1
A220: 2030—A Blueprint of Technology, Applications and Market Drivers Towards the Year 2030 and Beyond | B220: ITU-T FG-NET-2030 | C220: 2019 | D220: ITU-T FG-NET-2030 (Report) | E220: =--(ROW(A220)<>MATCH(A220,$A:$A,0)) -> 0 | F220: =IF(COUNTIF('Start Set'!A:A, A220) > 0, 1, 0) -> 0 | G220: =IF(COUNTIF('Iteration 1 - Forward'!A:A, A220) > 0, 1, 0) -> 0 | H220: =IF(COUNTIF('Iteration 1 - Backward'!A:A, A220) > 0, 1, 0) -> 0 | I220: =IF(COUNTIF('Iteration 2 - Forward-Forward'!A:A, A220) > 0, 1, 0) -> 0 | J220: 1 | K220: 1
A221: IIoT: The Current State of Industrial Connectivity and New Technologies | C221: 2019 | D221: Online Resource (Omdia) | E221: =--(ROW(A221)<>MATCH(A221,$A:$A,0)) -> 0 | F221: =IF(COUNTIF('Start Set'!A:A, A221) > 0, 1, 0) -> 0 | G221: =IF(COUNTIF('Iteration 1 - Forward'!A:A, A221) > 0, 1, 0) -> 0 | H221: =IF(COUNTIF('Iteration 1 - Backward'!A:A, A221) > 0, 1, 0) -> 0 | I221: =IF(COUNTIF('Iteration 2 - Forward-Forward'!A:A, A221) > 0, 1, 0) -> 0 | J221: 1 | K221: 1
A222: Open-MPI over MOSIX: paralleled computing in a clustered world | B222: A. Lev-Libfeld, A. Margolin, A. Barak | C222: 2019 | D222: CoRR | E222: =--(ROW(A222)<>MATCH(A222,$A:$A,0)) -> 0 | F222: =IF(COUNTIF('Start Set'!A:A, A222) > 0, 1, 0) -> 0 | G222: =IF(COUNTIF('Iteration 1 - Forward'!A:A, A222) > 0, 1, 0) -> 0 | H222: =IF(COUNTIF('Iteration 1 - Backward'!A:A, A222) > 0, 1, 0) -> 0 | I222: =IF(COUNTIF('Iteration 2 - Forward-Forward'!A:A, A222) > 0, 1, 0) -> 0 | J222: 1 | K222: 1
A223: Case analysis for introduction of machine learning technology to the mining industry | B223: C. Lee, S. Kim, Y. Choi | C223: 2019 | D223: Tunnelling and Underground Space Technology | E223: =--(ROW(A223)<>MATCH(A223,$A:$A,0)) -> 0 | F223: =IF(COUNTIF('Start Set'!A:A, A223) > 0, 1, 0) -> 0 | G223: =IF(COUNTIF('Iteration 1 - Forward'!A:A, A223) > 0, 1, 0) -> 0 | H223: =IF(COUNTIF('Iteration 1 - Backward'!A:A, A223) > 0, 1, 0) -> 0 | I223: =IF(COUNTIF('Iteration 2 - Forward-Forward'!A:A, A223) > 0, 1, 0) -> 0 | J223: 1 | K223: 0
A224: Toward holographic-guided surgery | B224: J.W. Meulstee, J. Nijsink, R. Schreurs, L.M. Verhamme, T. Xi, H.H. Delye, W.A. Borstlap, T.J. Maal | C224: 2019 | D224: Surg. Innov. | E224: =--(ROW(A224)<>MATCH(A224,$A:$A,0)) -> 0 | F224: =IF(COUNTIF('Start Set'!A:A, A224) > 0, 1, 0) -> 0 | G224: =IF(COUNTIF('Iteration 1 - Forward'!A:A, A224) > 0, 1, 0) -> 0 | H224: =IF(COUNTIF('Iteration 1 - Backward'!A:A, A224) > 0, 1, 0) -> 0 | I224: =IF(COUNTIF('Iteration 2 - Forward-Forward'!A:A, A224) > 0, 1, 0) -> 0 | J224: 1 | K224: 0
A225: Smart Industrial IoT monitoring and control system based on UAV and cloud computing applied to a concrete plant | B225: M. Salhaoui, A. Guerrero-González, M. Arioua, F. J. Ortiz, A. El Oualkadi, C. L. Torregrosa | C225: 2019 | D225: Sensors | E225: =--(ROW(A225)<>MATCH(A225,$A:$A,0)) -> 0 | F225: =IF(COUNTIF('Start Set'!A:A, A225) > 0, 1, 0) -> 0 | G225: =IF(COUNTIF('Iteration 1 - Forward'!A:A, A225) > 0, 1, 0) -> 0 | H225: =IF(COUNTIF('Iteration 1 - Backward'!A:A, A225) > 0, 1, 0) -> 0 | I225: =IF(COUNTIF('Iteration 2 - Forward-Forward'!A:A, A225) > 0, 1, 0) -> 0 | J225: 1 | K225: 0
A226: Joint placement and device association of UAV base stations in IoT networks | B226: A. Ahmed, M. Awais, T. Akram, S. Kulac, M. Alhussein, K. Aurangzeb | C226: 2019 | D226: Sensors | E226: =--(ROW(A226)<>MATCH(A226,$A:$A,0)) -> 0 | F226: =IF(COUNTIF('Start Set'!A:A, A226) > 0, 1, 0) -> 0 | G226: =IF(COUNTIF('Iteration 1 - Forward'!A:A, A226) > 0, 1, 0) -> 0 | H226: =IF(COUNTIF('Iteration 1 - Backward'!A:A, A226) > 0, 1, 0) -> 0 | I226: =IF(COUNTIF('Iteration 2 - Forward-Forward'!A:A, A226) > 0, 1, 0) -> 0 | J226: 1 | K226: 0
A227: Extending accurate time distribution and timeliness capabilities over the air to enable future wireless industrial automation systems | B227: D. Cavalcanti, J. Perez-Ramirez, M. M. Rashid, J. Fang, M. Galeev, K. B. Stanton | C227: 2019 | D227: Proceedings of the IEEE | E227: =--(ROW(A227)<>MATCH(A227,$A:$A,0)) -> 0 | F227: =IF(COUNTIF('Start Set'!A:A, A227) > 0, 1, 0) -> 0 | G227: =IF(COUNTIF('Iteration 1 - Forward'!A:A, A227) > 0, 1, 0) -> 0 | H227: =IF(COUNTIF('Iteration 1 - Backward'!A:A, A227) > 0, 1, 0) -> 0 | I227: =IF(COUNTIF('Iteration 2 - Forward-Forward'!A:A, A227) > 0, 1, 0) -> 0 | J227: 1 | K227: 0
A228: 5G-based systems design for tactile Internet | B228: C. Li, et al. | C228: 2019 | D228: Proceedings of the IEEE | E228: =--(ROW(A228)<>MATCH(A228,$A:$A,0)) -> 0 | F228: =IF(COUNTIF('Start Set'!A:A, A228) > 0, 1, 0) -> 0 | G228: =IF(COUNTIF('Iteration 1 - Forward'!A:A, A228) > 0, 1, 0) -> 0 | H228: =IF(COUNTIF('Iteration 1 - Backward'!A:A, A228) > 0, 1, 0) -> 0 | I228: =IF(COUNTIF('Iteration 2 - Forward-Forward'!A:A, A228) > 0, 1, 0) -> 0 | J228: 1 | K228: 0
...

Sheet Iteration 2 - Backward-Backward
A1: Title | B1: Authors | C1: Year | D1: Venue | E1: D | F1: DS | G1: DF | H1: DB | I1: DFF | J1: DFB | K1: EC1 | L1: EC2 | M1: EC3 | N1: EC4 | O1: EC5 | P1: EC6 | Q1: IC1
A2: Monte Carlo simulation and random number generation | B2: R. F. W. Coates, G. J. Janacek, K. V. Lever | C2: 1988 | D2: IEEE Journal on Selected Areas in Communications | E2: =--(ROW(A2)<>MATCH(A2,$A:$A,0)) -> 0 | F2: =IF(COUNTIF('Start Set'!A:A, A2) > 0, 1, 0) -> 0 | G2: =IF(COUNTIF('Iteration 1 - Forward'!A:A, A2) > 0, 1, 0) -> 0 | H2: =IF(COUNTIF('Iteration 1 - Backward'!A:A, A2) > 0, 1, 0) -> 0 | I2: =IF(COUNTIF('Iteration 2 - Forward-Forward'!A:A, A2) > 0, 1, 0) -> 0 | J2: =IF(COUNTIF('Iteration 2 - Forward-Backward'!A:A, A2) > 0, 1, 0) -> 0 | K2: 1
A3: Feasibility Study on Licensed-Assisted Access to Unlicensed Spectrum (Release 13) | B3: 3GPP | C3: 2015 | D3: TR 36.889 V13.0.0 | E3: =--(ROW(A3)<>MATCH(A3,$A:$A,0)) -> 0 | F3: =IF(COUNTIF('Start Set'!A:A, A3) > 0, 1, 0) -> 0 | G3: =IF(COUNTIF('Iteration 1 - Forward'!A:A, A3) > 0, 1, 0) -> 0 | H3: =IF(COUNTIF('Iteration 1 - Backward'!A:A, A3) > 0, 1, 0) -> 0 | I3: =IF(COUNTIF('Iteration 2 - Forward-Forward'!A:A, A3) > 0, 1, 0) -> 0 | J3: =IF(COUNTIF('Iteration 2 - Forward-Backward'!A:A, A3) > 0, 1, 0) -> 0 | K3: 1
A4: Wireless LAN Medium Access Control (MAC) and Physical Layer (PHY) Specifications. Amendment 8: Medium Access Control (MAC) Quality of Service Enhancements | B4: IEEE 802.11 WG | C4: 2015 | D4: IEEE 802.11e Standard | E4: =--(ROW(A4)<>MATCH(A4,$A:$A,0)) -> 0 | F4: =IF(COUNTIF('Start Set'!A:A, A4) > 0, 1, 0) -> 0 | G4: =IF(COUNTIF('Iteration 1 - Forward'!A:A, A4) > 0, 1, 0) -> 0 | H4: =IF(COUNTIF('Iteration 1 - Backward'!A:A, A4) > 0, 1, 0) -> 0 | I4: =IF(COUNTIF('Iteration 2 - Forward-Forward'!A:A, A4) > 0, 1, 0) -> 0 | J4: =IF(COUNTIF('Iteration 2 - Forward-Backward'!A:A, A4) > 0, 1, 0) -> 0 | K4: 1
A5: Generalized attacker and attack models for cyber physical systems | B5: S. Adepu, A. Mathur | C5: 2016 | D5: IEEE Computer Software and Applications Conference | E5: =--(ROW(A5)<>MATCH(A5,$A:$A,0)) -> 0 | F5: =IF(COUNTIF('Start Set'!A:A, A5) > 0, 1, 0) -> 0 | G5: =IF(COUNTIF('Iteration 1 - Forward'!A:A, A5) > 0, 1, 0) -> 0 | H5: =IF(COUNTIF('Iteration 1 - Backward'!A:A, A5) > 0, 1, 0) -> 0 | I5: =IF(COUNTIF('Iteration 2 - Forward-Forward'!A:A, A5) > 0, 1, 0) -> 0 | J5: =IF(COUNTIF('Iteration 2 - Forward-Backward'!A:A, A5) > 0, 1, 0) -> 0 | K5: 1
A6: Seamless link-level redundancy to improve reliability of industrial Wi-Fi networks | B6: G. Cena, S. Scanzio, A. Valenzano | C6: 2016 | D6: IEEE Transactions on Industrial Informatics | E6: =--(ROW(A6)<>MATCH(A6,$A:$A,0)) -> 0 | F6: =IF(COUNTIF('Start Set'!A:A, A6) > 0, 1, 0) -> 0 | G6: =IF(COUNTIF('Iteration 1 - Forward'!A:A, A6) > 0, 1, 0) -> 0 | H6: =IF(COUNTIF('Iteration 1 - Backward'!A:A, A6) > 0, 1, 0) -> 0 | I6: =IF(COUNTIF('Iteration 2 - Forward-Forward'!A:A, A6) > 0, 1, 0) -> 0 | J6: =IF(COUNTIF('Iteration 2 - Forward-Backward'!A:A, A6) > 0, 1, 0) -> 0 | K6: 1
A7: 5G field experimental trials on URLLC using new frame structure | B7: M. Iwabuchi, A. Benjebbour, Y. Kishiyama, G. Ren, C. Tang, T. Tian, L. Gu, T. Takada, T. Kashima | C7: 2017 | D7: IEEE Globecom Workshops (GC Wkshps) | E7: =--(ROW(A7)<>MATCH(A7,$A:$A,0)) -> 0 | F7: =IF(COUNTIF('Start Set'!A:A, A7) > 0, 1, 0) -> 0 | G7: =IF(COUNTIF('Iteration 1 - Forward'!A:A, A7) > 0, 1, 0) -> 0 | H7: =IF(COUNTIF('Iteration 1 - Backward'!A:A, A7) > 0, 1, 0) -> 0 | I7: =IF(COUNTIF('Iteration 2 - Forward-Forward'!A:A, A7) > 0, 1, 0) -> 0 | J7: =IF(COUNTIF('Iteration 2 - Forward-Backward'!A:A, A7) > 0, 1, 0) -> 1 | K7: 1
A8: 5 GHz RLAN; Harmonised Standard Covering the Essential Requirements of Article 3.2 of Directive 2014/53/EU | B8: ETSI | C8: 2017 | D8: EN 301 893 V2.1.1 | E8: =--(ROW(A8)<>MATCH(A8,$A:$A,0)) -> 0 | F8: =IF(COUNTIF('Start Set'!A:A, A8) > 0, 1, 0) -> 0 | G8: =IF(COUNTIF('Iteration 1 - Forward'!A:A, A8) > 0, 1, 0) -> 0 | H8: =IF(COUNTIF('Iteration 1 - Backward'!A:A, A8) > 0, 1, 0) -> 0 | I8: =IF(COUNTIF('Iteration 2 - Forward-Forward'!A:A, A8) > 0, 1, 0) -> 0 | J8: =IF(COUNTIF('Iteration 2 - Forward-Backward'!A:A, A8) > 0, 1, 0) -> 0 | K8: 1
A9: MAC layer enhancements for ultra-reliable low-latency communications in cellular networks | B9: G. Pocovi, B. Soret, K. I. Pedersen, P. Mogensen | C9: 2017 | D9: IEEE International Conference on Communications Workshops (ICC Workshops) | E9: =--(ROW(A9)<>MATCH(A9,$A:$A,0)) -> 0 | F9: =IF(COUNTIF('Start Set'!A:A, A9) > 0, 1, 0) -> 0 | G9: =IF(COUNTIF('Iteration 1 - Forward'!A:A, A9) > 0, 1, 0) -> 0 | H9: =IF(COUNTIF('Iteration 1 - Backward'!A:A, A9) > 0, 1, 0) -> 0 | I9: =IF(COUNTIF('Iteration 2 - Forward-Forward'!A:A, A9) > 0, 1, 0) -> 0 | J9: =IF(COUNTIF('Iteration 2 - Forward-Backward'!A:A, A9) > 0, 1, 0) -> 1 | K9: 1
A10: Joint link adaptation and scheduling for 5G ultra-reliable low-latency communications | B10: G. Pocovi, K. I. Pedersen, P. Mogensen | C10: 2018 | D10: IEEE Access | E10: =--(ROW(A10)<>MATCH(A10,$A:$A,0)) -> 0 | F10: =IF(COUNTIF('Start Set'!A:A, A10) > 0, 1, 0) -> 0 | G10: =IF(COUNTIF('Iteration 1 - Forward'!A:A, A10) > 0, 1, 0) -> 0 | H10: =IF(COUNTIF('Iteration 1 - Backward'!A:A, A10) > 0, 1, 0) -> 0 | I10: =IF(COUNTIF('Iteration 2 - Forward-Forward'!A:A, A10) > 0, 1, 0) -> 0 | J10: =IF(COUNTIF('Iteration 2 - Forward-Backward'!A:A, A10) > 0, 1, 0) -> 0 | K10: 1
A11: Discussion on the RAN2 LS on TSN Requirements Evaluation | B11: 3GPP | C11: 2018 | D11: TR R1-1813120 | E11: =--(ROW(A11)<>MATCH(A11,$A:$A,0)) -> 0 | F11: =IF(COUNTIF('Start Set'!A:A, A11) > 0, 1, 0) -> 0 | G11: =IF(COUNTIF('Iteration 1 - Forward'!A:A, A11) > 0, 1, 0) -> 0 | H11: =IF(COUNTIF('Iteration 1 - Backward'!A:A, A11) > 0, 1, 0) -> 0 | I11: =IF(COUNTIF('Iteration 2 - Forward-Forward'!A:A, A11) > 0, 1, 0) -> 0 | J11: =IF(COUNTIF('Iteration 2 - Forward-Backward'!A:A, A11) > 0, 1, 0) -> 0 | K11: 1
A12: Performance evaluation of 5G radio configurations for industry 4.0 | B12: M. Mhedhbi, M. Morcos, A. Galindo-Serrano, S. E. Elayoubi | C12: 2019 | D12: International Conference on Wireless and Mobile Computing, Networking and Communications (WiMob) | E12: =--(ROW(A12)<>MATCH(A12,$A:$A,0)) -> 0 | F12: =IF(COUNTIF('Start Set'!A:A, A12) > 0, 1, 0) -> 0 | G12: =IF(COUNTIF('Iteration 1 - Forward'!A:A, A12) > 0, 1, 0) -> 0 | H12: =IF(COUNTIF('Iteration 1 - Backward'!A:A, A12) > 0, 1, 0) -> 0 | I12: =IF(COUNTIF('Iteration 2 - Forward-Forward'!A:A, A12) > 0, 1, 0) -> 0 | J12: =IF(COUNTIF('Iteration 2 - Forward-Backward'!A:A, A12) > 0, 1, 0) -> 0 | K12: 1
A13: Indoor Industrial Channel Model Calibration Results | B13: 3GPP | C13: 2019 | D13: TR R1-1909704 | E13: =--(ROW(A13)<>MATCH(A13,$A:$A,0)) -> 0 | F13: =IF(COUNTIF('Start Set'!A:A, A13) > 0, 1, 0) -> 0 | G13: =IF(COUNTIF('Iteration 1 - Forward'!A:A, A13) > 0, 1, 0) -> 0 | H13: =IF(COUNTIF('Iteration 1 - Backward'!A:A, A13) > 0, 1, 0) -> 0 | I13: =IF(COUNTIF('Iteration 2 - Forward-Forward'!A:A, A13) > 0, 1, 0) -> 0 | J13: =IF(COUNTIF('Iteration 2 - Forward-Backward'!A:A, A13) > 0, 1, 0) -> 0 | K13: 1
... A15: Study on Self Evaluation Towards IMT-2020 Submission (Release 16) | B15: 3GPP | C15: 2019 | D15: TR 37.910 V16.1.0 | E15: =--(ROW(A15)<>MATCH(A15,$A:$A,0)) -> 0 | F15: =IF(COUNTIF('Start Set'!A:A, A15) > 0, 1, 0) -> 0 | G15: =IF(COUNTIF('Iteration 1 - Forward'!A:A, A15) > 0, 1, 0) -> 0 | H15: =IF(COUNTIF('Iteration 1 - Backward'!A:A, A15) > 0, 1, 0) -> 0 | I15: =IF(COUNTIF('Iteration 2 - Forward-Forward'!A:A, A15) > 0, 1, 0) -> 0 | J15: =IF(COUNTIF('Iteration 2 - Forward-Backward'!A:A, A15) > 0, 1, 0) -> 0 | K15: 1
A16: NR; NR and NG-RAN Overall Description; Stage-2 (Release 16) | B16: 3GPP | C16: 2020 | D16: TR 38.300 V16.4.0 | E16: =--(ROW(A16)<>MATCH(A16,$A:$A,0)) -> 0 | F16: =IF(COUNTIF('Start Set'!A:A, A16) > 0, 1, 0) -> 0 | G16: =IF(COUNTIF('Iteration 1 - Forward'!A:A, A16) > 0, 1, 0) -> 0 | H16: =IF(COUNTIF('Iteration 1 - Backward'!A:A, A16) > 0, 1, 0) -> 0 | I16: =IF(COUNTIF('Iteration 2 - Forward-Forward'!A:A, A16) > 0, 1, 0) -> 0 | J16: =IF(COUNTIF('Iteration 2 - Forward-Backward'!A:A, A16) > 0, 1, 0) -> 0 | L16: 1
A17: Study on Channel Model for Frequencies From 0.5 to 100 GHz (Release 16) | B17: 3GPP | C17: 2020 | D17: TR 38.901 V16.1.0 | E17: =--(ROW(A17)<>MATCH(A17,$A:$A,0)) -> 0 | F17: =IF(COUNTIF('Start Set'!A:A, A17) > 0, 1, 0) -> 0 | G17: =IF(COUNTIF('Iteration 1 - Forward'!A:A, A17) > 0, 1, 0) -> 0 | H17: =IF(COUNTIF('Iteration 1 - Backward'!A:A, A17) > 0, 1, 0) -> 0 | I17: =IF(COUNTIF('Iteration 2 - Forward-Forward'!A:A, A17) > 0, 1, 0) -> 0 | J17: =IF(COUNTIF('Iteration 2 - Forward-Backward'!A:A, A17) > 0, 1, 0) -> 0 | L17: 1
A18: NR; Physical Layer Procedures for Data (Release 16) | B18: 3GPP | C18: 2021 | D18: TR 38.214 V16.4.0 | E18: =--(ROW(A18)<>MATCH(A18,$A:$A,0)) -> 0 | F18: =IF(COUNTIF('Start Set'!A:A, A18) > 0, 1, 0) -> 0 | G18: =IF(COUNTIF('Iteration 1 - Forward'!A:A, A18) > 0, 1, 0) -> 0 | H18: =IF(COUNTIF('Iteration 1 - Backward'!A:A, A18) > 0, 1, 0) -> 0 | I18: =IF(COUNTIF('Iteration 2 - Forward-Forward'!A:A, A18) > 0, 1, 0) -> 0 | J18: =IF(COUNTIF('Iteration 2 - Forward-Backward'!A:A, A18) > 0, 1, 0) -> 0 | L18: 1
A19: MQTT Protocol | B19: MQTT.org | C19: 2020 | E19: =--(ROW(A19)<>MATCH(A19,$A:$A,0)) -> 0 | F19: =IF(COUNTIF('Start Set'!A:A, A19) > 0, 1, 0) -> 0 | G19: =IF(COUNTIF('Iteration 1 - Forward'!A:A, A19) > 0, 1, 0) -> 0 | H19: =IF(COUNTIF('Iteration 1 - Backward'!A:A, A19) > 0, 1, 0) -> 0 | I19: =IF(COUNTIF('Iteration 2 - Forward-Forward'!A:A, A19) > 0, 1, 0) -> 0 | J19: =IF(COUNTIF('Iteration 2 - Forward-Backward'!A:A, A19) > 0, 1, 0) -> 0 | L19: 1
A20: Decision-theoretic recursive modeling and the coordinated attack problem | B20: P. Gmytrasiewicz, E. Durfee | C20: 1992 | D20: International Conference on Artificial Intelligence Planning Systems | E20: =--(ROW(A20)<>MATCH(A20,$A:$A,0)) -> 0 | F20: =IF(COUNTIF('Start Set'!A:A, A20) > 0, 1, 0) -> 0 | G20: =IF(COUNTIF('Iteration 1 - Forward'!A:A, A20) > 0, 1, 0) -> 0 | H20: =IF(COUNTIF('Iteration 1 - Backward'!A:A, A20) > 0, 1, 0) -> 0 | I20: =IF(COUNTIF('Iteration 2 - Forward-Forward'!A:A, A20) > 0, 1, 0) -> 0 | J20: =IF(COUNTIF('Iteration 2 - Forward-Backward'!A:A, A20) > 0, 1, 0) -> 0 | K20: 1
A21: A Survey on Mobility Management in Next Generation All-IP Based Wireless Systems | B21: I. Akyildiz, J. Xie, S. Mohanty | C21: 2004 | D21: IEEE Wireless Communications | E21: =--(ROW(A21)<>MATCH(A21,$A:$A,0)) -> 0 | F21: =IF(COUNTIF('Start Set'!A:A, A21) > 0, 1, 0) -> 0 | G21: =IF(COUNTIF('Iteration 1 - Forward'!A:A, A21) > 0, 1, 0) -> 0 | H21: =IF(COUNTIF('Iteration 1 - Backward'!A:A, A21) > 0, 1, 0) -> 0 | I21: =IF(COUNTIF('Iteration 2 - Forward-Forward'!A:A, A21) > 0, 1, 0) -> 0 | J21: =IF(COUNTIF('Iteration 2 - Forward-Backward'!A:A, A21) > 0, 1, 0) -> 0 | K21: 1
A22: RFID security and privacy: A research survey | B22: A. Juels | C22: 2006 | D22: IEEE Journal on Selected Areas in Communications | E22: =--(ROW(A22)<>MATCH(A22,$A:$A,0)) -> 0 | F22: =IF(COUNTIF('Start Set'!A:A, A22) > 0, 1, 0) -> 0 | G22: =IF(COUNTIF('Iteration 1 - Forward'!A:A, A22) > 0, 1, 0) -> 0 | H22: =IF(COUNTIF('Iteration 1 - Backward'!A:A, A22) > 0, 1, 0) -> 0 | I22: =IF(COUNTIF('Iteration 2 - Forward-Forward'!A:A, A22) > 0, 1, 0) -> 0 | J22: =IF(COUNTIF('Iteration 2 - Forward-Backward'!A:A, A22) > 0, 1, 0) -> 0 | K22: 1
A23: IPv6 Over Low-Power Wireless Personal Area Networks (6LoWPANs): Overview, Assumptions, Problem Statement, and Goals | B23: N. Kushalnagar, G. Montenegro, C. Schumacher | C23: 2007 | D23: RFC 4919 | E23: =--(ROW(A23)<>MATCH(A23,$A:$A,0)) -> 0 | F23: =IF(COUNTIF('Start Set'!A:A, A23) > 0, 1, 0) -> 0 | G23: =IF(COUNTIF('Iteration 1 - Forward'!A:A, A23) > 0, 1, 0) -> 0 | H23: =IF(COUNTIF('Iteration 1 - Backward'!A:A, A23) > 0, 1, 0) -> 0 | I23: =IF(COUNTIF('Iteration 2 - Forward-Forward'!A:A, A23) > 0, 1, 0) -> 0 | J23: =IF(COUNTIF('Iteration 2 - Forward-Backward'!A:A, A23) > 0, 1, 0) -> 0 | K23: 1
A24: Transmission of IPv6 packets over IEEE 802.15.4 Networks | B24: G. Montenegro, N. Kushalnagar, J. Hui, D. C. Muller | C24: 2007 | D24: RFC 4944 | E24: =--(ROW(A24)<>MATCH(A24,$A:$A,0)) -> 0 | F24: =IF(COUNTIF('Start Set'!A:A, A24) > 0, 1, 0) -> 0 | G24: =IF(COUNTIF('Iteration 1 - Forward'!A:A, A24) > 0, 1, 0) -> 0 | H24: =IF(COUNTIF('Iteration 1 - Backward'!A:A, A24) > 0, 1, 0) -> 0 | I24: =IF(COUNTIF('Iteration 2 - Forward-Forward'!A:A, A24) > 0, 1, 0) -> 0 | J24: =IF(COUNTIF('Iteration 2 - Forward-Backward'!A:A, A24) > 0, 1, 0) -> 0 | K24: 1
A25: XMPP: The Definitive Guide: Building Real-Time Applications with Jabber Technologies | B25: P. Saint-Andre, K. Smith, R. Tronçon | C25: 2009 | D25: O’Reilly Media | E25: =--(ROW(A25)<>MATCH(A25,$A:$A,0)) -> 0 | F25: =IF(COUNTIF('Start Set'!A:A, A25) > 0, 1, 0) -> 0 | G25: =IF(COUNTIF('Iteration 1 - Forward'!A:A, A25) > 0, 1, 0) -> 0 | H25: =IF(COUNTIF('Iteration 1 - Backward'!A:A, A25) > 0, 1, 0) -> 0 | I25: =IF(COUNTIF('Iteration 2 - Forward-Forward'!A:A, A25) > 0, 1, 0) -> 0 | J25: =IF(COUNTIF('Iteration 2 - Forward-Backward'!A:A, A25) > 0, 1, 0) -> 0 | K25: 1
A26: 6LoWPAN: Incorporating IEEE 802.15.4 into the IP Architecture | B26: J. Hui, D. Culler, S. Chakrabarti | C26: 2009 | D26: IPSO Alliance White Paper | E26: =--(ROW(A26)<>MATCH(A26,$A:$A,0)) -> 0 | F26: =IF(COUNTIF('Start Set'!A:A, A26) > 0, 1, 0) -> 0 | G26: =IF(COUNTIF('Iteration 1 - Forward'!A:A, A26) > 0, 1, 0) -> 0 | H26: =IF(COUNTIF('Iteration 1 - Backward'!A:A, A26) > 0, 1, 0) -> 0 | I26: =IF(COUNTIF('Iteration 2 - Forward-Forward'!A:A, A26) > 0, 1, 0) -> 0 | J26: =IF(COUNTIF('Iteration 2 - Forward-Backward'!A:A, A26) > 0, 1, 0) -> 0 | K26: 1
A27: A survey of the Internet of Things | B27: D. Yang, F. Liu, Y. Liang | C27: 2010 | D27: International Conference on E-Business and Intelligence | E27: =--(ROW(A27)<>MATCH(A27,$A:$A,0)) -> 0 | F27: =IF(COUNTIF('Start Set'!A:A, A27) > 0, 1, 0) -> 0 | G27: =IF(COUNTIF('Iteration 1 - Forward'!A:A, A27) > 0, 1, 0) -> 0 | H27: =IF(COUNTIF('Iteration 1 - Backward'!A:A, A27) > 0, 1, 0) -> 0 | I27: =IF(COUNTIF('Iteration 2 - Forward-Forward'!A:A, A27) > 0, 1, 0) -> 0 | J27: =IF(COUNTIF('Iteration 2 - Forward-Backward'!A:A, A27) > 0, 1, 0) -> 0 | K27: 1
A28: Services and key technologies of the Internet of Things | B28: X. Xiaojiang, W. Jianli, L. Mingdong | C28: 2010 | D28: ZTE Communications | E28: =--(ROW(A28)<>MATCH(A28,$A:$A,0)) -> 0 | F28: =IF(COUNTIF('Start Set'!A:A, A28) > 0, 1, 0) -> 0 | G28: =IF(COUNTIF('Iteration 1 - Forward'!A:A, A28) > 0, 1, 0) -> 0 | H28: =IF(COUNTIF('Iteration 1 - Backward'!A:A, A28) > 0, 1, 0) -> 0 | I28: =IF(COUNTIF('Iteration 2 - Forward-Forward'!A:A, A28) > 0, 1, 0) -> 0 | J28: =IF(COUNTIF('Iteration 2 - Forward-Backward'!A:A, A28) > 0, 1, 0) -> 0 | K28: 1
A29: Future research challenges in wireless sensor and actuator networks targeting industrial automation | B29: J. Akerberg, M. Gidlund, M. Bjorkman | C29: 2011 | D29: IEEE International Conference on Industrial Informatics | E29: =--(ROW(A29)<>MATCH(A29,$A:$A,0)) -> 0 | F29: =IF(COUNTIF('Start Set'!A:A, A29) > 0, 1, 0) -> 0 | G29: =IF(COUNTIF('Iteration 1 - Forward'!A:A, A29) > 0, 1, 0) -> 0 | H29: =IF(COUNTIF('Iteration 1 - Backward'!A:A, A29) > 0, 1, 0) -> 1 | I29: =IF(COUNTIF('Iteration 2 - Forward-Forward'!A:A, A29) > 0, 1, 0) -> 0 | J29: =IF(COUNTIF('Iteration 2 - Forward-Backward'!A:A, A29) > 0, 1, 0) -> 0 | K29: 1
A30: IEEE Standard for Utility Industry Metering Communication Protocol Application Layer (End Device Data Tables) | B30: IEEE | C30: 2012 | D30: IEEE Std 1377-2012 | E30: =--(ROW(A30)<>MATCH(A30,$A:$A,0)) -> 0 | F30: =IF(COUNTIF('Start Set'!A:A, A30) > 0, 1, 0) -> 0 | G30: =IF(COUNTIF('Iteration 1 - Forward'!A:A, A30) > 0, 1, 0) -> 0 | H30: =IF(COUNTIF('Iteration 1 - Backward'!A:A, A30) > 0, 1, 0) -> 0 | I30: =IF(COUNTIF('Iteration 2 - Forward-Forward'!A:A, A30) > 0, 1, 0) -> 0 | J30: =IF(COUNTIF('Iteration 2 - Forward-Backward'!A:A, A30) > 0, 1, 0) -> 0 | K30: 1
A31: Future Internet: The Internet of Things architecture, possible applications and key challenges | B31: R. Khan, S. U. Khan, R. Zaheer, S. Khan | C31: 2012 | D31: International Conference on Frontiers of Information Technology | E31: =--(ROW(A31)<>MATCH(A31,$A:$A,0)) -> 0 | F31: =IF(COUNTIF('Start Set'!A:A, A31) > 0, 1, 0) -> 0 | G31: =IF(COUNTIF('Iteration 1 - Forward'!A:A, A31) > 0, 1, 0) -> 0 | H31: =IF(COUNTIF('Iteration 1 - Backward'!A:A, A31) > 0, 1, 0) -> 0 | I31: =IF(COUNTIF('Iteration 2 - Forward-Forward'!A:A, A31) > 0, 1, 0) -> 0 | J31: =IF(COUNTIF('Iteration 2 - Forward-Backward'!A:A, A31) > 0, 1, 0) -> 0 | K31: 1
... A71: A systematic review of IoT communication strategies for an efficient smart environment | B71: A. Souri, A. Hussien, M. Hoseyninezhad, M. Norouzi | C71: 2019 | D71: Transactions on Emerging Telecommunications Technologies | E71: =--(ROW(A71)<>MATCH(A71,$A:$A,0)) -> 0 | F71: =IF(COUNTIF('Start Set'!A:A, A71) > 0, 1, 0) -> 0 | G71: =IF(COUNTIF('Iteration 1 - Forward'!A:A, A71) > 0, 1, 0) -> 0 | H71: =IF(COUNTIF('Iteration 1 - Backward'!A:A, A71) > 0, 1, 0) -> 0 | I71: =IF(COUNTIF('Iteration 2 - Forward-Forward'!A:A, A71) > 0, 1, 0) -> 0 | J71: =IF(COUNTIF('Iteration 2 - Forward-Backward'!A:A, A71) > 0, 1, 0) -> 0 | K71: 1
A72: 2019 IoT Developer Survey | B72: Eclipse Foundation | C72: 2019 | E72: =--(ROW(A72)<>MATCH(A72,$A:$A,0)) -> 0 | F72: =IF(COUNTIF('Start Set'!A:A, A72) > 0, 1, 0) -> 0 | G72: =IF(COUNTIF('Iteration 1 - Forward'!A:A, A72) > 0, 1, 0) -> 0 | H72: =IF(COUNTIF('Iteration 1 - Backward'!A:A, A72) > 0, 1, 0) -> 0 | I72: =IF(COUNTIF('Iteration 2 - Forward-Forward'!A:A, A72) > 0, 1, 0) -> 0 | J72: =IF(COUNTIF('Iteration 2 - Forward-Backward'!A:A, A72) > 0, 1, 0) -> 0 | K72: 1
A73: Open Systems Interconnection (OSI) Standard (35.100) | B73: International Organization for Standardization (ISO) | C73: 2020 | E73: =--(ROW(A73)<>MATCH(A73,$A:$A,0)) -> 0 | F73: =IF(COUNTIF('Start Set'!A:A, A73) > 0, 1, 0) -> 0 | G73: =IF(COUNTIF('Iteration 1 - Forward'!A:A, A73) > 0, 1, 0) -> 0 | H73: =IF(COUNTIF('Iteration 1 - Backward'!A:A, A73) > 0, 1, 0) -> 0 | I73: =IF(COUNTIF('Iteration 2 - Forward-Forward'!A:A, A73) > 0, 1, 0) -> 0 | J73: =IF(COUNTIF('Iteration 2 - Forward-Backward'!A:A, A73) > 0, 1, 0) -> 0 | L73: 1
A74: Hypertext Transfer Protocol (HTTP) | B74: The Internet Society | C74: 2020 | E74: =--(ROW(A74)<>MATCH(A74,$A:$A,0)) -> 0 | F74: =IF(COUNTIF('Start Set'!A:A, A74) > 0, 1, 0) -> 0 | G74: =IF(COUNTIF('Iteration 1 - Forward'!A:A, A74) > 0, 1, 0) -> 0 | H74: =IF(COUNTIF('Iteration 1 - Backward'!A:A, A74) > 0, 1, 0) -> 0 | I74: =IF(COUNTIF('Iteration 2 - Forward-Forward'!A:A, A74) > 0, 1, 0) -> 0 | J74: =IF(COUNTIF('Iteration 2 - Forward-Backward'!A:A, A74) > 0, 1, 0) -> 0 | L74: 1
A75: HTTP version 3.0 (H3) IETF Draft | B75: IETF | C75: 2020 | E75: =--(ROW(A75)<>MATCH(A75,$A:$A,0)) -> 0 | F75: =IF(COUNTIF('Start Set'!A:A, A75) > 0, 1, 0) -> 0 | G75: =IF(COUNTIF('Iteration 1 - Forward'!A:A, A75) > 0, 1, 0) -> 0 | H75: =IF(COUNTIF('Iteration 1 - Backward'!A:A, A75) > 0, 1, 0) -> 0 | I75: =IF(COUNTIF('Iteration 2 - Forward-Forward'!A:A, A75) > 0, 1, 0) -> 0 | J75: =IF(COUNTIF('Iteration 2 - Forward-Backward'!A:A, A75) > 0, 1, 0) -> 0 | L75: 1
A76: Constrained Application Protocol (CoAP) Standard | B76: IETF | C76: 2020 | E76: =--(ROW(A76)<>MATCH(A76,$A:$A,0)) -> 0 | F76: =IF(COUNTIF('Start Set'!A:A, A76) > 0, 1, 0) -> 0 | G76: =IF(COUNTIF('Iteration 1 - Forward'!A:A, A76) > 0, 1, 0) -> 0 | H76: =IF(COUNTIF('Iteration 1 - Backward'!A:A, A76) > 0, 1, 0) -> 0 | I76: =IF(COUNTIF('Iteration 2 - Forward-Forward'!A:A, A76) > 0, 1, 0) -> 0 | J76: =IF(COUNTIF('Iteration 2 - Forward-Backward'!A:A, A76) > 0, 1, 0) -> 0 | L76: 1
A77: Message Queue Telemetry Transport (MQTT) | B77: OASIS | C77: 2020 | E77: =--(ROW(A77)<>MATCH(A77,$A:$A,0)) -> 0 | F77: =IF(COUNTIF('Start Set'!A:A, A77) > 0, 1, 0) -> 0 | G77: =IF(COUNTIF('Iteration 1 - Forward'!A:A, A77) > 0, 1, 0) -> 0 | H77: =IF(COUNTIF('Iteration 1 - Backward'!A:A, A77) > 0, 1, 0) -> 0 | I77: =IF(COUNTIF('Iteration 2 - Forward-Forward'!A:A, A77) > 0, 1, 0) -> 0 | J77: =IF(COUNTIF('Iteration 2 - Forward-Backward'!A:A, A77) > 0, 1, 0) -> 0 | L77: 1
A78: IBM Watson IoT Platform | B78: IBM | C78: 2020 | E78: =--(ROW(A78)<>MATCH(A78,$A:$A,0)) -> 0 | F78: =IF(COUNTIF('Start Set'!A:A, A78) > 0, 1, 0) -> 0 | G78: =IF(COUNTIF('Iteration 1 - Forward'!A:A, A78) > 0, 1, 0) -> 0 | H78: =IF(COUNTIF('Iteration 1 - Backward'!A:A, A78) > 0, 1, 0) -> 0 | I78: =IF(COUNTIF('Iteration 2 - Forward-Forward'!A:A, A78) > 0, 1, 0) -> 0 | J78: =IF(COUNTIF('Iteration 2 - Forward-Backward'!A:A, A78) > 0, 1, 0) -> 0 | L78: 1
A79: Microsoft Azure IoT Hub | B79: Microsoft | C79: 2020 | E79: =--(ROW(A79)<>MATCH(A79,$A:$A,0)) -> 0 | F79: =IF(COUNTIF('Start Set'!A:A, A79) > 0, 1, 0) -> 0 | G79: =IF(COUNTIF('Iteration 1 - Forward'!A:A, A79) > 0, 1, 0) -> 0 | H79: =IF(COUNTIF('Iteration 1 - Backward'!A:A, A79) > 0, 1, 0) -> 0 | I79: =IF(COUNTIF('Iteration 2 - Forward-Forward'!A:A, A79) > 0, 1, 0) -> 0 | J79: =IF(COUNTIF('Iteration 2 - Forward-Backward'!A:A, A79) > 0, 1, 0) -> 0 | L79: 1
A80: Google Cloud IoT Core | B80: Google | C80: 2020 | E80: =--(ROW(A80)<>MATCH(A80,$A:$A,0)) -> 0 | F80: =IF(COUNTIF('Start Set'!A:A, A80) > 0, 1, 0) -> 0 | G80: =IF(COUNTIF('Iteration 1 - Forward'!A:A, A80) > 0, 1, 0) -> 0 | H80: =IF(COUNTIF('Iteration 1 - Backward'!A:A, A80) > 0, 1, 0) -> 0 | I80: =IF(COUNTIF('Iteration 2 - Forward-Forward'!A:A, A80) > 0, 1, 0) -> 0 | J80: =IF(COUNTIF('Iteration 2 - Forward-Backward'!A:A, A80) > 0, 1, 0) -> 0 | L80: 1
A81: Bosch IoT Hub | B81: Bosch | C81: 2020 | E81: =--(ROW(A81)<>MATCH(A81,$A:$A,0)) -> 0 | F81: =IF(COUNTIF('Start Set'!A:A, A81) > 0, 1, 0) -> 0 | G81: =IF(COUNTIF('Iteration 1 - Forward'!A:A, A81) > 0, 1, 0) -> 0 | H81: =IF(COUNTIF('Iteration 1 - Backward'!A:A, A81) > 0, 1, 0) -> 0 | I81: =IF(COUNTIF('Iteration 2 - Forward-Forward'!A:A, A81) > 0, 1, 0) -> 0 | J81: =IF(COUNTIF('Iteration 2 - Forward-Backward'!A:A, A81) > 0, 1, 0) -> 0 | L81: 1
A82: AWS IoT | B82: Amazon Web Services | C82: 2020 | E82: =--(ROW(A82)<>MATCH(A82,$A:$A,0)) -> 0 | F82: =IF(COUNTIF('Start Set'!A:A, A82) > 0, 1, 0) -> 0 | G82: =IF(COUNTIF('Iteration 1 - Forward'!A:A, A82) > 0, 1, 0) -> 0 | H82: =IF(COUNTIF('Iteration 1 - Backward'!A:A, A82) > 0, 1, 0) -> 0 | I82: =IF(COUNTIF('Iteration 2 - Forward-Forward'!A:A, A82) > 0, 1, 0) -> 0 | J82: =IF(COUNTIF('Iteration 2 - Forward-Backward'!A:A, A82) > 0, 1, 0) -> 0 | L82: 1
A83: IoTivity | B83: IoTivity | C83: 2020 | E83: =--(ROW(A83)<>MATCH(A83,$A:$A,0)) -> 0 | F83: =IF(COUNTIF('Start Set'!A:A, A83) > 0, 1, 0) -> 0 | G83: =IF(COUNTIF('Iteration 1 - Forward'!A:A, A83) > 0, 1, 0) -> 0 | H83: =IF(COUNTIF('Iteration 1 - Backward'!A:A, A83) > 0, 1, 0) -> 0 | I83: =IF(COUNTIF('Iteration 2 - Forward-Forward'!A:A, A83) > 0, 1, 0) -> 0 | J83: =IF(COUNTIF('Iteration 2 - Forward-Backward'!A:A, A83) > 0, 1, 0) -> 0 | L83: 1
A84: OMG Data-Distribution Service for Real-Time Systems (DDS) | B84: OMG | C84: 2020 | E84: =--(ROW(A84)<>MATCH(A84,$A:$A,0)) -> 0 | F84: =IF(COUNTIF('Start Set'!A:A, A84) > 0, 1, 0) -> 0 | G84: =IF(COUNTIF('Iteration 1 - Forward'!A:A, A84) > 0, 1, 0) -> 0 | H84: =IF(COUNTIF('Iteration 1 - Backward'!A:A, A84) > 0, 1, 0) -> 0 | I84: =IF(COUNTIF('Iteration 2 - Forward-Forward'!A:A, A84) > 0, 1, 0) -> 0 | J84: =IF(COUNTIF('Iteration 2 - Forward-Backward'!A:A, A84) > 0, 1, 0) -> 0 | L84: 1
... A150: RTI TypeObject | B150: RTI | C150: 2020 | E150: =--(ROW(A150)<>MATCH(A150,$A:$A,0)) -> 0 | F150: =IF(COUNTIF('Start Set'!A:A, A150) > 0, 1, 0) -> 0 | G150: =IF(COUNTIF('Iteration 1 - Forward'!A:A, A150) > 0, 1, 0) -> 0 | H150: =IF(COUNTIF('Iteration 1 - Backward'!A:A, A150) > 0, 1, 0) -> 0 | I150: =IF(COUNTIF('Iteration 2 - Forward-Forward'!A:A, A150) > 0, 1, 0) -> 0 | J150: =IF(COUNTIF('Iteration 2 - Forward-Backward'!A:A, A150) > 0, 1, 0) -> 0 | L150: 1
A151: CoAP-Lite | C151: 2020 | E151: =--(ROW(A151)<>MATCH(A151,$A:$A,0)) -> 0 | F151: =IF(COUNTIF('Start Set'!A:A, A151) > 0, 1, 0) -> 0 | G151: =IF(COUNTIF('Iteration 1 - Forward'!A:A, A151) > 0, 1, 0) -> 0 | H151: =IF(COUNTIF('Iteration 1 - Backward'!A:A, A151) > 0, 1, 0) -> 0 | I151: =IF(COUNTIF('Iteration 2 - Forward-Forward'!A:A, A151) > 0, 1, 0) -> 0 | J151: =IF(COUNTIF('Iteration 2 - Forward-Backward'!A:A, A151) > 0, 1, 0) -> 0 | L151: 1
A152: Red Hat Enterprise MRG | B152: Red Hat | C152: 2020 | E152: =--(ROW(A152)<>MATCH(A152,$A:$A,0)) -> 0 | F152: =IF(COUNTIF('Start Set'!A:A, A152) > 0, 1, 0) -> 0 | G152: =IF(COUNTIF('Iteration 1 - Forward'!A:A, A152) > 0, 1, 0) -> 0 | H152: =IF(COUNTIF('Iteration 1 - Backward'!A:A, A152) > 0, 1, 0) -> 0 | I152: =IF(COUNTIF('Iteration 2 - Forward-Forward'!A:A, A152) > 0, 1, 0) -> 0 | J152: =IF(COUNTIF('Iteration 2 - Forward-Backward'!A:A, A152) > 0, 1, 0) -> 0 | L152: 1
A153: OpenMQ | B153: OpenAMQ | C153: 2020 | E153: =--(ROW(A153)<>MATCH(A153,$A:$A,0)) -> 0 | F153: =IF(COUNTIF('Start Set'!A:A, A153) > 0, 1, 0) -> 0 | G153: =IF(COUNTIF('Iteration 1 - Forward'!A:A, A153) > 0, 1, 0) -> 0 | H153: =IF(COUNTIF('Iteration 1 - Backward'!A:A, A153) > 0, 1, 0) -> 0 | I153: =IF(COUNTIF('Iteration 2 - Forward-Forward'!A:A, A153) > 0, 1, 0) -> 0 | J153: =IF(COUNTIF('Iteration 2 - Forward-Backward'!A:A, A153) > 0, 1, 0) -> 0 | L153: 1
A154: XEP-0076: Malicious Stanzas | B154: XMPP Standards Foundation | C154: 2020 | E154: =--(ROW(A154)<>MATCH(A154,$A:$A,0)) -> 0 | F154: =IF(COUNTIF('Start Set'!A:A, A154) > 0, 1, 0) -> 0 | G154: =IF(COUNTIF('Iteration 1 - Forward'!A:A, A154) > 0, 1, 0) -> 0 | H154: =IF(COUNTIF('Iteration 1 - Backward'!A:A, A154) > 0, 1, 0) -> 0 | I154: =IF(COUNTIF('Iteration 2 - Forward-Forward'!A:A, A154) > 0, 1, 0) -> 0 | J154: =IF(COUNTIF('Iteration 2 - Forward-Backward'!A:A, A154) > 0, 1, 0) -> 0 | L154: 1
A155: XEP-0030: Service Discovery | B155: XMPP Standards Foundation | C155: 2020 | E155: =--(ROW(A155)<>MATCH(A155,$A:$A,0)) -> 0 | F155: =IF(COUNTIF('Start Set'!A:A, A155) > 0, 1, 0) -> 0 | G155: =IF(COUNTIF('Iteration 1 - Forward'!A:A, A155) > 0, 1, 0) -> 0 | H155: =IF(COUNTIF('Iteration 1 - Backward'!A:A, A155) > 0, 1, 0) -> 0 | I155: =IF(COUNTIF('Iteration 2 - Forward-Forward'!A:A, A155) > 0, 1, 0) -> 0 | J155: =IF(COUNTIF('Iteration 2 - Forward-Backward'!A:A, A155) > 0, 1, 0) -> 0 | L155: 1
A156: XEP-0080: User Location | B156: XMPP Standards Foundation | C156: 2020 | E156: =--(ROW(A156)<>MATCH(A156,$A:$A,0)) -> 0 | F156: =IF(COUNTIF('Start Set'!A:A, A156) > 0, 1, 0) -> 0 | G156: =IF(COUNTIF('Iteration 1 - Forward'!A:A, A156) > 0, 1, 0) -> 0 | H156: =IF(COUNTIF('Iteration 1 - Backward'!A:A, A156) > 0, 1, 0) -> 0 | I156: =IF(COUNTIF('Iteration 2 - Forward-Forward'!A:A, A156) > 0, 1, 0) -> 0 | J156: =IF(COUNTIF('Iteration 2 - Forward-Backward'!A:A, A156) > 0, 1, 0) -> 0 | L156: 1
A157: Extensible and Dynamic Topic Types for DDS | B157: OMG | C157: 2020 | E157: =--(ROW(A157)<>MATCH(A157,$A:$A,0)) -> 0 | F157: =IF(COUNTIF('Start Set'!A:A, A157) > 0, 1, 0) -> 0 | G157: =IF(COUNTIF('Iteration 1 - Forward'!A:A, A157) > 0, 1, 0) -> 0 | H157: =IF(COUNTIF('Iteration 1 - Backward'!A:A, A157) > 0, 1, 0) -> 0 | I157: =IF(COUNTIF('Iteration 2 - Forward-Forward'!A:A, A157) > 0, 1, 0) -> 0 | J157: =IF(COUNTIF('Iteration 2 - Forward-Backward'!A:A, A157) > 0, 1, 0) -> 0 | L157: 1
A158: RabbitMQ: Per-Queue Message TTL in Queues | B158: RabbitMQ | C158: 2020 | E158: =--(ROW(A158)<>MATCH(A158,$A:$A,0)) -> 0 | F158: =IF(COUNTIF('Start Set'!A:A, A158) > 0, 1, 0) -> 0 | G158: =IF(COUNTIF('Iteration 1 - Forward'!A:A, A158) > 0, 1, 0) -> 0 | H158: =IF(COUNTIF('Iteration 1 - Backward'!A:A, A158) > 0, 1, 0) -> 0 | I158: =IF(COUNTIF('Iteration 2 - Forward-Forward'!A:A, A158) > 0, 1, 0) -> 0 | J158: =IF(COUNTIF('Iteration 2 - Forward-Backward'!A:A, A158) > 0, 1, 0) -> 0 | L158: 1
A159: DDS at Volkswagen | B159: RTI | C159: 2020 | E159: =--(ROW(A159)<>MATCH(A159,$A:$A,0)) -> 0 | F159: =IF(COUNTIF('Start Set'!A:A, A159) > 0, 1, 0) -> 0 | G159: =IF(COUNTIF('Iteration 1 - Forward'!A:A, A159) > 0, 1, 0) -> 0 | H159: =IF(COUNTIF('Iteration 1 - Backward'!A:A, A159) > 0, 1, 0) -> 0 | I159: =IF(COUNTIF('Iteration 2 - Forward-Forward'!A:A, A159) > 0, 1, 0) -> 0 | J159: =IF(COUNTIF('Iteration 2 - Forward-Backward'!A:A, A159) > 0, 1, 0) -> 0 | L159: 1
A160: Future of Automotive Industry | B160: RTI | C160: 2020 | E160: =--(ROW(A160)<>MATCH(A160,$A:$A,0)) -> 0 | F160: =IF(COUNTIF('Start Set'!A:A, A160) > 0, 1, 0) -> 0 | G160: =IF(COUNTIF('Iteration 1 - Forward'!A:A, A160) > 0, 1, 0) -> 0 | H160: =IF(COUNTIF('Iteration 1 - Backward'!A:A, A160) > 0, 1, 0) -> 0 | I160: =IF(COUNTIF('Iteration 2 - Forward-Forward'!A:A, A160) > 0, 1, 0) -> 0 | J160: =IF(COUNTIF('Iteration 2 - Forward-Backward'!A:A, A160) > 0, 1, 0) -> 0 | L160: 1
A161: DDS Security Library | B161: ARM | C161: 2020 | E161: =--(ROW(A161)<>MATCH(A161,$A:$A,0)) -> 0 | F161: =IF(COUNTIF('Start Set'!A:A, A161) > 0, 1, 0) -> 0 | G161: =IF(COUNTIF('Iteration 1 - Forward'!A:A, A161) > 0, 1, 0) -> 0 | H161: =IF(COUNTIF('Iteration 1 - Backward'!A:A, A161) > 0, 1, 0) -> 0 | I161: =IF(COUNTIF('Iteration 2 - Forward-Forward'!A:A, A161) > 0, 1, 0) -> 0 | J161: =IF(COUNTIF('Iteration 2 - Forward-Backward'!A:A, A161) > 0, 1, 0) -> 0 | L161: 1
A162: TrustZone | B162: Arm | C162: 2020 | E162: =--(ROW(A162)<>MATCH(A162,$A:$A,0)) -> 0 | F162: =IF(COUNTIF('Start Set'!A:A, A162) > 0, 1, 0) -> 0 | G162: =IF(COUNTIF('Iteration 1 - Forward'!A:A, A162) > 0, 1, 0) -> 0 | H162: =IF(COUNTIF('Iteration 1 - Backward'!A:A, A162) > 0, 1, 0) -> 0 | I162: =IF(COUNTIF('Iteration 2 - Forward-Forward'!A:A, A162) > 0, 1, 0) -> 0 | J162: =IF(COUNTIF('Iteration 2 - Forward-Backward'!A:A, A162) > 0, 1, 0) -> 0 | L162: 1
A163: XEP-0235: Authorization Tokens | B163: XMPP Standards Foundation | C163: 2020 | E163: =--(ROW(A163)<>MATCH(A163,$A:$A,0)) -> 0 | F163: =IF(COUNTIF('Start Set'!A:A, A163) > 0, 1, 0) -> 0 | G163: =IF(COUNTIF('Iteration 1 - Forward'!A:A, A163) > 0, 1, 0) -> 0 | H163: =IF(COUNTIF('Iteration 1 - Backward'!A:A, A163) > 0, 1, 0) -> 0 | I163: =IF(COUNTIF('Iteration 2 - Forward-Forward'!A:A, A163) > 0, 1, 0) -> 0 | J163: =IF(COUNTIF('Iteration 2 - Forward-Backward'!A:A, A163) > 0, 1, 0) -> 0 | L163: 1
... A170: Web of Things (WoT) Thing Description | B170: W3C | C170: 2020 | E170: =--(ROW(A170)<>MATCH(A170,$A:$A,0)) -> 0 | F170: =IF(COUNTIF('Start Set'!A:A, A170) > 0, 1, 0) -> 0 | G170: =IF(COUNTIF('Iteration 1 - Forward'!A:A, A170) > 0, 1, 0) -> 0 | H170: =IF(COUNTIF('Iteration 1 - Backward'!A:A, A170) > 0, 1, 0) -> 0 | I170: =IF(COUNTIF('Iteration 2 - Forward-Forward'!A:A, A170) > 0, 1, 0) -> 0 | J170: =IF(COUNTIF('Iteration 2 - Forward-Backward'!A:A, A170) > 0, 1, 0) -> 0 | L170: 1
A171: Concise Binary Object Representation (CBOR) | B171: IETF | C171: 2020 | D171: RFC 7049 | E171: =--(ROW(A171)<>MATCH(A171,$A:$A,0)) -> 0 | F171: =IF(COUNTIF('Start Set'!A:A, A171) > 0, 1, 0) -> 0 | G171: =IF(COUNTIF('Iteration 1 - Forward'!A:A, A171) > 0, 1, 0) -> 0 | H171: =IF(COUNTIF('Iteration 1 - Backward'!A:A, A171) > 0, 1, 0) -> 0 | I171: =IF(COUNTIF('Iteration 2 - Forward-Forward'!A:A, A171) > 0, 1, 0) -> 0 | J171: =IF(COUNTIF('Iteration 2 - Forward-Backward'!A:A, A171) > 0, 1, 0) -> 0 | L171: 1
A172: Concise Binary Object Representation (CBOR) | B172: R. Startin | C172: 2020 | D172: IETF | E172: =--(ROW(A172)<>MATCH(A172,$A:$A,0)) -> 1 | F172: =IF(COUNTIF('Start Set'!A:A, A172) > 0, 1, 0) -> 0 | G172: =IF(COUNTIF('Iteration 1 - Forward'!A:A, A172) > 0, 1, 0) -> 0 | H172: =IF(COUNTIF('Iteration 1 - Backward'!A:A, A172) > 0, 1, 0) -> 0 | I172: =IF(COUNTIF('Iteration 2 - Forward-Forward'!A:A, A172) > 0, 1, 0) -> 0 | J172: =IF(COUNTIF('Iteration 2 - Forward-Backward'!A:A, A172) > 0, 1, 0) -> 0 | L172: 1
A173: IoT Developer Surveys | B173: Eclipse Foundation | C173: 2020 | E173: =--(ROW(A173)<>MATCH(A173,$A:$A,0)) -> 0 | F173: =IF(COUNTIF('Start Set'!A:A, A173) > 0, 1, 0) -> 0 | G173: =IF(COUNTIF('Iteration 1 - Forward'!A:A, A173) > 0, 1, 0) -> 0 | H173: =IF(COUNTIF('Iteration 1 - Backward'!A:A, A173) > 0, 1, 0) -> 0 | I173: =IF(COUNTIF('Iteration 2 - Forward-Forward'!A:A, A173) > 0, 1, 0) -> 0 | J173: =IF(COUNTIF('Iteration 2 - Forward-Backward'!A:A, A173) > 0, 1, 0) -> 0 | L173: 1
A174: Multicast DNS (mDNS) | B174: IETF | C174: 2020 | E174: =--(ROW(A174)<>MATCH(A174,$A:$A,0)) -> 0 | F174: =IF(COUNTIF('Start Set'!A:A, A174) > 0, 1, 0) -> 0 | G174: =IF(COUNTIF('Iteration 1 - Forward'!A:A, A174) > 0, 1, 0) -> 0 | H174: =IF(COUNTIF('Iteration 1 - Backward'!A:A, A174) > 0, 1, 0) -> 0 | I174: =IF(COUNTIF('Iteration 2 - Forward-Forward'!A:A, A174) > 0, 1, 0) -> 0 | J174: =IF(COUNTIF('Iteration 2 - Forward-Backward'!A:A, A174) > 0, 1, 0) -> 0 | L174: 1
A175: DNS-Based Service Discovery | B175: IETF | C175: 2020 | E175: =--(ROW(A175)<>MATCH(A175,$A:$A,0)) -> 0 | F175: =IF(COUNTIF('Start Set'!A:A, A175) > 0, 1, 0) -> 0 | G175: =IF(COUNTIF('Iteration 1 - Forward'!A:A, A175) > 0, 1, 0) -> 0 | H175: =IF(COUNTIF('Iteration 1 - Backward'!A:A, A175) > 0, 1, 0) -> 0 | I175: =IF(COUNTIF('Iteration 2 - Forward-Forward'!A:A, A175) > 0, 1, 0) -> 0 | J175: =IF(COUNTIF('Iteration 2 - Forward-Backward'!A:A, A175) > 0, 1, 0) -> 0 | L175: 1
A176: Avahi | B176: Avahi | C176: 2020 | E176: =--(ROW(A176)<>MATCH(A176,$A:$A,0)) -> 0 | F176: =IF(COUNTIF('Start Set'!A:A, A176) > 0, 1, 0) -> 0 | G176: =IF(COUNTIF('Iteration 1 - Forward'!A:A, A176) > 0, 1, 0) -> 0 | H176: =IF(COUNTIF('Iteration 1 - Backward'!A:A, A176) > 0, 1, 0) -> 0 | I176: =IF(COUNTIF('Iteration 2 - Forward-Forward'!A:A, A176) > 0, 1, 0) -> 0 | J176: =IF(COUNTIF('Iteration 2 - Forward-Backward'!A:A, A176) > 0, 1, 0) -> 0 | L176: 1
A177: Apple Bonjour | B177: Apple | C177: 2020 | E177: =--(ROW(A177)<>MATCH(A177,$A:$A,0)) -> 0 | F177: =IF(COUNTIF('Start Set'!A:A, A177) > 0, 1, 0) -> 0 | G177: =IF(COUNTIF('Iteration 1 - Forward'!A:A, A177) > 0, 1, 0) -> 0 | H177: =IF(COUNTIF('Iteration 1 - Backward'!A:A, A177) > 0, 1, 0) -> 0 | I177: =IF(COUNTIF('Iteration 2 - Forward-Forward'!A:A, A177) > 0, 1, 0) -> 0 | J177: =IF(COUNTIF('Iteration 2 - Forward-Backward'!A:A, A177) > 0, 1, 0) -> 0 | L177: 1
A178: HyperCat (BSI) | B178: HyperCat | C178: 2020 | E178: =--(ROW(A178)<>MATCH(A178,$A:$A,0)) -> 0 | F178: =IF(COUNTIF('Start Set'!A:A, A178) > 0, 1, 0) -> 0 | G178: =IF(COUNTIF('Iteration 1 - Forward'!A:A, A178) > 0, 1, 0) -> 0 | H178: =IF(COUNTIF('Iteration 1 - Backward'!A:A, A178) > 0, 1, 0) -> 0 | I178: =IF(COUNTIF('Iteration 2 - Forward-Forward'!A:A, A178) > 0, 1, 0) -> 0 | J178: =IF(COUNTIF('Iteration 2 - Forward-Backward'!A:A, A178) > 0, 1, 0) -> 0 | L178: 1
A179: Physical Web | B179: Google | C179: 2020 | E179: =--(ROW(A179)<>MATCH(A179,$A:$A,0)) -> 0 | F179: =IF(COUNTIF('Start Set'!A:A, A179) > 0, 1, 0) -> 0 | G179: =IF(COUNTIF('Iteration 1 - Forward'!A:A, A179) > 0, 1, 0) -> 0 | H179: =IF(COUNTIF('Iteration 1 - Backward'!A:A, A179) > 0, 1, 0) -> 0 | I179: =IF(COUNTIF('Iteration 2 - Forward-Forward'!A:A, A179) > 0, 1, 0) -> 0 | J179: =IF(COUNTIF('Iteration 2 - Forward-Backward'!A:A, A179) > 0, 1, 0) -> 0 | L179: 1
A180: Universal Plug and Play (UPnP) | B180: IETF | C180: 2020 | E180: =--(ROW(A180)<>MATCH(A180,$A:$A,0)) -> 0 | F180: =IF(COUNTIF('Start Set'!A:A, A180) > 0, 1, 0) -> 0 | G180: =IF(COUNTIF('Iteration 1 - Forward'!A:A, A180) > 0, 1, 0) -> 0 | H180: =IF(COUNTIF('Iteration 1 - Backward'!A:A, A180) > 0, 1, 0) -> 0 | I180: =IF(COUNTIF('Iteration 2 - Forward-Forward'!A:A, A180) > 0, 1, 0) -> 0 | J180: =IF(COUNTIF('Iteration 2 - Forward-Backward'!A:A, A180) > 0, 1, 0) -> 0 | L180: 1
A181: Azure IoT Hub | B181: Microsoft | C181: 2020 | E181: =--(ROW(A181)<>MATCH(A181,$A:$A,0)) -> 0 | F181: =IF(COUNTIF('Start Set'!A:A, A181) > 0, 1, 0) -> 0 | G181: =IF(COUNTIF('Iteration 1 - Forward'!A:A, A181) > 0, 1, 0) -> 0 | H181: =IF(COUNTIF('Iteration 1 - Backward'!A:A, A181) > 0, 1, 0) -> 0 | I181: =IF(COUNTIF('Iteration 2 - Forward-Forward'!A:A, A181) > 0, 1, 0) -> 0 | J181: =IF(COUNTIF('Iteration 2 - Forward-Backward'!A:A, A181) > 0, 1, 0) -> 0 | L181: 1
A182: Google IoT Core | B182: Google | C182: 2020 | E182: =--(ROW(A182)<>MATCH(A182,$A:$A,0)) -> 0 | F182: =IF(COUNTIF('Start Set'!A:A, A182) > 0, 1, 0) -> 0 | G182: =IF(COUNTIF('Iteration 1 - Forward'!A:A, A182) > 0, 1, 0) -> 0 | H182: =IF(COUNTIF('Iteration 1 - Backward'!A:A, A182) > 0, 1, 0) -> 0 | I182: =IF(COUNTIF('Iteration 2 - Forward-Forward'!A:A, A182) > 0, 1, 0) -> 0 | J182: =IF(COUNTIF('Iteration 2 - Forward-Backward'!A:A, A182) > 0, 1, 0) -> 0 | L182: 1
A183: IBM Watson IoT Platform | B183: IBM | C183: 2020 | E183: =--(ROW(A183)<>MATCH(A183,$A:$A,0)) -> 1 | F183: =IF(COUNTIF('Start Set'!A:A, A183) > 0, 1, 0) -> 0 | G183: =IF(COUNTIF('Iteration 1 - Forward'!A:A, A183) > 0, 1, 0) -> 0 | H183: =IF(COUNTIF('Iteration 1 - Backward'!A:A, A183) > 0, 1, 0) -> 0 | I183: =IF(COUNTIF('Iteration 2 - Forward-Forward'!A:A, A183) > 0, 1, 0) -> 0 | J183: =IF(COUNTIF('Iteration 2 - Forward-Backward'!A:A, A183) > 0, 1, 0) -> 0 | L183: 1
A184: AWS IoT Core | B184: Amazon Web Services | C184: 2020 | E184: =--(ROW(A184)<>MATCH(A184,$A:$A,0)) -> 0 | F184: =IF(COUNTIF('Start Set'!A:A, A184) > 0, 1, 0) -> 0 | G184: =IF(COUNTIF('Iteration 1 - Forward'!A:A, A184) > 0, 1, 0) -> 0 | H184: =IF(COUNTIF('Iteration 1 - Backward'!A:A, A184) > 0, 1, 0) -> 0 | I184: =IF(COUNTIF('Iteration 2 - Forward-Forward'!A:A, A184) > 0, 1, 0) -> 0 | J184: =IF(COUNTIF('Iteration 2 - Forward-Backward'!A:A, A184) > 0, 1, 0) -> 0 | L184: 1
... A191: IoT 2020: Smart and Secure IoT Platform | B191: IEC | C191: 2020 | E191: =--(ROW(A191)<>MATCH(A191,$A:$A,0)) -> 0 | F191: =IF(COUNTIF('Start Set'!A:A, A191) > 0, 1, 0) -> 0 | G191: =IF(COUNTIF('Iteration 1 - Forward'!A:A, A191) > 0, 1, 0) -> 0 | H191: =IF(COUNTIF('Iteration 1 - Backward'!A:A, A191) > 0, 1, 0) -> 0 | I191: =IF(COUNTIF('Iteration 2 - Forward-Forward'!A:A, A191) > 0, 1, 0) -> 0 | J191: =IF(COUNTIF('Iteration 2 - Forward-Backward'!A:A, A191) > 0, 1, 0) -> 0 | L191: 1
A192: Advanced Message Queuing Protocol (AMQP) | B192: AMQP | E192: =--(ROW(A192)<>MATCH(A192,$A:$A,0)) -> 0 | F192: =IF(COUNTIF('Start Set'!A:A, A192) > 0, 1, 0) -> 0 | G192: =IF(COUNTIF('Iteration 1 - Forward'!A:A, A192) > 0, 1, 0) -> 0 | H192: =IF(COUNTIF('Iteration 1 - Backward'!A:A, A192) > 0, 1, 0) -> 0 | I192: =IF(COUNTIF('Iteration 2 - Forward-Forward'!A:A, A192) > 0, 1, 0) -> 0 | J192: =IF(COUNTIF('Iteration 2 - Forward-Backward'!A:A, A192) > 0, 1, 0) -> 0 | L192: 1
